Workbook

Sheet All
N1: 44592
A2: ល.រ | B2: Factory ID | C2: គោត្តនាម | D2: នាម | E2: គោត្តនាមឡាតាំង | F2: នាមឡាតាំង | G2: ភេទ | H2: ថ្ងៃខែឆ្នាំកំណើត | I2: កាលបរិ. ចូលធ្វើការ | J2: ផ្នែក | K2: ក្រុម | L2: តួនាទី | M2: Salary Report 2021 | U2: Adjust amount | V2: Adjust Date | W2: Evaluator | X2: 2022 Total Marks | Y2: With Comment | Z2: Salary Report 2022
A3: Nº | B3: Factory ID | C3: Khmer Sure name | D3: Khmer Name | E3: English Sure name | F3: Khmer Name | G3: Sex | H3: Birth of Date | I3: Join Date | J3: Department | K3: Group | L3: Position | M3: Basic | N3: Seniority | O3: Skill | P3: Position | Q3: Language | R3: Housing &Transportation | S3: Motivation | T3: Total | U3: 調動金額 | V3: 調動日期 | W3: 評核人 | X3: 2021總分 | Y3: 意見 | Z3: Basic | AA3: Seniority | AB3: Skill | AC3: Position | AD3: Language | AE3: Housing &Transportation | AF3: Motivation | AG3: Total
A4: =1 -> 1 | B4: 2168 | C4: យិន | D4: ផារី | E4: YIN | F4: PHARY | G4: F | H4: 32278 | I4: 43192 | J4: ADMINISTRATION | K4: HR | L4: Leader | T4: =SUM(M4:S4) -> 0 | Z4: =M4+2 -> 2 | AA4: =N4 -> 0 | AB4: =O4 -> 0 | AC4: =P4 -> 0 | AD4: =Q4 -> 0 | AE4: =R4 -> 0 | AF4: =S4 -> 0 | AG4: =SUM(Z4:AF4) -> 2 | AH4: =Z4-M4 -> 2 | AI4: =AA4-N4 -> 0 | AJ4: =AB4-O4 -> 0 | AK4: =AC4-P4 -> 0 | AL4: =AD4-Q4 -> 0 | AM4: =AE4-R4 -> 0 | AN4: =AF4-S4 -> 0 | AO4: =AG4-T4 -> 2
A5: =1+A4 -> 2 | B5: 2360 | C5: ម៉ម | D5: រត្ននី | E5: MAM | F5: ROTNY | G5: F | H5: 31391 | I5: 43252 | J5: ADMINISTRATION | K5: Admin | L5: Ass. Admin | T5: =SUM(M5:S5) -> 0 | Z5: =M5+2 -> 2 | AA5: =N5 -> 0 | AB5: =O5 -> 0 | AC5: =P5 -> 0 | AD5: =Q5 -> 0 | AE5: =R5 -> 0 | AF5: =S5 -> 0 | AG5: =SUM(Z5:AF5) -> 2 | AH5: =Z5-M5 -> 2 | AI5: =AA5-N5 -> 0 | AJ5: =AB5-O5 -> 0 | AK5: =AC5-P5 -> 0 | AL5: =AD5-Q5 -> 0 | AM5: =AE5-R5 -> 0 | AN5: =AF5-S5 -> 0 | AO5: =AG5-T5 -> 2
A6: =1+A5 -> 3 | B6: 4 | C6: ពុធ | D6: ធារី | E6: Put | F6: Theary | G6: F | H6: 30411 | I6: 41575 | J6: Shipping | K6: Import | L6: Leader | M6: 200 | N6: 9 | O6: 66 | P6: 250 | Q6: 175 | R6: 7 | S6: 10 | T6: =SUM(M6:S6) -> 717 | Z6: =M6+2 -> 202 | AA6: =N6 -> 9 | AB6: =O6 -> 66 | AC6: =P6 -> 250 | AD6: =Q6 -> 175 | AE6: =R6 -> 7 | AF6: =S6 -> 10 | AG6: =SUM(Z6:AF6) -> 719 | AH6: =Z6-M6 -> 2 | AI6: =AA6-N6 -> 0 | AJ6: =AB6-O6 -> 0 | AK6: =AC6-P6 -> 0 | AL6: =AD6-Q6 -> 0 | AM6: =AE6-R6 -> 0 | AN6: =AF6-S6 -> 0 | AO6: =AG6-T6 -> 2
A7: =1+A6 -> 4 | B7: 2 | C7: អ៊ូច | D7: ចាន់ម៉ាឡែន | E7: Ouch | F7: Chanmalen | G7: M | H7: 32387 | I7: 41575 | J7: IT | K7: IT | L7: Leader | T7: =SUM(M7:S7) -> 0 | Z7: =M7+2 -> 2 | AA7: =N7 -> 0 | AB7: =O7 -> 0 | AC7: =P7 -> 0 | AD7: =Q7 -> 0 | AE7: =R7 -> 0 | AF7: =S7 -> 0 | AG7: =SUM(Z7:AF7) -> 2 | AH7: =Z7-M7 -> 2 | AI7: =AA7-N7 -> 0 | AJ7: =AB7-O7 -> 0 | AK7: =AC7-P7 -> 0 | AL7: =AD7-Q7 -> 0 | AM7: =AE7-R7 -> 0 | AN7: =AF7-S7 -> 0 | AO7: =AG7-T7 -> 2
A8: =1+A7 -> 5 | B8: 10 | C8: ញ៉ិល | D8: ចន័្នធា | E8: NHEL | F8: CHANTHEA | G8: F | H8: 30135 | I8: 41575 | J8: Production | K8: Supervisor | L8: supervisor Line 17,18,19,20,21 | M8: 192 | N8: =ROUNDDOWN(INT($N$1-I8-16)/365,0)+1 -> 9 | O8: 20 | P8: 195 | Q8: 75 | R8: 7 | S8: 10 | T8: =SUM(M8:S8) -> 508 | Z8: =M8+2 -> 194 | AA8: =N8 -> 9 | AB8: =O8 -> 20 | AC8: =P8 -> 195 | AD8: =Q8 -> 75 | AE8: =R8 -> 7 | AF8: =S8 -> 10 | AG8: =SUM(Z8:AF8) -> 510 | AH8: =Z8-M8 -> 2 | AI8: =AA8-N8 -> 0 | AJ8: =AB8-O8 -> 0 | AK8: =AC8-P8 -> 0 | AL8: =AD8-Q8 -> 0 | AM8: =AE8-R8 -> 0 | AN8: =AF8-S8 -> 0 | AO8: =AG8-T8 -> 2 | AR8: 4
A9: =1+A8 -> 6 | B9: 14 | C9: គឹម | D9: សារិន | E9: Koem | F9: Sarim | G9: F | H9: 27490 | I9: 41573 | J9: ADMINISTRATION | K9: GA | L9: Cleaner | M9: 192 | N9: =ROUNDDOWN(INT($N$1-I9-16)/365,0)+1 -> 9 | O9: 20 | P9: 50 | Q9: 0 | R9: 7 | S9: 10 | T9: =SUM(M9:S9) -> 288 | Z9: =M9+2 -> 194 | AA9: =N9 -> 9 | AB9: =O9 -> 20 | AC9: =P9 -> 50 | AD9: =Q9 -> 0 | AE9: =R9 -> 7 | AF9: =S9 -> 10 | AG9: =SUM(Z9:AF9) -> 290 | AH9: =Z9-M9 -> 2 | AI9: =AA9-N9 -> 0 | AJ9: =AB9-O9 -> 0 | AK9: =AC9-P9 -> 0 | AL9: =AD9-Q9 -> 0 | AM9: =AE9-R9 -> 0 | AN9: =AF9-S9 -> 0 | AO9: =AG9-T9 -> 2 | AR9: 2
A10: =1+A9 -> 7 | B10: 18 | C10: ស្រី | D10: ច័ន្ទថុនា | E10: Srey | F10: Chanthuna | G10: M | H10: 33771 | I10: 41577 | J10: Production Development | K10: Development | L10: Marker technicial | M10: 262 | N10: =ROUNDDOWN(INT($N$1-I10-16)/365,0)+1 -> 9 | O10: 20 | P10: 72 | Q10: 66 | R10: 7 | S10: 10 | T10: =SUM(M10:S10) -> 446 | Z10: =M10+2 -> 264 | AA10: =N10 -> 9 | AB10: =O10 -> 20 | AC10: =P10 -> 72 | AD10: =Q10 -> 66 | AE10: =R10 -> 7 | AF10: =S10 -> 10 | AG10: =SUM(Z10:AF10) -> 448 | AH10: =Z10-M10 -> 2 | AI10: =AA10-N10 -> 0 | AJ10: =AB10-O10 -> 0 | AK10: =AC10-P10 -> 0 | AL10: =AD10-Q10 -> 0 | AM10: =AE10-R10 -> 0 | AN10: =AF10-S10 -> 0 | AO10: =AG10-T10 -> 2 | AR10: 1012
A11: =1+A10 -> 8 | B11: 24 | C11: អ៊ឹម | D11: ផានី | E11: Im | F11: Phany | G11: F | H11: 30165 | I11: 41579 | J11: Production | K11: Line3 | L11: Leader Line 3 | M11: 192 | N11: =ROUNDDOWN(INT($N$1-I11-16)/365,0)+1 -> 9 | O11: 20 | P11: 52 | Q11: 15 | R11: 7 | S11: 10 | T11: =SUM(M11:S11) -> 305 | Z11: =M11+2 -> 194 | AA11: =N11 -> 9 | AB11: =O11 -> 20 | AC11: =P11 -> 52 | AD11: =Q11 -> 15 | AE11: =R11 -> 7 | AF11: =S11 -> 10 | AG11: =SUM(Z11:AF11) -> 307 | AH11: =Z11-M11 -> 2 | AI11: =AA11-N11 -> 0 | AJ11: =AB11-O11 -> 0 | AK11: =AC11-P11 -> 0 | AL11: =AD11-Q11 -> 0 | AM11: =AE11-R11 -> 0 | AN11: =AF11-S11 -> 0 | AO11: =AG11-T11 -> 2
A12: =1+A11 -> 9 | B12: 30 | C12: ភោក | D12: ស៊ីណា | E12: Phouk | F12: Sina | G12: F | H12: 29927 | I12: 41579 | J12: Production | K12: Supervisor | L12: supervisor Line 1,2,3,15 | M12: 192 | N12: =ROUNDDOWN(INT($N$1-I12-16)/365,0)+1 -> 9 | O12: 20 | P12: 175 | Q12: 75 | R12: 7 | S12: 10 | T12: =SUM(M12:S12) -> 488 | Z12: =M12+2 -> 194 | AA12: =N12 -> 9 | AB12: =O12 -> 20 | AC12: =P12 -> 175 | AD12: =Q12 -> 75 | AE12: =R12 -> 7 | AF12: =S12 -> 10 | AG12: =SUM(Z12:AF12) -> 490 | AH12: =Z12-M12 -> 2 | AI12: =AA12-N12 -> 0 | AJ12: =AB12-O12 -> 0 | AK12: =AC12-P12 -> 0 | AL12: =AD12-Q12 -> 0 | AM12: =AE12-R12 -> 0 | AN12: =AF12-S12 -> 0 | AO12: =AG12-T12 -> 2
A13: =1+A12 -> 10 | B13: 32 | C13: ហៀ | D13: ហឿង | E13: Hear | F13: Hoeung | G13: F | H13: 27885 | I13: 41579 | J13: Production | K13: Supervisor | L13: supervisor L 8,9,10,11 | M13: 192 | N13: =ROUNDDOWN(INT($N$1-I13-16)/365,0)+1 -> 9 | O13: 0 | P13: 260 | Q13: 50 | R13: 7 | S13: 10 | T13: =SUM(M13:S13) -> 528 | Z13: =M13+2 -> 194 | AA13: =N13 -> 9 | AB13: =O13 -> 0 | AC13: =P13 -> 260 | AD13: =Q13 -> 50 | AE13: =R13 -> 7 | AF13: =S13 -> 10 | AG13: =SUM(Z13:AF13) -> 530 | AH13: =Z13-M13 -> 2 | AI13: =AA13-N13 -> 0 | AJ13: =AB13-O13 -> 0 | AK13: =AC13-P13 -> 0 | AL13: =AD13-Q13 -> 0 | AM13: =AE13-R13 -> 0 | AN13: =AF13-S13 -> 0 | AO13: =AG13-T13 -> 2
A14: =1+A13 -> 11 | B14: 39 | C14: អ៊ឹម | D14: ស្រីល័ក្ខ | E14: Oem | F14: Srey Leak | G14: F | H14: 32600 | I14: 41579 | J14: Production | K14: QC | L14: supervisor Line | T14: =SUM(M14:S14) -> 0 | Z14: =M14+2 -> 2 | AA14: =N14 -> 0 | AB14: =O14 -> 0 | AC14: =P14 -> 0 | AD14: =Q14 -> 0 | AE14: =R14 -> 0 | AF14: =S14 -> 0 | AG14: =SUM(Z14:AF14) -> 2 | AH14: =Z14-M14 -> 2 | AI14: =AA14-N14 -> 0 | AJ14: =AB14-O14 -> 0 | AK14: =AC14-P14 -> 0 | AL14: =AD14-Q14 -> 0 | AM14: =AE14-R14 -> 0 | AN14: =AF14-S14 -> 0 | AO14: =AG14-T14 -> 2
A15: =1+A14 -> 12 | B15: 44 | C15: ប៊ុន | D15: គឹមសែ | E15: Bun | F15: Kimse | G15: F | H15: 31836 | I15: 41579 | J15: Production | K15: Line19 | L15: Assist.Line 19 | M15: 192 | N15: =ROUNDDOWN(INT($N$1-I15-16)/365,0)+1 -> 9 | O15: 20 | P15: 30 | Q15: 10 | R15: 7 | S15: 10 | T15: =SUM(M15:S15) -> 278 | Z15: =M15+2 -> 194 | AA15: =N15 -> 9 | AB15: =O15 -> 20 | AC15: =P15 -> 30 | AD15: =Q15 -> 10 | AE15: =R15 -> 7 | AF15: =S15 -> 10 | AG15: =SUM(Z15:AF15) -> 280 | AH15: =Z15-M15 -> 2 | AI15: =AA15-N15 -> 0 | AJ15: =AB15-O15 -> 0 | AK15: =AC15-P15 -> 0 | AL15: =AD15-Q15 -> 0 | AM15: =AE15-R15 -> 0 | AN15: =AF15-S15 -> 0 | AO15: =AG15-T15 -> 2
A16: =1+A15 -> 13 | B16: 47 | C16: ឃុន | D16: សាខន | E16: Khun | F16: Sakhân | G16: F | H16: 24152 | I16: 41583 | J16: Production | K16: Line8 | L16: Sewing operator | M16: 199 | N16: =ROUNDDOWN(INT($N$1-I16-16)/365,0)+1 -> 9 | O16: 20 | P16: 0 | Q16: 0 | R16: 7 | S16: 10 | T16: =SUM(M16:S16) -> 245 | Z16: =M16+2 -> 201 | AA16: =N16 -> 9 | AB16: =O16 -> 20 | AC16: =P16 -> 0 | AD16: =Q16 -> 0 | AE16: =R16 -> 7 | AF16: =S16 -> 10 | AG16: =SUM(Z16:AF16) -> 247 | AH16: =Z16-M16 -> 2 | AI16: =AA16-N16 -> 0 | AJ16: =AB16-O16 -> 0 | AK16: =AC16-P16 -> 0 | AL16: =AD16-Q16 -> 0 | AM16: =AE16-R16 -> 0 | AN16: =AF16-S16 -> 0 | AO16: =AG16-T16 -> 2
A17: =1+A16 -> 14 | B17: 67 | C17: ហុង | D17: សេងចន្នី | E17: HONG | F17: SENG CHANNY | G17: F | H17: 30439 | I17: 41591 | J17: Production | K17: Line9 | L17: Sewing operator | M17: 192 | N17: =ROUNDDOWN(INT($N$1-I17-16)/365,0)+1 -> 9 | O17: 20 | P17: 0 | Q17: 0 | R17: 7 | S17: 10 | T17: =SUM(M17:S17) -> 238 | Z17: =M17+2 -> 194 | AA17: =N17 -> 9 | AB17: =O17 -> 20 | AC17: =P17 -> 0 | AD17: =Q17 -> 0 | AE17: =R17 -> 7 | AF17: =S17 -> 10 | AG17: =SUM(Z17:AF17) -> 240 | AH17: =Z17-M17 -> 2 | AI17: =AA17-N17 -> 0 | AJ17: =AB17-O17 -> 0 | AK17: =AC17-P17 -> 0 | AL17: =AD17-Q17 -> 0 | AM17: =AE17-R17 -> 0 | AN17: =AF17-S17 -> 0 | AO17: =AG17-T17 -> 2
A18: =1+A17 -> 15 | B18: 69 | C18: ធង | D18: អួន | E18: THORNG | F18: UON | G18: F | H18: 29285 | I18: 41591 | J18: Production | K18: Line21 | L18: Sewing operator | M18: 192 | N18: =ROUNDDOWN(INT($N$1-I18-16)/365,0)+1 -> 9 | O18: 20 | P18: 0 | Q18: 0 | R18: 7 | S18: 10 | T18: =SUM(M18:S18) -> 238 | Z18: =M18+2 -> 194 | AA18: =N18 -> 9 | AB18: =O18 -> 20 | AC18: =P18 -> 0 | AD18: =Q18 -> 0 | AE18: =R18 -> 7 | AF18: =S18 -> 10 | AG18: =SUM(Z18:AF18) -> 240 | AH18: =Z18-M18 -> 2 | AI18: =AA18-N18 -> 0 | AJ18: =AB18-O18 -> 0 | AK18: =AC18-P18 -> 0 | AL18: =AD18-Q18 -> 0 | AM18: =AE18-R18 -> 0 | AN18: =AF18-S18 -> 0 | AO18: =AG18-T18 -> 2
A19: =1+A18 -> 16 | B19: 74 | C19: ពេជ | D19: សោភា | E19: Pich | F19: Sophea | G19: F | H19: 29108 | I19: 41598 | J19: Production | K19: Line17 | L19: Leader Line 17 | M19: 192 | N19: =ROUNDDOWN(INT($N$1-I19-16)/365,0)+1 -> 9 | O19: 20 | P19: 47 | Q19: 15 | R19: 7 | S19: 10 | T19: =SUM(M19:S19) -> 300 | Z19: =M19+2 -> 194 | AA19: =N19 -> 9 | AB19: =O19 -> 20 | AC19: =P19 -> 47 | AD19: =Q19 -> 15 | AE19: =R19 -> 7 | AF19: =S19 -> 10 | AG19: =SUM(Z19:AF19) -> 302 | AH19: =Z19-M19 -> 2 | AI19: =AA19-N19 -> 0 | AJ19: =AB19-O19 -> 0 | AK19: =AC19-P19 -> 0 | AL19: =AD19-Q19 -> 0 | AM19: =AE19-R19 -> 0 | AN19: =AF19-S19 -> 0 | AO19: =AG19-T19 -> 2
A20: =1+A19 -> 17 | B20: 78 | C20: ម៉ូវ | D20: សុធឿន | E20: MOUV | F20: SOTHOEUNRN | G20: F | H20: 31630 | I20: 41598 | J20: Production | K20: Line10 | L20: Sewing operator | M20: 192 | N20: =ROUNDDOWN(INT($N$1-I20-16)/365,0)+1 -> 9 | O20: 20 | P20: 0 | Q20: 0 | R20: 7 | S20: 10 | T20: =SUM(M20:S20) -> 238 | Z20: =M20+2 -> 194 | AA20: =N20 -> 9 | AB20: =O20 -> 20 | AC20: =P20 -> 0 | AD20: =Q20 -> 0 | AE20: =R20 -> 7 | AF20: =S20 -> 10 | AG20: =SUM(Z20:AF20) -> 240 | AH20: =Z20-M20 -> 2 | AI20: =AA20-N20 -> 0 | AJ20: =AB20-O20 -> 0 | AK20: =AC20-P20 -> 0 | AL20: =AD20-Q20 -> 0 | AM20: =AE20-R20 -> 0 | AN20: =AF20-S20 -> 0 | AO20: =AG20-T20 -> 2
A21: =1+A20 -> 18 | B21: 81 | C21: វ៉ន | D21: ភា | E21: Vorn | F21: Phea | G21: F | H21: 28299 | I21: 41599 | J21: Production | K21: Line10 | L21: Sewing operator | M21: 192 | N21: =ROUNDDOWN(INT($N$1-I21-16)/365,0)+1 -> 9 | O21: 20 | P21: 0 | Q21: 0 | R21: 7 | S21: 10 | T21: =SUM(M21:S21) -> 238 | Z21: =M21+2 -> 194 | AA21: =N21 -> 9 | AB21: =O21 -> 20 | AC21: =P21 -> 0 | AD21: =Q21 -> 0 | AE21: =R21 -> 7 | AF21: =S21 -> 10 | AG21: =SUM(Z21:AF21) -> 240 | AH21: =Z21-M21 -> 2 | AI21: =AA21-N21 -> 0 | AJ21: =AB21-O21 -> 0 | AK21: =AC21-P21 -> 0 | AL21: =AD21-Q21 -> 0 | AM21: =AE21-R21 -> 0 | AN21: =AF21-S21 -> 0 | AO21: =AG21-T21 -> 2
A22: =1+A21 -> 19 | B22: 90 | C22: ហឿង | D22: សុខឡាង | E22: HOEUNG | F22: SOK LANG | G22: F | H22: 33244 | I22: 41598 | J22: Production | K22: Line10 | L22: Sewing operator | M22: 192 | N22: =ROUNDDOWN(INT($N$1-I22-16)/365,0)+1 -> 9 | O22: 20 | P22: 0 | Q22: 0 | R22: 7 | S22: 10 | T22: =SUM(M22:S22) -> 238 | Z22: =M22+2 -> 194 | AA22: =N22 -> 9 | AB22: =O22 -> 20 | AC22: =P22 -> 0 | AD22: =Q22 -> 0 | AE22: =R22 -> 7 | AF22: =S22 -> 10 | AG22: =SUM(Z22:AF22) -> 240 | AH22: =Z22-M22 -> 2 | AI22: =AA22-N22 -> 0 | AJ22: =AB22-O22 -> 0 | AK22: =AC22-P22 -> 0 | AL22: =AD22-Q22 -> 0 | AM22: =AE22-R22 -> 0 | AN22: =AF22-S22 -> 0 | AO22: =AG22-T22 -> 2
A23: =1+A22 -> 20 | B23: 113 | C23: អៀម | D23: សារីម | E23: IEM | F23: SARIM | G23: F | H23: 29385 | I23: 41612 | J23: Production | K23: Line1 | L23: Sewing operator | M23: 192 | N23: =ROUNDDOWN(INT($N$1-I23-16)/365,0)+1 -> 9 | O23: 20 | P23: 0 | Q23: 0 | R23: 7 | S23: 10 | T23: =SUM(M23:S23) -> 238 | Z23: =M23+2 -> 194 | AA23: =N23 -> 9 | AB23: =O23 -> 20 | AC23: =P23 -> 0 | AD23: =Q23 -> 0 | AE23: =R23 -> 7 | AF23: =S23 -> 10 | AG23: =SUM(Z23:AF23) -> 240 | AH23: =Z23-M23 -> 2 | AI23: =AA23-N23 -> 0 | AJ23: =AB23-O23 -> 0 | AK23: =AC23-P23 -> 0 | AL23: =AD23-Q23 -> 0 | AM23: =AE23-R23 -> 0 | AN23: =AF23-S23 -> 0 | AO23: =AG23-T23 -> 2 | AT23: =VLOOKUP(#REF!,All!$B$4:$S$8977,4,FALSE) -> #REF! | AU23: =VLOOKUP(#REF!,All!$B$4:$S$8977,5,FALSE) -> #REF!
A24: =1+A23 -> 21 | B24: 146 | C24: ទៀប | D24: សូនី | E24: Teab | F24: sony | G24: F | H24: 25950 | I24: 41619 | J24: Production | K24: Line2 | L24: Sewing operator | M24: 192 | N24: =ROUNDDOWN(INT($N$1-I24-16)/365,0)+1 -> 9 | O24: 20 | P24: 0 | Q24: 0 | R24: 7 | S24: 10 | T24: =SUM(M24:S24) -> 238 | Z24: =M24+2 -> 194 | AA24: =N24 -> 9 | AB24: =O24 -> 20 | AC24: =P24 -> 0 | AD24: =Q24 -> 0 | AE24: =R24 -> 7 | AF24: =S24 -> 10 | AG24: =SUM(Z24:AF24) -> 240 | AH24: =Z24-M24 -> 2 | AI24: =AA24-N24 -> 0 | AJ24: =AB24-O24 -> 0 | AK24: =AC24-P24 -> 0 | AL24: =AD24-Q24 -> 0 | AM24: =AE24-R24 -> 0 | AN24: =AF24-S24 -> 0 | AO24: =AG24-T24 -> 2 | AT24: =VLOOKUP(#REF!,All!$B$4:$S$8977,4,FALSE) -> #REF! | AU24: =VLOOKUP(#REF!,All!$B$4:$S$8977,5,FALSE) -> #REF!
A25: =1+A24 -> 22 | B25: 161 | C25: សែត | D25: មឿន | E25: Set | F25: moeun | G25: F | H25: 34710 | I25: 41674 | J25: Production | K25: Line1 | L25: Leader Line 1 | M25: 192 | N25: =ROUNDDOWN(INT($N$1-I25-16)/365,0)+1 -> 8 | O25: 20 | P25: 45 | Q25: 0 | R25: 7 | S25: 10 | T25: =SUM(M25:S25) -> 282 | Z25: =M25+2 -> 194 | AA25: =N25 -> 8 | AB25: =O25 -> 20 | AC25: =P25 -> 45 | AD25: =Q25 -> 0 | AE25: =R25 -> 7 | AF25: =S25 -> 10 | AG25: =SUM(Z25:AF25) -> 284 | AH25: =Z25-M25 -> 2 | AI25: =AA25-N25 -> 0 | AJ25: =AB25-O25 -> 0 | AK25: =AC25-P25 -> 0 | AL25: =AD25-Q25 -> 0 | AM25: =AE25-R25 -> 0 | AN25: =AF25-S25 -> 0 | AO25: =AG25-T25 -> 2 | AT25: =VLOOKUP(#REF!,All!$B$4:$S$8977,4,FALSE) -> #REF! | AU25: =VLOOKUP(#REF!,All!$B$4:$S$8977,5,FALSE) -> #REF!
A26: =1+A25 -> 23 | B26: 163 | C26: ខៀវ | D26: ចាន់នួន | E26: keav | F26: channoun | G26: F | H26: 30297 | I26: 41676 | J26: Production | K26: Sample | L26: Leader Sample | M26: 192 | N26: =ROUNDDOWN(INT($N$1-I26-16)/365,0)+1 -> 8 | O26: 20 | P26: 45 | Q26: 0 | R26: 7 | S26: 10 | T26: =SUM(M26:S26) -> 282 | Z26: =M26+2 -> 194 | AA26: =N26 -> 8 | AB26: =O26 -> 20 | AC26: =P26 -> 45 | AD26: =Q26 -> 0 | AE26: =R26 -> 7 | AF26: =S26 -> 10 | AG26: =SUM(Z26:AF26) -> 284 | AH26: =Z26-M26 -> 2 | AI26: =AA26-N26 -> 0 | AJ26: =AB26-O26 -> 0 | AK26: =AC26-P26 -> 0 | AL26: =AD26-Q26 -> 0 | AM26: =AE26-R26 -> 0 | AN26: =AF26-S26 -> 0 | AO26: =AG26-T26 -> 2 | AT26: =VLOOKUP(#REF!,All!$B$4:$S$8977,4,FALSE) -> #REF! | AU26: =VLOOKUP(#REF!,All!$B$4:$S$8977,5,FALSE) -> #REF!
A27: =1+A26 -> 24 | B27: 171 | C27: សោម | D27: ចន្ធី | E27: Som | F27: Chanthy | G27: F | H27: 32617 | I27: 41680 | J27: ADMINISTRATION | K27: HR | L27: Nurse | M27: 192 | N27: =ROUNDDOWN(INT($N$1-I27-16)/365,0)+1 -> 8 | O27: 0 | P27: 118 | Q27: 35 | R27: 7 | S27: 10 | T27: =SUM(M27:S27) -> 370 | Z27: =M27+2 -> 194 | AA27: =N27 -> 8 | AB27: =O27 -> 0 | AC27: =P27 -> 118 | AD27: =Q27 -> 35 | AE27: =R27 -> 7 | AF27: =S27 -> 10 | AG27: =SUM(Z27:AF27) -> 372 | AH27: =Z27-M27 -> 2 | AI27: =AA27-N27 -> 0 | AJ27: =AB27-O27 -> 0 | AK27: =AC27-P27 -> 0 | AL27: =AD27-Q27 -> 0 | AM27: =AE27-R27 -> 0 | AN27: =AF27-S27 -> 0 | AO27: =AG27-T27 -> 2 | AT27: =VLOOKUP(#REF!,All!$B$4:$S$8977,4,FALSE) -> #REF! | AU27: =VLOOKUP(#REF!,All!$B$4:$S$8977,5,FALSE) -> #REF!
A28: =1+A27 -> 25 | B28: 26 | C28: ឯម | D28: សោភា | E28: Em | F28: Sophea | G28: M | H28: 30171 | I28: 41568 | J28: ADMINISTRATION | K28: GA | L28: Leader GA | M28: 202 | N28: =ROUNDDOWN(INT($N$1-I28-16)/365,0)+1 -> 9 | O28: 60 | P28: 395 | Q28: 71 | R28: 7 | S28: 10 | T28: =SUM(M28:S28) -> 754 | Z28: =M28+2 -> 204 | AA28: =N28 -> 9 | AB28: =O28 -> 60 | AC28: =P28 -> 395 | AD28: =Q28 -> 71 | AE28: =R28 -> 7 | AF28: =S28 -> 10 | AG28: =SUM(Z28:AF28) -> 756 | AH28: =Z28-M28 -> 2 | AI28: =AA28-N28 -> 0 | AJ28: =AB28-O28 -> 0 | AK28: =AC28-P28 -> 0 | AL28: =AD28-Q28 -> 0 | AM28: =AE28-R28 -> 0 | AN28: =AF28-S28 -> 0 | AO28: =AG28-T28 -> 2 | AT28: =VLOOKUP(#REF!,All!$B$4:$S$8977,4,FALSE) -> #REF! | AU28: =VLOOKUP(#REF!,All!$B$4:$S$8977,5,FALSE) -> #REF!
A29: =1+A28 -> 26 | B29: 200 | C29: អ៊ុំ | D29: ចន្ថា | E29: OUM | F29: CHANTHA | G29: M | H29: 29800 | I29: 41694 | J29: Production | K29: Mechanic in line | L29: Leader Mechanic | M29: 192 | N29: =ROUNDDOWN(INT($N$1-I29-16)/365,0)+1 -> 8 | O29: 20 | P29: 295 | Q29: 0 | R29: 7 | S29: 10 | T29: =SUM(M29:S29) -> 532 | Z29: =M29+2 -> 194 | AA29: =N29 -> 8 | AB29: =O29 -> 20 | AC29: =P29 -> 295 | AD29: =Q29 -> 0 | AE29: =R29 -> 7 | AF29: =S29 -> 10 | AG29: =SUM(Z29:AF29) -> 534 | AH29: =Z29-M29 -> 2 | AI29: =AA29-N29 -> 0 | AJ29: =AB29-O29 -> 0 | AK29: =AC29-P29 -> 0 | AL29: =AD29-Q29 -> 0 | AM29: =AE29-R29 -> 0 | AN29: =AF29-S29 -> 0 | AO29: =AG29-T29 -> 2 | AT29: =VLOOKUP(#REF!,All!$B$4:$S$8977,4,FALSE) -> #REF! | AU29: =VLOOKUP(#REF!,All!$B$4:$S$8977,5,FALSE) -> #REF!
A30: =1+A29 -> 27 | B30: 176 | C30: ឃុំ | D30: ផល្លី | E30: khom | F30: pholy | G30: F | H30: 29575 | I30: 41683 | J30: Production | K30: Line15 | L30: Sewing operator | M30: 192 | N30: =ROUNDDOWN(INT($N$1-I30-16)/365,0)+1 -> 8 | O30: 25 | P30: 0 | Q30: 0 | R30: 7 | S30: 10 | T30: =SUM(M30:S30) -> 242 | Z30: =M30+2 -> 194 | AA30: =N30 -> 8 | AB30: =O30 -> 25 | AC30: =P30 -> 0 | AD30: =Q30 -> 0 | AE30: =R30 -> 7 | AF30: =S30 -> 10 | AG30: =SUM(Z30:AF30) -> 244 | AH30: =Z30-M30 -> 2 | AI30: =AA30-N30 -> 0 | AJ30: =AB30-O30 -> 0 | AK30: =AC30-P30 -> 0 | AL30: =AD30-Q30 -> 0 | AM30: =AE30-R30 -> 0 | AN30: =AF30-S30 -> 0 | AO30: =AG30-T30 -> 2 | AT30: =VLOOKUP(#REF!,All!$B$4:$S$8977,4,FALSE) -> #REF! | AU30: =VLOOKUP(#REF!,All!$B$4:$S$8977,5,FALSE) -> #REF!
A31: =1+A30 -> 28 | B31: 224 | C31: ជឿន | D31: រឿម | E31: Choeun | F31: Roeum | G31: F | H31: 28491 | I31: 41702 | J31: Production | K31: Line2 | L31: Sewing operator | M31: 192 | N31: =ROUNDDOWN(INT($N$1-I31-16)/365,0)+1 -> 8 | O31: 20 | P31: 0 | Q31: 0 | R31: 7 | S31: 10 | T31: =SUM(M31:S31) -> 237 | Z31: =M31+2 -> 194 | AA31: =N31 -> 8 | AB31: =O31 -> 20 | AC31: =P31 -> 0 | AD31: =Q31 -> 0 | AE31: =R31 -> 7 | AF31: =S31 -> 10 | AG31: =SUM(Z31:AF31) -> 239 | AH31: =Z31-M31 -> 2 | AI31: =AA31-N31 -> 0 | AJ31: =AB31-O31 -> 0 | AK31: =AC31-P31 -> 0 | AL31: =AD31-Q31 -> 0 | AM31: =AE31-R31 -> 0 | AN31: =AF31-S31 -> 0 | AO31: =AG31-T31 -> 2 | AT31: =VLOOKUP(#REF!,All!$B$4:$S$8977,4,FALSE) -> #REF! | AU31: =VLOOKUP(#REF!,All!$B$4:$S$8977,5,FALSE) -> #REF!
A32: =1+A31 -> 29 | B32: 226 | C32: រស់ | D32: ផល្លី | E32: Ros | F32: Poly | G32: F | H32: 30275 | I32: 41702 | J32: Production | K32: Line2 | L32: Sewing operator | M32: 192 | N32: =ROUNDDOWN(INT($N$1-I32-16)/365,0)+1 -> 8 | O32: 20 | P32: 0 | Q32: 0 | R32: 7 | S32: 10 | T32: =SUM(M32:S32) -> 237 | Z32: =M32+2 -> 194 | AA32: =N32 -> 8 | AB32: =O32 -> 20 | AC32: =P32 -> 0 | AD32: =Q32 -> 0 | AE32: =R32 -> 7 | AF32: =S32 -> 10 | AG32: =SUM(Z32:AF32) -> 239 | AH32: =Z32-M32 -> 2 | AI32: =AA32-N32 -> 0 | AJ32: =AB32-O32 -> 0 | AK32: =AC32-P32 -> 0 | AL32: =AD32-Q32 -> 0 | AM32: =AE32-R32 -> 0 | AN32: =AF32-S32 -> 0 | AO32: =AG32-T32 -> 2
A33: =1+A32 -> 30 | B33: 271 | C33: វុន | D33: តាំង | E33: VUN | F33: TAING | G33: F | H33: 29064 | I33: 41730 | J33: Production | K33: Line17 | L33: Sewing operator | M33: 192 | N33: =ROUNDDOWN(INT($N$1-I33-16)/365,0)+1 -> 8 | O33: 20 | P33: 0 | Q33: 0 | R33: 7 | S33: 10 | T33: =SUM(M33:S33) -> 237 | Z33: =M33+2 -> 194 | AA33: =N33 -> 8 | AB33: =O33 -> 20 | AC33: =P33 -> 0 | AD33: =Q33 -> 0 | AE33: =R33 -> 7 | AF33: =S33 -> 10 | AG33: =SUM(Z33:AF33) -> 239 | AH33: =Z33-M33 -> 2 | AI33: =AA33-N33 -> 0 | AJ33: =AB33-O33 -> 0 | AK33: =AC33-P33 -> 0 | AL33: =AD33-Q33 -> 0 | AM33: =AE33-R33 -> 0 | AN33: =AF33-S33 -> 0 | AO33: =AG33-T33 -> 2
A34: =1+A33 -> 31 | B34: 283 | C34: កែវ | D34: ពុទ្ធា | E34: KEO | F34: PUTHEA | G34: F | H34: 34151 | I34: 41750 | J34: Production | K34: Line21 | L34: Sewing operator | M34: 192 | N34: =ROUNDDOWN(INT($N$1-I34-16)/365,0)+1 -> 8 | O34: 20 | P34: 0 | Q34: 0 | R34: 7 | S34: 10 | T34: =SUM(M34:S34) -> 237 | Z34: =M34+2 -> 194 | AA34: =N34 -> 8 | AB34: =O34 -> 20 | AC34: =P34 -> 0 | AD34: =Q34 -> 0 | AE34: =R34 -> 7 | AF34: =S34 -> 10 | AG34: =SUM(Z34:AF34) -> 239 | AH34: =Z34-M34 -> 2 | AI34: =AA34-N34 -> 0 | AJ34: =AB34-O34 -> 0 | AK34: =AC34-P34 -> 0 | AL34: =AD34-Q34 -> 0 | AM34: =AE34-R34 -> 0 | AN34: =AF34-S34 -> 0 | AO34: =AG34-T34 -> 2
A35: =1+A34 -> 32 | B35: 286 | C35: ម៉ិល | D35: វី | E35: MIL | F35: VY | G35: F | H35: 26674 | I35: 41751 | J35: Production | K35: Line21 | L35: Sewing operator | M35: 192 | N35: =ROUNDDOWN(INT($N$1-I35-16)/365,0)+1 -> 8 | O35: 20 | P35: 0 | Q35: 0 | R35: 7 | S35: 10 | T35: =SUM(M35:S35) -> 237 | Z35: =M35+2 -> 194 | AA35: =N35 -> 8 | AB35: =O35 -> 20 | AC35: =P35 -> 0 | AD35: =Q35 -> 0 | AE35: =R35 -> 7 | AF35: =S35 -> 10 | AG35: =SUM(Z35:AF35) -> 239 | AH35: =Z35-M35 -> 2 | AI35: =AA35-N35 -> 0 | AJ35: =AB35-O35 -> 0 | AK35: =AC35-P35 -> 0 | AL35: =AD35-Q35 -> 0 | AM35: =AE35-R35 -> 0 | AN35: =AF35-S35 -> 0 | AO35: =AG35-T35 -> 2
A36: =1+A35 -> 33 | B36: 312 | C36: នាក់ | D36: នួន | E36: NAK | F36: NGUON | G36: F | H36: 30906 | I36: 41754 | J36: Production | K36: Line21 | L36: Sewing operator | M36: 192 | N36: =ROUNDDOWN(INT($N$1-I36-16)/365,0)+1 -> 8 | O36: 20 | P36: 0 | Q36: 0 | R36: 7 | S36: 10 | T36: =SUM(M36:S36) -> 237 | Z36: =M36+2 -> 194 | AA36: =N36 -> 8 | AB36: =O36 -> 20 | AC36: =P36 -> 0 | AD36: =Q36 -> 0 | AE36: =R36 -> 7 | AF36: =S36 -> 10 | AG36: =SUM(Z36:AF36) -> 239 | AH36: =Z36-M36 -> 2 | AI36: =AA36-N36 -> 0 | AJ36: =AB36-O36 -> 0 | AK36: =AC36-P36 -> 0 | AL36: =AD36-Q36 -> 0 | AM36: =AE36-R36 -> 0 | AN36: =AF36-S36 -> 0 | AO36: =AG36-T36 -> 2
A37: =1+A36 -> 34 | B37: 316 | C37: រិន | D37: ចាន់ថា | E37: RIN | F37: CHANTHA | G37: F | H37: 34981 | I37: 41755 | J37: Production | K37: Warehouse Trims | L37: accessory assistant | M37: 192 | N37: =ROUNDDOWN(INT($N$1-I37-16)/365,0)+1 -> 8 | O37: 20 | P37: 20 | Q37: 0 | R37: 7 | S37: 10 | T37: =SUM(M37:S37) -> 257 | Z37: =M37+2 -> 194 | AA37: =N37 -> 8 | AB37: =O37 -> 20 | AC37: =P37 -> 20 | AD37: =Q37 -> 0 | AE37: =R37 -> 7 | AF37: =S37 -> 10 | AG37: =SUM(Z37:AF37) -> 259 | AH37: =Z37-M37 -> 2 | AI37: =AA37-N37 -> 0 | AJ37: =AB37-O37 -> 0 | AK37: =AC37-P37 -> 0 | AL37: =AD37-Q37 -> 0 | AM37: =AE37-R37 -> 0 | AN37: =AF37-S37 -> 0 | AO37: =AG37-T37 -> 2
A38: =1+A37 -> 35 | B38: 326 | C38: ផង់ | D38: ហៃ | E38: PHANG | F38: HEY | G38: F | H38: 30929 | I38: 41762 | J38: Production | K38: Line1 | L38: Sewing operator | M38: 192 | N38: =ROUNDDOWN(INT($N$1-I38-16)/365,0)+1 -> 8 | O38: 20 | P38: 0 | Q38: 0 | R38: 7 | S38: 10 | T38: =SUM(M38:S38) -> 237 | Z38: =M38+2 -> 194 | AA38: =N38 -> 8 | AB38: =O38 -> 20 | AC38: =P38 -> 0 | AD38: =Q38 -> 0 | AE38: =R38 -> 7 | AF38: =S38 -> 10 | AG38: =SUM(Z38:AF38) -> 239 | AH38: =Z38-M38 -> 2 | AI38: =AA38-N38 -> 0 | AJ38: =AB38-O38 -> 0 | AK38: =AC38-P38 -> 0 | AL38: =AD38-Q38 -> 0 | AM38: =AE38-R38 -> 0 | AN38: =AF38-S38 -> 0 | AO38: =AG38-T38 -> 2
A39: =1+A38 -> 36 | B39: 351 | C39: និត | D39: ស្រីនាង | E39: NIT | F39: SREYNEANG | G39: F | H39: 32567 | I39: 41766 | J39: Production | K39: Line20 | L39: Sewing operator | M39: 192 | N39: =ROUNDDOWN(INT($N$1-I39-16)/365,0)+1 -> 8 | O39: 20 | P39: 5 | Q39: 0 | R39: 7 | S39: 10 | T39: =SUM(M39:S39) -> 242 | Z39: =M39+2 -> 194 | AA39: =N39 -> 8 | AB39: =O39 -> 20 | AC39: =P39 -> 5 | AD39: =Q39 -> 0 | AE39: =R39 -> 7 | AF39: =S39 -> 10 | AG39: =SUM(Z39:AF39) -> 244 | AH39: =Z39-M39 -> 2 | AI39: =AA39-N39 -> 0 | AJ39: =AB39-O39 -> 0 | AK39: =AC39-P39 -> 0 | AL39: =AD39-Q39 -> 0 | AM39: =AE39-R39 -> 0 | AN39: =AF39-S39 -> 0 | AO39: =AG39-T39 -> 2
A40: =1+A39 -> 37 | B40: 372 | C40: លី | D40: ប៊ុនរិទ្ធ | E40: LY | F40: BONRETH | G40: M | H40: 30348 | I40: 41765 | J40: ADMINISTRATION | K40: ME | L40: Leader Maiternance | M40: 192 | N40: =ROUNDDOWN(INT($N$1-I40-16)/365,0)+1 -> 8 | O40: 85 | P40: 400 | Q40: 0 | R40: 7 | S40: 10 | T40: =SUM(M40:S40) -> 702 | Z40: =M40+2 -> 194 | AA40: =N40 -> 8 | AB40: =O40 -> 85 | AC40: =P40 -> 400 | AD40: =Q40 -> 0 | AE40: =R40 -> 7 | AF40: =S40 -> 10 | AG40: =SUM(Z40:AF40) -> 704 | AH40: =Z40-M40 -> 2 | AI40: =AA40-N40 -> 0 | AJ40: =AB40-O40 -> 0 | AK40: =AC40-P40 -> 0 | AL40: =AD40-Q40 -> 0 | AM40: =AE40-R40 -> 0 | AN40: =AF40-S40 -> 0 | AO40: =AG40-T40 -> 2
A41: =1+A40 -> 38 | B41: 333 | C41: ផាន់ | D41: ផេន | E41: PHAN | F41: PHEN | G41: F | H41: 28524 | I41: 41765 | J41: Production | K41: Line15 | L41: Sewing operator | M41: 192 | N41: =ROUNDDOWN(INT($N$1-I41-16)/365,0)+1 -> 8 | O41: 20 | P41: 0 | Q41: 0 | R41: 7 | S41: 10 | T41: =SUM(M41:S41) -> 237 | Z41: =M41+2 -> 194 | AA41: =N41 -> 8 | AB41: =O41 -> 20 | AC41: =P41 -> 0 | AD41: =Q41 -> 0 | AE41: =R41 -> 7 | AF41: =S41 -> 10 | AG41: =SUM(Z41:AF41) -> 239 | AH41: =Z41-M41 -> 2 | AI41: =AA41-N41 -> 0 | AJ41: =AB41-O41 -> 0 | AK41: =AC41-P41 -> 0 | AL41: =AD41-Q41 -> 0 | AM41: =AE41-R41 -> 0 | AN41: =AF41-S41 -> 0 | AO41: =AG41-T41 -> 2
A42: =1+A41 -> 39 | B42: 385 | C42: ដេង | D42: តេង | E42: DANG | F42: TANG | G42: M | H42: 33217 | I42: 41782 | J42: Production | K42: Packing B | L42: Leader Packing B | M42: 192 | N42: =ROUNDDOWN(INT($N$1-I42-16)/365,0)+1 -> 8 | O42: 20 | P42: 45 | Q42: 0 | R42: 7 | S42: 10 | T42: =SUM(M42:S42) -> 282 | Z42: =M42+2 -> 194 | AA42: =N42 -> 8 | AB42: =O42 -> 20 | AC42: =P42 -> 45 | AD42: =Q42 -> 0 | AE42: =R42 -> 7 | AF42: =S42 -> 10 | AG42: =SUM(Z42:AF42) -> 284 | AH42: =Z42-M42 -> 2 | AI42: =AA42-N42 -> 0 | AJ42: =AB42-O42 -> 0 | AK42: =AC42-P42 -> 0 | AL42: =AD42-Q42 -> 0 | AM42: =AE42-R42 -> 0 | AN42: =AF42-S42 -> 0 | AO42: =AG42-T42 -> 2
A43: =1+A42 -> 40 | B43: 404 | C43: គង់ | D43: ស្រស់ | E43: KONG | F43: SROS | G43: F | H43: 34116 | I43: 41793 | J43: Production | K43: Packing A | L43: Assist.Packing A | M43: 192 | N43: =ROUNDDOWN(INT($N$1-I43-16)/365,0)+1 -> 8 | O43: 20 | P43: 10 | Q43: 0 | R43: 7 | S43: 10 | T43: =SUM(M43:S43) -> 247 | Z43: =M43+2 -> 194 | AA43: =N43 -> 8 | AB43: =O43 -> 20 | AC43: =P43 -> 10 | AD43: =Q43 -> 0 | AE43: =R43 -> 7 | AF43: =S43 -> 10 | AG43: =SUM(Z43:AF43) -> 249 | AH43: =Z43-M43 -> 2 | AI43: =AA43-N43 -> 0 | AJ43: =AB43-O43 -> 0 | AK43: =AC43-P43 -> 0 | AL43: =AD43-Q43 -> 0 | AM43: =AE43-R43 -> 0 | AN43: =AF43-S43 -> 0 | AO43: =AG43-T43 -> 2
... A127: =1+A126 -> 124 | B127: 1497 | C127: គង់ | D127: គា | E127: KONG | F127: KEA | G127: F | H127: 34920 | I127: 42445 | J127: Production | K127: QC B | L127: Assist.QC B | M127: 192 | N127: =ROUNDDOWN(INT($N$1-I127-16)/365,0)+1 -> 6 | O127: 20 | P127: 20 | Q127: 0 | R127: 7 | S127: 10 | T127: =SUM(M127:S127) -> 255 | Z127: =M127+2 -> 194 | AA127: =N127 -> 6 | AB127: =O127 -> 20 | AC127: =P127 -> 20 | AD127: =Q127 -> 0 | AE127: =R127 -> 7 | AF127: =S127 -> 10 | AG127: =SUM(Z127:AF127) -> 257 | AH127: =Z127-M127 -> 2 | AI127: =AA127-N127 -> 0 | AJ127: =AB127-O127 -> 0 | AK127: =AC127-P127 -> 0 | AL127: =AD127-Q127 -> 0 | AM127: =AE127-R127 -> 0 | AN127: =AF127-S127 -> 0 | AO127: =AG127-T127 -> 2
A128: =1+A127 -> 125 | B128: 1505 | C128: ឆឹម | D128: ម៉ុងហួត | E128: CHHE | F128: MONG HOURT | G128: M | H128: 25563 | I128: 42466 | J128: ADMINISTRATION | K128: HR | L128: Doctor | M128: 352 | N128: =ROUNDDOWN(INT($N$1-I128-16)/365,0)+1 -> 6 | O128: 0 | P128: 30 | Q128: 0 | T128: =SUM(M128:S128) -> 388 | Z128: =M128+2 -> 354 | AA128: =N128 -> 6 | AB128: =O128 -> 0 | AC128: =P128 -> 30 | AD128: =Q128 -> 0 | AE128: =R128 -> 0 | AF128: =S128 -> 0 | AG128: =SUM(Z128:AF128) -> 390 | AH128: =Z128-M128 -> 2 | AI128: =AA128-N128 -> 0 | AJ128: =AB128-O128 -> 0 | AK128: =AC128-P128 -> 0 | AL128: =AD128-Q128 -> 0 | AM128: =AE128-R128 -> 0 | AN128: =AF128-S128 -> 0 | AO128: =AG128-T128 -> 2
A129: =1+A128 -> 126 | B129: 1522 | C129: ប៉ាន់ | D129: ស៊ីឌឿន | E129: PANN | F129: SIDOEUN | G129: F | H129: 33351 | I129: 42500 | J129: Production | K129: QC B | L129: Inspector | M129: 192 | N129: =ROUNDDOWN(INT($N$1-I129-16)/365,0)+1 -> 6 | O129: 20 | P129: 0 | Q129: 0 | R129: 7 | S129: 10 | T129: =SUM(M129:S129) -> 235 | Z129: =M129+2 -> 194 | AA129: =N129 -> 6 | AB129: =O129 -> 20 | AC129: =P129 -> 0 | AD129: =Q129 -> 0 | AE129: =R129 -> 7 | AF129: =S129 -> 10 | AG129: =SUM(Z129:AF129) -> 237 | AH129: =Z129-M129 -> 2 | AI129: =AA129-N129 -> 0 | AJ129: =AB129-O129 -> 0 | AK129: =AC129-P129 -> 0 | AL129: =AD129-Q129 -> 0 | AM129: =AE129-R129 -> 0 | AN129: =AF129-S129 -> 0 | AO129: =AG129-T129 -> 2
A130: =1+A129 -> 127 | B130: 1531 | C130: ផេង | D130: ដានី | E130: PHENG | F130: DANY | G130: F | H130: 34586 | I130: 42523 | J130: Production | K130: Line8 | L130: Sewing operator | M130: 192 | N130: =ROUNDDOWN(INT($N$1-I130-16)/365,0)+1 -> 6 | O130: 20 | P130: 0 | Q130: 0 | R130: 7 | S130: 10 | T130: =SUM(M130:S130) -> 235 | Z130: =M130+2 -> 194 | AA130: =N130 -> 6 | AB130: =O130 -> 20 | AC130: =P130 -> 0 | AD130: =Q130 -> 0 | AE130: =R130 -> 7 | AF130: =S130 -> 10 | AG130: =SUM(Z130:AF130) -> 237 | AH130: =Z130-M130 -> 2 | AI130: =AA130-N130 -> 0 | AJ130: =AB130-O130 -> 0 | AK130: =AC130-P130 -> 0 | AL130: =AD130-Q130 -> 0 | AM130: =AE130-R130 -> 0 | AN130: =AF130-S130 -> 0 | AO130: =AG130-T130 -> 2
A131: =1+A130 -> 128 | B131: 1540 | C131: នាក់ | D131: ស្រីនិច្ច | E131: NAK | F131: SREYNECH | G131: F | H131: 34552 | I131: 42528 | J131: Production | K131: Line9 | L131: Sewing operator | M131: 192 | N131: =ROUNDDOWN(INT($N$1-I131-16)/365,0)+1 -> 6 | O131: 20 | P131: 0 | Q131: 0 | R131: 7 | S131: 10 | T131: =SUM(M131:S131) -> 235 | Z131: =M131+2 -> 194 | AA131: =N131 -> 6 | AB131: =O131 -> 20 | AC131: =P131 -> 0 | AD131: =Q131 -> 0 | AE131: =R131 -> 7 | AF131: =S131 -> 10 | AG131: =SUM(Z131:AF131) -> 237 | AH131: =Z131-M131 -> 2 | AI131: =AA131-N131 -> 0 | AJ131: =AB131-O131 -> 0 | AK131: =AC131-P131 -> 0 | AL131: =AD131-Q131 -> 0 | AM131: =AE131-R131 -> 0 | AN131: =AF131-S131 -> 0 | AO131: =AG131-T131 -> 2
A132: =1+A131 -> 129 | B132: 1553 | C132: សាក់ | D132: ចាន់រ៉ា | E132: SAK | F132: CHANRA | G132: F | H132: 31240 | I132: 42537 | J132: Production | K132: Line9 | L132: Sewing operator | M132: 192 | N132: =ROUNDDOWN(INT($N$1-I132-16)/365,0)+1 -> 6 | O132: 20 | P132: 0 | Q132: 0 | R132: 7 | S132: 10 | T132: =SUM(M132:S132) -> 235 | Z132: =M132+2 -> 194 | AA132: =N132 -> 6 | AB132: =O132 -> 20 | AC132: =P132 -> 0 | AD132: =Q132 -> 0 | AE132: =R132 -> 7 | AF132: =S132 -> 10 | AG132: =SUM(Z132:AF132) -> 237 | AH132: =Z132-M132 -> 2 | AI132: =AA132-N132 -> 0 | AJ132: =AB132-O132 -> 0 | AK132: =AC132-P132 -> 0 | AL132: =AD132-Q132 -> 0 | AM132: =AE132-R132 -> 0 | AN132: =AF132-S132 -> 0 | AO132: =AG132-T132 -> 2
A133: =1+A132 -> 130 | B133: 1559 | C133: ដៀប | D133: អន | E133: DIEB | F133: ON | G133: F | H133: 31459 | I133: 42545 | J133: Production | K133: Line8 | L133: Sewing operator | M133: 192 | N133: =ROUNDDOWN(INT($N$1-I133-16)/365,0)+1 -> 6 | O133: 20 | P133: 0 | Q133: 0 | R133: 7 | S133: 10 | T133: =SUM(M133:S133) -> 235 | Z133: =M133+2 -> 194 | AA133: =N133 -> 6 | AB133: =O133 -> 20 | AC133: =P133 -> 0 | AD133: =Q133 -> 0 | AE133: =R133 -> 7 | AF133: =S133 -> 10 | AG133: =SUM(Z133:AF133) -> 237 | AH133: =Z133-M133 -> 2 | AI133: =AA133-N133 -> 0 | AJ133: =AB133-O133 -> 0 | AK133: =AC133-P133 -> 0 | AL133: =AD133-Q133 -> 0 | AM133: =AE133-R133 -> 0 | AN133: =AF133-S133 -> 0 | AO133: =AG133-T133 -> 2
A134: =1+A133 -> 131 | B134: 1569 | C134: សន | D134: ស៊ីណាត | E134: SORN | F134: SINAT | G134: F | H134: 31659 | I134: 42565 | J134: Production | K134: Line9 | L134: Leader Line 9 | M134: 192 | N134: =ROUNDDOWN(INT($N$1-I134-16)/365,0)+1 -> 6 | O134: 20 | P134: 45 | Q134: 0 | R134: 7 | S134: 10 | T134: =SUM(M134:S134) -> 280 | Z134: =M134+2 -> 194 | AA134: =N134 -> 6 | AB134: =O134 -> 20 | AC134: =P134 -> 45 | AD134: =Q134 -> 0 | AE134: =R134 -> 7 | AF134: =S134 -> 10 | AG134: =SUM(Z134:AF134) -> 282 | AH134: =Z134-M134 -> 2 | AI134: =AA134-N134 -> 0 | AJ134: =AB134-O134 -> 0 | AK134: =AC134-P134 -> 0 | AL134: =AD134-Q134 -> 0 | AM134: =AE134-R134 -> 0 | AN134: =AF134-S134 -> 0 | AO134: =AG134-T134 -> 2
A135: =1+A134 -> 132 | B135: 1593 | C135: ប៊ុន | D135: ស្រីឃីម | E135: BUN | F135: SREI KHIM | G135: F | H135: 28495 | I135: 42597 | J135: Production | K135: Cutting | L135: Cutter | M135: 192 | N135: =ROUNDDOWN(INT($N$1-I135-16)/365,0)+1 -> 6 | O135: 20 | P135: 0 | Q135: 0 | R135: 7 | S135: 10 | T135: =SUM(M135:S135) -> 235 | Z135: =M135+2 -> 194 | AA135: =N135 -> 6 | AB135: =O135 -> 20 | AC135: =P135 -> 0 | AD135: =Q135 -> 0 | AE135: =R135 -> 7 | AF135: =S135 -> 10 | AG135: =SUM(Z135:AF135) -> 237 | AH135: =Z135-M135 -> 2 | AI135: =AA135-N135 -> 0 | AJ135: =AB135-O135 -> 0 | AK135: =AC135-P135 -> 0 | AL135: =AD135-Q135 -> 0 | AM135: =AE135-R135 -> 0 | AN135: =AF135-S135 -> 0 | AO135: =AG135-T135 -> 2
A136: =1+A135 -> 133 | B136: 1608 | C136: យ៉ាន់ | D136: ចាន់រី | E136: YANN | F136: CHANRY | G136: F | H136: 31124 | I136: 42615 | J136: Production | K136: Line17 | L136: Sewing operator | M136: 192 | N136: =ROUNDDOWN(INT($N$1-I136-16)/365,0)+1 -> 6 | O136: 20 | P136: 0 | Q136: 0 | R136: 7 | S136: 10 | T136: =SUM(M136:S136) -> 235 | Z136: =M136+2 -> 194 | AA136: =N136 -> 6 | AB136: =O136 -> 20 | AC136: =P136 -> 0 | AD136: =Q136 -> 0 | AE136: =R136 -> 7 | AF136: =S136 -> 10 | AG136: =SUM(Z136:AF136) -> 237 | AH136: =Z136-M136 -> 2 | AI136: =AA136-N136 -> 0 | AJ136: =AB136-O136 -> 0 | AK136: =AC136-P136 -> 0 | AL136: =AD136-Q136 -> 0 | AM136: =AE136-R136 -> 0 | AN136: =AF136-S136 -> 0 | AO136: =AG136-T136 -> 2
A137: =1+A136 -> 134 | B137: 1610 | C137: យ៉ូន | D137: សំអឿន | E137: YAUN | F137: SAMOEUN | G137: F | H137: 29710 | I137: 42618 | J137: Production | K137: Cutting | L137: Cutter | M137: 192 | N137: =ROUNDDOWN(INT($N$1-I137-16)/365,0)+1 -> 6 | O137: 20 | P137: 0 | Q137: 0 | R137: 7 | S137: 10 | T137: =SUM(M137:S137) -> 235 | Z137: =M137+2 -> 194 | AA137: =N137 -> 6 | AB137: =O137 -> 20 | AC137: =P137 -> 0 | AD137: =Q137 -> 0 | AE137: =R137 -> 7 | AF137: =S137 -> 10 | AG137: =SUM(Z137:AF137) -> 237 | AH137: =Z137-M137 -> 2 | AI137: =AA137-N137 -> 0 | AJ137: =AB137-O137 -> 0 | AK137: =AC137-P137 -> 0 | AL137: =AD137-Q137 -> 0 | AM137: =AE137-R137 -> 0 | AN137: =AF137-S137 -> 0 | AO137: =AG137-T137 -> 2
A138: =1+A137 -> 135 | B138: 1611 | C138: ឃុន | D138: អ៊ុយ | E138: KHUN | F138: UY | G138: F | H138: 29315 | I138: 42615 | J138: Production | K138: Line19 | L138: Sewing operator | M138: 192 | N138: =ROUNDDOWN(INT($N$1-I138-16)/365,0)+1 -> 6 | O138: 20 | P138: 0 | Q138: 0 | R138: 7 | S138: 10 | T138: =SUM(M138:S138) -> 235 | Z138: =M138+2 -> 194 | AA138: =N138 -> 6 | AB138: =O138 -> 20 | AC138: =P138 -> 0 | AD138: =Q138 -> 0 | AE138: =R138 -> 7 | AF138: =S138 -> 10 | AG138: =SUM(Z138:AF138) -> 237 | AH138: =Z138-M138 -> 2 | AI138: =AA138-N138 -> 0 | AJ138: =AB138-O138 -> 0 | AK138: =AC138-P138 -> 0 | AL138: =AD138-Q138 -> 0 | AM138: =AE138-R138 -> 0 | AN138: =AF138-S138 -> 0 | AO138: =AG138-T138 -> 2
A139: =1+A138 -> 136 | B139: 1622 | C139: ឈឹម | D139: រៀម | E139: CHHIM | F139: REAM | G139: F | H139: 26160 | I139: 42655 | J139: ADMINISTRATION | K139: GA | L139: Cook | M139: 192 | N139: =ROUNDDOWN(INT($N$1-I139-16)/365,0)+1 -> 6 | O139: 20 | P139: 80 | Q139: 0 | R139: 7 | S139: 10 | T139: =SUM(M139:S139) -> 315 | Z139: =M139+2 -> 194 | AA139: =N139 -> 6 | AB139: =O139 -> 20 | AC139: =P139 -> 80 | AD139: =Q139 -> 0 | AE139: =R139 -> 7 | AF139: =S139 -> 10 | AG139: =SUM(Z139:AF139) -> 317 | AH139: =Z139-M139 -> 2 | AI139: =AA139-N139 -> 0 | AJ139: =AB139-O139 -> 0 | AK139: =AC139-P139 -> 0 | AL139: =AD139-Q139 -> 0 | AM139: =AE139-R139 -> 0 | AN139: =AF139-S139 -> 0 | AO139: =AG139-T139 -> 2
A140: =1+A139 -> 137 | B140: 1627 | C140: កូវ | D140: សាឌី | E140: KOV | F140: SADY | G140: F | H140: 29676 | I140: 42656 | J140: Production | K140: Line19 | L140: Sewing operator | M140: 192 | N140: =ROUNDDOWN(INT($N$1-I140-16)/365,0)+1 -> 6 | O140: 20 | P140: 0 | Q140: 0 | R140: 7 | S140: 10 | T140: =SUM(M140:S140) -> 235 | Z140: =M140+2 -> 194 | AA140: =N140 -> 6 | AB140: =O140 -> 20 | AC140: =P140 -> 0 | AD140: =Q140 -> 0 | AE140: =R140 -> 7 | AF140: =S140 -> 10 | AG140: =SUM(Z140:AF140) -> 237 | AH140: =Z140-M140 -> 2 | AI140: =AA140-N140 -> 0 | AJ140: =AB140-O140 -> 0 | AK140: =AC140-P140 -> 0 | AL140: =AD140-Q140 -> 0 | AM140: =AE140-R140 -> 0 | AN140: =AF140-S140 -> 0 | AO140: =AG140-T140 -> 2
... A316: =1+A315 -> 313 | B316: 3352 | C316: ធី | D316: ស្រីម៉ៅ | E316: THY | F316: SREYMAO | G316: F | H316: 33119 | I316: 43755 | J316: Production | K316: Line21 | L316: Sewing operator | M316: 192 | N316: =ROUNDDOWN(INT($N$1-I316-16)/365,0)+1 -> 3 | O316: 0 | P316: 0 | Q316: 0 | R316: 7 | S316: 10 | T316: =SUM(M316:S316) -> 212 | Z316: =M316+2 -> 194 | AA316: =N316 -> 3 | AB316: =O316 -> 0 | AC316: =P316 -> 0 | AD316: =Q316 -> 0 | AE316: =R316 -> 7 | AF316: =S316 -> 10 | AG316: =SUM(Z316:AF316) -> 214 | AH316: =Z316-M316 -> 2 | AI316: =AA316-N316 -> 0 | AJ316: =AB316-O316 -> 0 | AK316: =AC316-P316 -> 0 | AL316: =AD316-Q316 -> 0 | AM316: =AE316-R316 -> 0 | AN316: =AF316-S316 -> 0 | AO316: =AG316-T316 -> 2
A317: =1+A316 -> 314 | B317: 3413 | C317: អ៊ុន | D317: ស្រីនោ | E317: UON | F317: SREYNOU | G317: F | H317: 34355 | I317: 43763 | J317: Production | K317: Line19 | L317: Sewing operator | M317: 192 | N317: =ROUNDDOWN(INT($N$1-I317-16)/365,0)+1 -> 3 | O317: 0 | P317: 0 | Q317: 0 | R317: 7 | S317: 10 | T317: =SUM(M317:S317) -> 212 | U317: 10 | V317: 44197 | W317: Paul | X317: 0.73 | Z317: =M317+2 -> 194 | AA317: =N317 -> 3 | AB317: =O317 -> 0 | AC317: =P317 -> 0 | AD317: =Q317 -> 0 | AE317: =R317 -> 7 | AF317: =S317 -> 10 | AG317: =SUM(Z317:AF317) -> 214 | AH317: =Z317-M317 -> 2 | AI317: =AA317-N317 -> 0 | AJ317: =AB317-O317 -> 0 | AK317: =AC317-P317 -> 0 | AL317: =AD317-Q317 -> 0 | AM317: =AE317-R317 -> 0 | AN317: =AF317-S317 -> 0 | AO317: =AG317-T317 -> 2
A318: =1+A317 -> 315 | B318: 3381 | C318: វង្ស | D318: សុវណ្ណា | E318: VONG | F318: SOVANNA | G318: F | H318: 31579 | I318: 43755 | J318: Production | K318: Line19 | L318: Sewing operator | M318: 192 | N318: =ROUNDDOWN(INT($N$1-I318-16)/365,0)+1 -> 3 | O318: 0 | P318: 0 | Q318: 0 | R318: 7 | S318: 10 | T318: =SUM(M318:S318) -> 212 | Z318: =M318+2 -> 194 | AA318: =N318 -> 3 | AB318: =O318 -> 0 | AC318: =P318 -> 0 | AD318: =Q318 -> 0 | AE318: =R318 -> 7 | AF318: =S318 -> 10 | AG318: =SUM(Z318:AF318) -> 214 | AH318: =Z318-M318 -> 2 | AI318: =AA318-N318 -> 0 | AJ318: =AB318-O318 -> 0 | AK318: =AC318-P318 -> 0 | AL318: =AD318-Q318 -> 0 | AM318: =AE318-R318 -> 0 | AN318: =AF318-S318 -> 0 | AO318: =AG318-T318 -> 2
A319: =1+A318 -> 316 | B319: 3660 | C319: រឿន | D319: ចន្នី | E319: Reoun | F319: Channy | G319: F | H319: 33677 | I319: 43757 | J319: Production | K319: Line6 | L319: Sewing operator | M319: 192 | N319: =ROUNDDOWN(INT($N$1-I319-16)/365,0)+1 -> 3 | O319: 0 | P319: 0 | Q319: 0 | R319: 7 | S319: 10 | T319: =SUM(M319:S319) -> 212 | Z319: =M319+2 -> 194 | AA319: =N319 -> 3 | AB319: =O319 -> 0 | AC319: =P319 -> 0 | AD319: =Q319 -> 0 | AE319: =R319 -> 7 | AF319: =S319 -> 10 | AG319: =SUM(Z319:AF319) -> 214 | AH319: =Z319-M319 -> 2 | AI319: =AA319-N319 -> 0 | AJ319: =AB319-O319 -> 0 | AK319: =AC319-P319 -> 0 | AL319: =AD319-Q319 -> 0 | AM319: =AE319-R319 -> 0 | AN319: =AF319-S319 -> 0 | AO319: =AG319-T319 -> 2
A320: =1+A319 -> 317 | B320: 3677 | C320: អ៊ុក | D320: យីម | E320: Uk | F320: Yim | G320: F | H320: 29747 | I320: 43757 | J320: Production | K320: Line5 | L320: Sewing operator | M320: 192 | N320: =ROUNDDOWN(INT($N$1-I320-16)/365,0)+1 -> 3 | O320: 0 | P320: 0 | Q320: 0 | R320: 7 | S320: 10 | T320: =SUM(M320:S320) -> 212 | Z320: =M320+2 -> 194 | AA320: =N320 -> 3 | AB320: =O320 -> 0 | AC320: =P320 -> 0 | AD320: =Q320 -> 0 | AE320: =R320 -> 7 | AF320: =S320 -> 10 | AG320: =SUM(Z320:AF320) -> 214 | AH320: =Z320-M320 -> 2 | AI320: =AA320-N320 -> 0 | AJ320: =AB320-O320 -> 0 | AK320: =AC320-P320 -> 0 | AL320: =AD320-Q320 -> 0 | AM320: =AE320-R320 -> 0 | AN320: =AF320-S320 -> 0 | AO320: =AG320-T320 -> 2
A321: =1+A320 -> 318 | B321: 3522 | C321: អោម | D321: ផាត | E321: Iem | F321: Phat | G321: F | H321: 31977 | I321: 43746 | J321: Production | K321: Line18 | L321: Sewing operator | M321: 192 | N321: =ROUNDDOWN(INT($N$1-I321-16)/365,0)+1 -> 3 | O321: 0 | P321: 0 | Q321: 0 | R321: 7 | S321: 10 | T321: =SUM(M321:S321) -> 212 | Z321: =M321+2 -> 194 | AA321: =N321 -> 3 | AB321: =O321 -> 0 | AC321: =P321 -> 0 | AD321: =Q321 -> 0 | AE321: =R321 -> 7 | AF321: =S321 -> 10 | AG321: =SUM(Z321:AF321) -> 214 | AH321: =Z321-M321 -> 2 | AI321: =AA321-N321 -> 0 | AJ321: =AB321-O321 -> 0 | AK321: =AC321-P321 -> 0 | AL321: =AD321-Q321 -> 0 | AM321: =AE321-R321 -> 0 | AN321: =AF321-S321 -> 0 | AO321: =AG321-T321 -> 2
A322: =1+A321 -> 319 | B322: 3547 | C322: ឈាន | D322: ទឹក | E322: Chhean | F322: Toek | G322: M | H322: 33894 | I322: 43747 | J322: Production | K322: Line5 | L322: Sewing operator | M322: 192 | N322: =ROUNDDOWN(INT($N$1-I322-16)/365,0)+1 -> 3 | O322: 0 | P322: 0 | Q322: 0 | R322: 7 | S322: 10 | T322: =SUM(M322:S322) -> 212 | Z322: =M322+2 -> 194 | AA322: =N322 -> 3 | AB322: =O322 -> 0 | AC322: =P322 -> 0 | AD322: =Q322 -> 0 | AE322: =R322 -> 7 | AF322: =S322 -> 10 | AG322: =SUM(Z322:AF322) -> 214 | AH322: =Z322-M322 -> 2 | AI322: =AA322-N322 -> 0 | AJ322: =AB322-O322 -> 0 | AK322: =AC322-P322 -> 0 | AL322: =AD322-Q322 -> 0 | AM322: =AE322-R322 -> 0 | AN322: =AF322-S322 -> 0 | AO322: =AG322-T322 -> 2
A323: =1+A322 -> 320 | B323: 3298 | C323: អ៊ុំ | D323: សម្បត្តិ | E323: Um | F323: SamBath | G323: F | H323: 34897 | I323: 43746 | J323: Production | K323: Line6 | L323: Sewing operator | M323: 192 | N323: =ROUNDDOWN(INT($N$1-I323-16)/365,0)+1 -> 3 | O323: 0 | P323: 0 | Q323: 0 | R323: 7 | S323: 10 | T323: =SUM(M323:S323) -> 212 | Z323: =M323+2 -> 194 | AA323: =N323 -> 3 | AB323: =O323 -> 0 | AC323: =P323 -> 0 | AD323: =Q323 -> 0 | AE323: =R323 -> 7 | AF323: =S323 -> 10 | AG323: =SUM(Z323:AF323) -> 214 | AH323: =Z323-M323 -> 2 | AI323: =AA323-N323 -> 0 | AJ323: =AB323-O323 -> 0 | AK323: =AC323-P323 -> 0 | AL323: =AD323-Q323 -> 0 | AM323: =AE323-R323 -> 0 | AN323: =AF323-S323 -> 0 | AO323: =AG323-T323 -> 2
A324: =1+A323 -> 321 | B324: 3383 | C324: អ៊ុក | D324: ផាច | E324: Uk | F324: Phach | G324: F | H324: 31640 | I324: 43756 | J324: Production | K324: Line19 | L324: Sewing operator | M324: 192 | N324: =ROUNDDOWN(INT($N$1-I324-16)/365,0)+1 -> 3 | O324: 0 | P324: 0 | Q324: 0 | R324: 7 | S324: 10 | T324: =SUM(M324:S324) -> 212 | Z324: =M324+2 -> 194 | AA324: =N324 -> 3 | AB324: =O324 -> 0 | AC324: =P324 -> 0 | AD324: =Q324 -> 0 | AE324: =R324 -> 7 | AF324: =S324 -> 10 | AG324: =SUM(Z324:AF324) -> 214 | AH324: =Z324-M324 -> 2 | AI324: =AA324-N324 -> 0 | AJ324: =AB324-O324 -> 0 | AK324: =AC324-P324 -> 0 | AL324: =AD324-Q324 -> 0 | AM324: =AE324-R324 -> 0 | AN324: =AF324-S324 -> 0 | AO324: =AG324-T324 -> 2
A325: =1+A324 -> 322 | B325: 3118 | C325: យ៉ាន | D325: ចំរើន | E325: Yan | F325: ChomReun | G325: F | H325: 32202 | I325: 43742 | J325: Production | K325: Line20 | L325: Sewing operator | M325: 192 | N325: =ROUNDDOWN(INT($N$1-I325-16)/365,0)+1 -> 3 | O325: 0 | P325: 0 | Q325: 0 | R325: 7 | S325: 10 | T325: =SUM(M325:S325) -> 212 | U325: 20 | V325: 44197 | W325: Paul | X325: 0.78 | Z325: =M325+2 -> 194 | AA325: =N325 -> 3 | AB325: =O325 -> 0 | AC325: =P325 -> 0 | AD325: =Q325 -> 0 | AE325: =R325 -> 7 | AF325: =S325 -> 10 | AG325: =SUM(Z325:AF325) -> 214 | AH325: =Z325-M325 -> 2 | AI325: =AA325-N325 -> 0 | AJ325: =AB325-O325 -> 0 | AK325: =AC325-P325 -> 0 | AL325: =AD325-Q325 -> 0 | AM325: =AE325-R325 -> 0 | AN325: =AF325-S325 -> 0 | AO325: =AG325-T325 -> 2
A326: =1+A325 -> 323 | B326: 3387 | C326: ខា | D326: សារឹម | E326: Ka | F326: SaRoem | G326: F | H326: 31846 | I326: 43760 | J326: Production | K326: Line2 | L326: Sewing operator | M326: 192 | N326: =ROUNDDOWN(INT($N$1-I326-16)/365,0)+1 -> 3 | O326: 0 | P326: 0 | Q326: 0 | R326: 7 | S326: 10 | T326: =SUM(M326:S326) -> 212 | Z326: =M326+2 -> 194 | AA326: =N326 -> 3 | AB326: =O326 -> 0 | AC326: =P326 -> 0 | AD326: =Q326 -> 0 | AE326: =R326 -> 7 | AF326: =S326 -> 10 | AG326: =SUM(Z326:AF326) -> 214 | AH326: =Z326-M326 -> 2 | AI326: =AA326-N326 -> 0 | AJ326: =AB326-O326 -> 0 | AK326: =AC326-P326 -> 0 | AL326: =AD326-Q326 -> 0 | AM326: =AE326-R326 -> 0 | AN326: =AF326-S326 -> 0 | AO326: =AG326-T326 -> 2
A327: =1+A326 -> 324 | B327: 3353 | C327: រ​ស់ | D327: សារឿន | E327: Ruos | F327: SaRoeurn | G327: F | H327: 29426 | I327: 43755 | J327: Production | K327: Line17 | L327: Sewing operator | M327: 192 | N327: =ROUNDDOWN(INT($N$1-I327-16)/365,0)+1 -> 3 | O327: 0 | P327: 0 | Q327: 0 | R327: 7 | S327: 10 | T327: =SUM(M327:S327) -> 212 | Z327: =M327+2 -> 194 | AA327: =N327 -> 3 | AB327: =O327 -> 0 | AC327: =P327 -> 0 | AD327: =Q327 -> 0 | AE327: =R327 -> 7 | AF327: =S327 -> 10 | AG327: =SUM(Z327:AF327) -> 214 | AH327: =Z327-M327 -> 2 | AI327: =AA327-N327 -> 0 | AJ327: =AB327-O327 -> 0 | AK327: =AC327-P327 -> 0 | AL327: =AD327-Q327 -> 0 | AM327: =AE327-R327 -> 0 | AN327: =AF327-S327 -> 0 | AO327: =AG327-T327 -> 2
A328: =1+A327 -> 325 | B328: 3355 | C328: ធូ | D328: ដានី | E328: Thouk | F328: Dany | G328: F | H328: 29230 | I328: 43755 | J328: Production | K328: Line3 | L328: Sewing operator | M328: 192 | N328: =ROUNDDOWN(INT($N$1-I328-16)/365,0)+1 -> 3 | O328: 0 | P328: 0 | Q328: 0 | R328: 7 | S328: 10 | T328: =SUM(M328:S328) -> 212 | Z328: =M328+2 -> 194 | AA328: =N328 -> 3 | AB328: =O328 -> 0 | AC328: =P328 -> 0 | AD328: =Q328 -> 0 | AE328: =R328 -> 7 | AF328: =S328 -> 10 | AG328: =SUM(Z328:AF328) -> 214 | AH328: =Z328-M328 -> 2 | AI328: =AA328-N328 -> 0 | AJ328: =AB328-O328 -> 0 | AK328: =AC328-P328 -> 0 | AL328: =AD328-Q328 -> 0 | AM328: =AE328-R328 -> 0 | AN328: =AF328-S328 -> 0 | AO328: =AG328-T328 -> 2
A329: =1+A328 -> 326 | B329: 3404 | C329: រុំ | D329: វី | E329: Rom | F329: Vy | G329: F | H329: 34402 | I329: 43761 | J329: Production | K329: Line18 | L329: Sewing operator | M329: 192 | N329: =ROUNDDOWN(INT($N$1-I329-16)/365,0)+1 -> 3 | O329: 0 | P329: 0 | Q329: 0 | R329: 7 | S329: 10 | T329: =SUM(M329:S329) -> 212 | Z329: =M329+2 -> 194 | AA329: =N329 -> 3 | AB329: =O329 -> 0 | AC329: =P329 -> 0 | AD329: =Q329 -> 0 | AE329: =R329 -> 7 | AF329: =S329 -> 10 | AG329: =SUM(Z329:AF329) -> 214 | AH329: =Z329-M329 -> 2 | AI329: =AA329-N329 -> 0 | AJ329: =AB329-O329 -> 0 | AK329: =AC329-P329 -> 0 | AL329: =AD329-Q329 -> 0 | AM329: =AE329-R329 -> 0 | AN329: =AF329-S329 -> 0 | AO329: =AG329-T329 -> 2
A330: =1+A329 -> 327 | B330: 3277 | C330: ចន | D330: សុខញ៉ាញ់ | E330: CHORN | F330: SOK NHANH | G330: M | H330: 34828 | I330: 43746 | J330: ADMINISTRATION | K330: ME | L330: Maiternance | M330: 192 | N330: =ROUNDDOWN(INT($N$1-I330-16)/365,0)+1 -> 3 | O330: 31 | P330: 20 | Q330: 0 | R330: 7 | S330: 10 | T330: =SUM(M330:S330) -> 263 | Z330: =M330+2 -> 194 | AA330: =N330 -> 3 | AB330: =O330 -> 31 | AC330: =P330 -> 20 | AD330: =Q330 -> 0 | AE330: =R330 -> 7 | AF330: =S330 -> 10 | AG330: =SUM(Z330:AF330) -> 265 | AH330: =Z330-M330 -> 2 | AI330: =AA330-N330 -> 0 | AJ330: =AB330-O330 -> 0 | AK330: =AC330-P330 -> 0 | AL330: =AD330-Q330 -> 0 | AM330: =AE330-R330 -> 0 | AN330: =AF330-S330 -> 0 | AO330: =AG330-T330 -> 2
A331: =1+A330 -> 328 | B331: 3638 | C331: ឈឺន | D331: ស្រីមួន | E331: CHHEUN | F331: SREY MUON | G331: F | H331: 34163 | I331: 43754 | J331: Production | K331: Line5 | L331: Sewing operator | M331: 192 | N331: =ROUNDDOWN(INT($N$1-I331-16)/365,0)+1 -> 3 | O331: 0 | P331: 0 | Q331: 0 | R331: 7 | S331: 10 | T331: =SUM(M331:S331) -> 212 | Z331: =M331+2 -> 194 | AA331: =N331 -> 3 | AB331: =O331 -> 0 | AC331: =P331 -> 0 | AD331: =Q331 -> 0 | AE331: =R331 -> 7 | AF331: =S331 -> 10 | AG331: =SUM(Z331:AF331) -> 214 | AH331: =Z331-M331 -> 2 | AI331: =AA331-N331 -> 0 | AJ331: =AB331-O331 -> 0 | AK331: =AC331-P331 -> 0 | AL331: =AD331-Q331 -> 0 | AM331: =AE331-R331 -> 0 | AN331: =AF331-S331 -> 0 | AO331: =AG331-T331 -> 2
A332: =1+A331 -> 329 | B332: 3606 | C332: ផាន់ | D332: សុកៀន | E332: PHAN | F332: SOKIEN | G332: F | H332: 29690 | I332: 43750 | J332: Production | K332: Line5 | L332: Sewing operator | M332: 192 | N332: =ROUNDDOWN(INT($N$1-I332-16)/365,0)+1 -> 3 | O332: 0 | P332: 0 | Q332: 0 | R332: 7 | S332: 10 | T332: =SUM(M332:S332) -> 212 | Z332: =M332+2 -> 194 | AA332: =N332 -> 3 | AB332: =O332 -> 0 | AC332: =P332 -> 0 | AD332: =Q332 -> 0 | AE332: =R332 -> 7 | AF332: =S332 -> 10 | AG332: =SUM(Z332:AF332) -> 214 | AH332: =Z332-M332 -> 2 | AI332: =AA332-N332 -> 0 | AJ332: =AB332-O332 -> 0 | AK332: =AC332-P332 -> 0 | AL332: =AD332-Q332 -> 0 | AM332: =AE332-R332 -> 0 | AN332: =AF332-S332 -> 0 | AO332: =AG332-T332 -> 2
A333: =1+A332 -> 330 | B333: 3637 | C333: ឌី | D333: ស៊ីណា | E333: DY | F333: SINA | G333: F | H333: 29805 | I333: 43754 | J333: Production | K333: Line5 | L333: Sewing operator | M333: 192 | N333: =ROUNDDOWN(INT($N$1-I333-16)/365,0)+1 -> 3 | O333: 0 | P333: 0 | Q333: 0 | R333: 7 | S333: 10 | T333: =SUM(M333:S333) -> 212 | Z333: =M333+2 -> 194 | AA333: =N333 -> 3 | AB333: =O333 -> 0 | AC333: =P333 -> 0 | AD333: =Q333 -> 0 | AE333: =R333 -> 7 | AF333: =S333 -> 10 | AG333: =SUM(Z333:AF333) -> 214 | AH333: =Z333-M333 -> 2 | AI333: =AA333-N333 -> 0 | AJ333: =AB333-O333 -> 0 | AK333: =AC333-P333 -> 0 | AL333: =AD333-Q333 -> 0 | AM333: =AE333-R333 -> 0 | AN333: =AF333-S333 -> 0 | AO333: =AG333-T333 -> 2
A334: =1+A333 -> 331 | B334: 3639 | C334: វុទ្ធី | D334: ម៉ានី | E334: VUTHY | F334: MANY | G334: F | H334: 33614 | I334: 43753 | J334: Production | K334: Line8 | L334: Sewing operator | M334: 192 | N334: =ROUNDDOWN(INT($N$1-I334-16)/365,0)+1 -> 3 | O334: 0 | P334: 0 | Q334: 0 | R334: 7 | S334: 10 | T334: =SUM(M334:S334) -> 212 | Z334: =M334+2 -> 194 | AA334: =N334 -> 3 | AB334: =O334 -> 0 | AC334: =P334 -> 0 | AD334: =Q334 -> 0 | AE334: =R334 -> 7 | AF334: =S334 -> 10 | AG334: =SUM(Z334:AF334) -> 214 | AH334: =Z334-M334 -> 2 | AI334: =AA334-N334 -> 0 | AJ334: =AB334-O334 -> 0 | AK334: =AC334-P334 -> 0 | AL334: =AD334-Q334 -> 0 | AM334: =AE334-R334 -> 0 | AN334: =AF334-S334 -> 0 | AO334: =AG334-T334 -> 2
A335: =1+A334 -> 332 | B335: 3197 | C335: យ៉ាវ | D335: ស៊ីណែត | E335: YAV | F335: SINAET | G335: F | H335: 30900 | I335: 43742 | J335: Production | K335: Line5 | L335: Sewing operator | M335: 192 | N335: =ROUNDDOWN(INT($N$1-I335-16)/365,0)+1 -> 3 | O335: 0 | P335: 0 | Q335: 0 | R335: 7 | S335: 10 | T335: =SUM(M335:S335) -> 212 | Z335: =M335+2 -> 194 | AA335: =N335 -> 3 | AB335: =O335 -> 0 | AC335: =P335 -> 0 | AD335: =Q335 -> 0 | AE335: =R335 -> 7 | AF335: =S335 -> 10 | AG335: =SUM(Z335:AF335) -> 214 | AH335: =Z335-M335 -> 2 | AI335: =AA335-N335 -> 0 | AJ335: =AB335-O335 -> 0 | AK335: =AC335-P335 -> 0 | AL335: =AD335-Q335 -> 0 | AM335: =AE335-R335 -> 0 | AN335: =AF335-S335 -> 0 | AO335: =AG335-T335 -> 2
A336: =1+A335 -> 333 | B336: 3605 | C336: ឱ | D336: ចិន្តា | E336: OR | F336: CHENDA | G336: F | H336: 33947 | I336: 43753 | J336: Production | K336: Line1 | L336: Sewing operator | M336: 192 | N336: =ROUNDDOWN(INT($N$1-I336-16)/365,0)+1 -> 3 | O336: 0 | P336: 0 | Q336: 0 | R336: 7 | S336: 10 | T336: =SUM(M336:S336) -> 212 | Z336: =M336+2 -> 194 | AA336: =N336 -> 3 | AB336: =O336 -> 0 | AC336: =P336 -> 0 | AD336: =Q336 -> 0 | AE336: =R336 -> 7 | AF336: =S336 -> 10 | AG336: =SUM(Z336:AF336) -> 214 | AH336: =Z336-M336 -> 2 | AI336: =AA336-N336 -> 0 | AJ336: =AB336-O336 -> 0 | AK336: =AC336-P336 -> 0 | AL336: =AD336-Q336 -> 0 | AM336: =AE336-R336 -> 0 | AN336: =AF336-S336 -> 0 | AO336: =AG336-T336 -> 2
A337: =1+A336 -> 334 | B337: 3255 | C337: អ៊ិន | D337: ចាន់ចាវ | E337: IN | F337: CHANCHAV | G337: M | H337: 34360 | I337: 43745 | J337: Production | K337: Cutting | L337: helper | M337: 192 | N337: =ROUNDDOWN(INT($N$1-I337-16)/365,0)+1 -> 3 | O337: 0 | P337: 20 | Q337: 0 | R337: 7 | S337: 10 | T337: =SUM(M337:S337) -> 232 | Z337: =M337+2 -> 194 | AA337: =N337 -> 3 | AB337: =O337 -> 0 | AC337: =P337 -> 20 | AD337: =Q337 -> 0 | AE337: =R337 -> 7 | AF337: =S337 -> 10 | AG337: =SUM(Z337:AF337) -> 234 | AH337: =Z337-M337 -> 2 | AI337: =AA337-N337 -> 0 | AJ337: =AB337-O337 -> 0 | AK337: =AC337-P337 -> 0 | AL337: =AD337-Q337 -> 0 | AM337: =AE337-R337 -> 0 | AN337: =AF337-S337 -> 0 | AO337: =AG337-T337 -> 2
... A408: =1+A407 -> 405 | B408: 3867 | C408: ម | D408: អៀង | E408: MOR | F408: EANG | G408: F | H408: 31872 | I408: 43773 | J408: Production | K408: Line10 | L408: Sewing operator | M408: 192 | N408: =ROUNDDOWN(INT($N$1-I408-16)/365,0)+1 -> 3 | O408: 0 | P408: 0 | Q408: 0 | R408: 7 | S408: 10 | T408: =SUM(M408:S408) -> 212 | Z408: =M408+2 -> 194 | AA408: =N408 -> 3 | AB408: =O408 -> 0 | AC408: =P408 -> 0 | AD408: =Q408 -> 0 | AE408: =R408 -> 7 | AF408: =S408 -> 10 | AG408: =SUM(Z408:AF408) -> 214 | AH408: =Z408-M408 -> 2 | AI408: =AA408-N408 -> 0 | AJ408: =AB408-O408 -> 0 | AK408: =AC408-P408 -> 0 | AL408: =AD408-Q408 -> 0 | AM408: =AE408-R408 -> 0 | AN408: =AF408-S408 -> 0 | AO408: =AG408-T408 -> 2
A409: =1+A408 -> 406 | B409: 3472 | C409: យ៉ន | D409: ចាន់ធឿន | E409: YORN | F409: CHANTHOEURN | G409: F | H409: 36923 | I409: 43810 | J409: Production | K409: Line1 | L409: Sewing operator | M409: 192 | N409: =ROUNDDOWN(INT($N$1-I409-16)/365,0)+1 -> 3 | O409: 0 | P409: 10 | Q409: 0 | R409: 7 | S409: 10 | Z409: =M409+2 -> 194 | AA409: =N409 -> 3 | AB409: =O409 -> 0 | AC409: =P409 -> 10 | AD409: =Q409 -> 0 | AE409: =R409 -> 7 | AF409: =S409 -> 10 | AG409: =SUM(Z409:AF409) -> 224
A410: =1+A409 -> 407 | B410: 3884 | C410: យ៉ុង | D410: ធារ៉ា | E410: YONG | F410: THEARA | G410: F | H410: 32266 | I410: 43781 | J410: Production | K410: QC B | L410: Inspector | M410: 192 | N410: =ROUNDDOWN(INT($N$1-I410-16)/365,0)+1 -> 3 | O410: 0 | P410: 0 | Q410: 0 | R410: 7 | S410: 10 | T410: =SUM(M410:S410) -> 212 | U410: -10 | V410: 44197 | W410: Paul | X410: 0.6 | Z410: =M410+2 -> 194 | AA410: =N410 -> 3 | AB410: =O410 -> 0 | AC410: =P410 -> 0 | AD410: =Q410 -> 0 | AE410: =R410 -> 7 | AF410: =S410 -> 10 | AG410: =SUM(Z410:AF410) -> 214 | AH410: =Z410-M410 -> 2 | AI410: =AA410-N410 -> 0 | AJ410: =AB410-O410 -> 0 | AK410: =AC410-P410 -> 0 | AL410: =AD410-Q410 -> 0 | AM410: =AE410-R410 -> 0 | AN410: =AF410-S410 -> 0 | AO410: =AG410-T410 -> 2
A411: =1+A410 -> 408 | B411: 3861 | C411: អ៊ុង | D411: ស្រីអូន | E411: UNG | F411: SREI ON | G411: F | H411: 31085 | I411: 43772 | J411: Production | K411: QC A | L411: Inspector | M411: 192 | N411: =ROUNDDOWN(INT($N$1-I411-16)/365,0)+1 -> 3 | O411: 0 | P411: 0 | Q411: 0 | R411: 7 | S411: 10 | T411: =SUM(M411:S411) -> 212 | U411: 120 | V411: 44197 | W411: Paul | X411: 0.92 | Z411: =M411+2 -> 194 | AA411: =N411 -> 3 | AB411: =O411 -> 0 | AC411: =P411 -> 0 | AD411: =Q411 -> 0 | AE411: =R411 -> 7 | AF411: =S411 -> 10 | AG411: =SUM(Z411:AF411) -> 214 | AH411: =Z411-M411 -> 2 | AI411: =AA411-N411 -> 0 | AJ411: =AB411-O411 -> 0 | AK411: =AC411-P411 -> 0 | AL411: =AD411-Q411 -> 0 | AM411: =AE411-R411 -> 0 | AN411: =AF411-S411 -> 0 | AO411: =AG411-T411 -> 2
A412: =1+A411 -> 409 | B412: 3864 | C412: ឡុង | D412: សុខនីម | E412: LONG | F412: SOKNIM | G412: F | H412: 30810 | I412: 43802 | J412: Production | K412: Line2 | L412: Sewing operator | M412: 192 | N412: =ROUNDDOWN(INT($N$1-I412-16)/365,0)+1 -> 3 | O412: 0 | P412: 0 | Q412: 0 | R412: 7 | S412: 10 | T412: =SUM(M412:S412) -> 212 | Z412: =M412+2 -> 194 | AA412: =N412 -> 3 | AB412: =O412 -> 0 | AC412: =P412 -> 0 | AD412: =Q412 -> 0 | AE412: =R412 -> 7 | AF412: =S412 -> 10 | AG412: =SUM(Z412:AF412) -> 214 | AH412: =Z412-M412 -> 2 | AI412: =AA412-N412 -> 0 | AJ412: =AB412-O412 -> 0 | AK412: =AC412-P412 -> 0 | AL412: =AD412-Q412 -> 0 | AM412: =AE412-R412 -> 0 | AN412: =AF412-S412 -> 0 | AO412: =AG412-T412 -> 2
A413: =1+A412 -> 410 | B413: 3860 | C413: ថូន | D413: ពៅ | E413: THON | F413: POV | G413: F | H413: 33334 | I413: 43801 | J413: Production | K413: Line15 | L413: Sewing operator | M413: 192 | N413: =ROUNDDOWN(INT($N$1-I413-16)/365,0)+1 -> 3 | O413: 0 | P413: 0 | Q413: 0 | R413: 7 | S413: 10 | T413: =SUM(M413:S413) -> 212 | Z413: =M413+2 -> 194 | AA413: =N413 -> 3 | AB413: =O413 -> 0 | AC413: =P413 -> 0 | AD413: =Q413 -> 0 | AE413: =R413 -> 7 | AF413: =S413 -> 10 | AG413: =SUM(Z413:AF413) -> 214 | AH413: =Z413-M413 -> 2 | AI413: =AA413-N413 -> 0 | AJ413: =AB413-O413 -> 0 | AK413: =AC413-P413 -> 0 | AL413: =AD413-Q413 -> 0 | AM413: =AE413-R413 -> 0 | AN413: =AF413-S413 -> 0 | AO413: =AG413-T413 -> 2
A414: =1+A413 -> 411 | B414: 3890 | C414: គីត | D414: ភឿន | E414: KIT | F414: PHOEURN | G414: F | H414: 30848 | I414: 43785 | J414: Production | K414: Line3 | L414: Sewing operator | M414: 192 | N414: =ROUNDDOWN(INT($N$1-I414-16)/365,0)+1 -> 3 | O414: 0 | P414: 0 | Q414: 0 | R414: 7 | S414: 10 | T414: =SUM(M414:S414) -> 212 | Z414: =M414+2 -> 194 | AA414: =N414 -> 3 | AB414: =O414 -> 0 | AC414: =P414 -> 0 | AD414: =Q414 -> 0 | AE414: =R414 -> 7 | AF414: =S414 -> 10 | AG414: =SUM(Z414:AF414) -> 214 | AH414: =Z414-M414 -> 2 | AI414: =AA414-N414 -> 0 | AJ414: =AB414-O414 -> 0 | AK414: =AC414-P414 -> 0 | AL414: =AD414-Q414 -> 0 | AM414: =AE414-R414 -> 0 | AN414: =AF414-S414 -> 0 | AO414: =AG414-T414 -> 2
A415: =1+A414 -> 412 | B415: 3465 | C415: កាក់ | D415: បឿន | E415: KAK | F415: BOEUN | G415: F | H415: 29440 | I415: 43772 | J415: Production | K415: Line21 | L415: Sewing operator | M415: 192 | N415: =ROUNDDOWN(INT($N$1-I415-16)/365,0)+1 -> 3 | O415: 0 | P415: 0 | Q415: 0 | R415: 7 | S415: 10 | T415: =SUM(M415:S415) -> 212 | Z415: =M415+2 -> 194 | AA415: =N415 -> 3 | AB415: =O415 -> 0 | AC415: =P415 -> 0 | AD415: =Q415 -> 0 | AE415: =R415 -> 7 | AF415: =S415 -> 10 | AG415: =SUM(Z415:AF415) -> 214 | AH415: =Z415-M415 -> 2 | AI415: =AA415-N415 -> 0 | AJ415: =AB415-O415 -> 0 | AK415: =AC415-P415 -> 0 | AL415: =AD415-Q415 -> 0 | AM415: =AE415-R415 -> 0 | AN415: =AF415-S415 -> 0 | AO415: =AG415-T415 -> 2
A416: =1+A415 -> 413 | B416: 3463 | C416: មុំ | D416: លី | E416: MOM | F416: LY | G416: F | H416: 23257 | I416: 43772 | J416: ADMINISTRATION | K416: GA | L416: Cleaner | M416: 192 | N416: =ROUNDDOWN(INT($N$1-I416-16)/365,0)+1 -> 3 | O416: 0 | P416: 0 | Q416: 0 | R416: 7 | S416: 10 | T416: =SUM(M416:S416) -> 212 | Z416: =M416+2 -> 194 | AA416: =N416 -> 3 | AB416: =O416 -> 0 | AC416: =P416 -> 0 | AD416: =Q416 -> 0 | AE416: =R416 -> 7 | AF416: =S416 -> 10 | AG416: =SUM(Z416:AF416) -> 214 | AH416: =Z416-M416 -> 2 | AI416: =AA416-N416 -> 0 | AJ416: =AB416-O416 -> 0 | AK416: =AC416-P416 -> 0 | AL416: =AD416-Q416 -> 0 | AM416: =AE416-R416 -> 0 | AN416: =AF416-S416 -> 0 | AO416: =AG416-T416 -> 2
A417: =1+A416 -> 414 | B417: 3488 | C417: វ៉ឹង | D417: កែវ | E417: VOENG | F417: KEO | G417: F | H417: 27357 | I417: 43786 | J417: Production | K417: Line3 | L417: Sewing operator | M417: 192 | N417: =ROUNDDOWN(INT($N$1-I417-16)/365,0)+1 -> 3 | O417: 0 | P417: 0 | Q417: 0 | R417: 7 | S417: 10 | T417: =SUM(M417:S417) -> 212 | Z417: =M417+2 -> 194 | AA417: =N417 -> 3 | AB417: =O417 -> 0 | AC417: =P417 -> 0 | AD417: =Q417 -> 0 | AE417: =R417 -> 7 | AF417: =S417 -> 10 | AG417: =SUM(Z417:AF417) -> 214 | AH417: =Z417-M417 -> 2 | AI417: =AA417-N417 -> 0 | AJ417: =AB417-O417 -> 0 | AK417: =AC417-P417 -> 0 | AL417: =AD417-Q417 -> 0 | AM417: =AE417-R417 -> 0 | AN417: =AF417-S417 -> 0 | AO417: =AG417-T417 -> 2
A418: =1+A417 -> 415 | B418: 3484 | C418: វុន | D418: ហៀង | E418: VUN | F418: HIENG | G418: F | H418: 27853 | I418: 43813 | J418: Production | K418: Sample | L418: SL sewer | M418: 192 | N418: =ROUNDDOWN(INT($N$1-I418-16)/365,0)+1 -> 3 | O418: 0 | P418: 0 | Q418: 0 | R418: 7 | S418: 10 | T418: =SUM(M418:S418) -> 212 | Z418: =M418+2 -> 194 | AA418: =N418 -> 3 | AB418: =O418 -> 0 | AC418: =P418 -> 0 | AD418: =Q418 -> 0 | AE418: =R418 -> 7 | AF418: =S418 -> 10 | AG418: =SUM(Z418:AF418) -> 214 | AH418: =Z418-M418 -> 2 | AI418: =AA418-N418 -> 0 | AJ418: =AB418-O418 -> 0 | AK418: =AC418-P418 -> 0 | AL418: =AD418-Q418 -> 0 | AM418: =AE418-R418 -> 0 | AN418: =AF418-S418 -> 0 | AO418: =AG418-T418 -> 2
A419: =1+A418 -> 416 | B419: 3486 | C419: សេក | D419: សំភ័ស្ស | E419: SEK | F419: SAMPHOIS | G419: F | H419: 35662 | I419: 43786 | J419: Production | K419: Line17 | L419: Assist.Line 17 | M419: 192 | N419: =ROUNDDOWN(INT($N$1-I419-16)/365,0)+1 -> 3 | O419: 0 | P419: 10 | Q419: 0 | R419: 7 | S419: 10 | T419: =SUM(M419:S419) -> 222 | Z419: =M419+2 -> 194 | AA419: =N419 -> 3 | AB419: =O419 -> 0 | AC419: =P419 -> 10 | AD419: =Q419 -> 0 | AE419: =R419 -> 7 | AF419: =S419 -> 10 | AG419: =SUM(Z419:AF419) -> 224 | AH419: =Z419-M419 -> 2 | AI419: =AA419-N419 -> 0 | AJ419: =AB419-O419 -> 0 | AK419: =AC419-P419 -> 0 | AL419: =AD419-Q419 -> 0 | AM419: =AE419-R419 -> 0 | AN419: =AF419-S419 -> 0 | AO419: =AG419-T419 -> 2
A420: =1+A419 -> 417 | B420: 3904 | C420: ទែល | D420: ឡៃ | E420: TEL | F420: LAI | G420: F | H420: 30438 | I420: 43801 | J420: Production | K420: Line5 | L420: Sewing operator | M420: 192 | N420: =ROUNDDOWN(INT($N$1-I420-16)/365,0)+1 -> 3 | O420: 0 | P420: 0 | Q420: 0 | R420: 7 | S420: 10 | T420: =SUM(M420:S420) -> 212 | Z420: =M420+2 -> 194 | AA420: =N420 -> 3 | AB420: =O420 -> 0 | AC420: =P420 -> 0 | AD420: =Q420 -> 0 | AE420: =R420 -> 7 | AF420: =S420 -> 10 | AG420: =SUM(Z420:AF420) -> 214 | AH420: =Z420-M420 -> 2 | AI420: =AA420-N420 -> 0 | AJ420: =AB420-O420 -> 0 | AK420: =AC420-P420 -> 0 | AL420: =AD420-Q420 -> 0 | AM420: =AE420-R420 -> 0 | AN420: =AF420-S420 -> 0 | AO420: =AG420-T420 -> 2
A421: =1+A420 -> 418 | B421: 3915 | C421: សៅ | D421: ស្រីពេជ | E421: SAO | F421: SREYPICH | G421: F | H421: 35796 | I421: 43802 | J421: Production | K421: Line3 | L421: Sewing operator | M421: 192 | N421: =ROUNDDOWN(INT($N$1-I421-16)/365,0)+1 -> 3 | O421: 0 | P421: 0 | Q421: 0 | R421: 7 | S421: 10 | T421: =SUM(M421:S421) -> 212 | Z421: =M421+2 -> 194 | AA421: =N421 -> 3 | AB421: =O421 -> 0 | AC421: =P421 -> 0 | AD421: =Q421 -> 0 | AE421: =R421 -> 7 | AF421: =S421 -> 10 | AG421: =SUM(Z421:AF421) -> 214 | AH421: =Z421-M421 -> 2 | AI421: =AA421-N421 -> 0 | AJ421: =AB421-O421 -> 0 | AK421: =AC421-P421 -> 0 | AL421: =AD421-Q421 -> 0 | AM421: =AE421-R421 -> 0 | AN421: =AF421-S421 -> 0 | AO421: =AG421-T421 -> 2
A422: =1+A421 -> 419 | B422: 3918 | C422: ញិល | D422: ឆាំ | E422: NHIL | F422: CHHOM | G422: F | H422: 33734 | I422: 43802 | J422: Production | K422: Line6 | L422: Sewing operator | M422: 192 | N422: =ROUNDDOWN(INT($N$1-I422-16)/365,0)+1 -> 3 | O422: 0 | P422: 0 | Q422: 0 | R422: 7 | S422: 10 | T422: =SUM(M422:S422) -> 212 | Z422: =M422+2 -> 194 | AA422: =N422 -> 3 | AB422: =O422 -> 0 | AC422: =P422 -> 0 | AD422: =Q422 -> 0 | AE422: =R422 -> 7 | AF422: =S422 -> 10 | AG422: =SUM(Z422:AF422) -> 214 | AH422: =Z422-M422 -> 2 | AI422: =AA422-N422 -> 0 | AJ422: =AB422-O422 -> 0 | AK422: =AC422-P422 -> 0 | AL422: =AD422-Q422 -> 0 | AM422: =AE422-R422 -> 0 | AN422: =AF422-S422 -> 0 | AO422: =AG422-T422 -> 2
A423: =1+A422 -> 420 | B423: 3928 | C423: តឹក | D423: សុខា | E423: TOEK | F423: SOKHA | G423: F | H423: 28230 | I423: 43808 | J423: Production | K423: Line6 | L423: Sewing operator | M423: 192 | N423: =ROUNDDOWN(INT($N$1-I423-16)/365,0)+1 -> 3 | O423: 0 | P423: 0 | Q423: 0 | R423: 7 | S423: 10 | T423: =SUM(M423:S423) -> 212 | Z423: =M423+2 -> 194 | AA423: =N423 -> 3 | AB423: =O423 -> 0 | AC423: =P423 -> 0 | AD423: =Q423 -> 0 | AE423: =R423 -> 7 | AF423: =S423 -> 10 | AG423: =SUM(Z423:AF423) -> 214 | AH423: =Z423-M423 -> 2 | AI423: =AA423-N423 -> 0 | AJ423: =AB423-O423 -> 0 | AK423: =AC423-P423 -> 0 | AL423: =AD423-Q423 -> 0 | AM423: =AE423-R423 -> 0 | AN423: =AF423-S423 -> 0 | AO423: =AG423-T423 -> 2
... A512: =1+A511 -> 509 | B512: 5002 | C512: អ៊ុក | D512: ស្រីណូ | E512: OUK | F512: SREYNO | G512: F | H512: 34713 | I512: 44139 | J512: Production | K512: Warehouse Trims | L512: accessory assistant | M512: 192 | N512: =ROUNDDOWN(INT($N$1-I512-16)/365,0)+1 -> 2 | O512: 0 | P512: 0 | Q512: 0 | R512: 7 | S512: 10 | T512: =SUM(M512:S512) -> 211 | Z512: =M512+2 -> 194 | AA512: =N512 -> 2 | AB512: =O512 -> 0 | AC512: =P512 -> 0 | AD512: =Q512 -> 0 | AE512: =R512 -> 7 | AF512: =S512 -> 10 | AG512: =SUM(Z512:AF512) -> 213 | AH512: =Z512-M512 -> 2 | AI512: =AA512-N512 -> 0 | AJ512: =AB512-O512 -> 0 | AK512: =AC512-P512 -> 0 | AL512: =AD512-Q512 -> 0 | AM512: =AE512-R512 -> 0 | AN512: =AF512-S512 -> 0 | AO512: =AG512-T512 -> 2
A513: =1+A512 -> 510 | B513: 5056 | C513: គុយ | D513: ចាន់សុខ | E513: KUY | F513: CHANSOK | G513: M | H513: 30486 | I513: 44153 | J513: Production | K513: Packing A | L513: Packer | M513: 192 | N513: 0 | O513: 0 | P513: 0 | Q513: 0 | R513: 7 | S513: 10 | T513: =SUM(M513:S513) -> 209 | Z513: =M513+2 -> 194 | AA513: =N513 -> 0 | AB513: =O513 -> 0 | AC513: =P513 -> 0 | AD513: =Q513 -> 0 | AE513: =R513 -> 7 | AF513: =S513 -> 10 | AG513: =SUM(Z513:AF513) -> 211 | AH513: =Z513-M513 -> 2 | AI513: =AA513-N513 -> 0 | AJ513: =AB513-O513 -> 0 | AK513: =AC513-P513 -> 0 | AL513: =AD513-Q513 -> 0 | AM513: =AE513-R513 -> 0 | AN513: =AF513-S513 -> 0 | AO513: =AG513-T513 -> 2
A514: =1+A513 -> 511 | B514: 5062 | C514: យឹម | D514: រ៉ាន | E514: YOEM | F514: RAN | G514: F | H514: 34188 | I514: 44166 | J514: Production | K514: Line5 | L514: Sewing operator | M514: 192 | N514: 0 | O514: 0 | P514: 0 | Q514: 0 | R514: 7 | S514: 10 | T514: =SUM(M514:S514) -> 209 | Z514: =M514+2 -> 194 | AA514: =N514 -> 0 | AB514: =O514 -> 0 | AC514: =P514 -> 0 | AD514: =Q514 -> 0 | AE514: =R514 -> 7 | AF514: =S514 -> 10 | AG514: =SUM(Z514:AF514) -> 211 | AH514: =Z514-M514 -> 2 | AI514: =AA514-N514 -> 0 | AJ514: =AB514-O514 -> 0 | AK514: =AC514-P514 -> 0 | AL514: =AD514-Q514 -> 0 | AM514: =AE514-R514 -> 0 | AN514: =AF514-S514 -> 0 | AO514: =AG514-T514 -> 2
A515: =1+A514 -> 512 | B515: 5081 | C515: លុន | D515: ស្រីតូច | E515: LUN | F515: SREYTOCH | G515: F | H515: 32217 | I515: 44167 | J515: Production | K515: Line15 | L515: Sewing operator | M515: 192 | N515: 0 | O515: 0 | P515: 0 | Q515: 0 | R515: 7 | S515: 10 | T515: =SUM(M515:S515) -> 209 | Z515: =M515+2 -> 194 | AA515: =N515 -> 0 | AB515: =O515 -> 0 | AC515: =P515 -> 0 | AD515: =Q515 -> 0 | AE515: =R515 -> 7 | AF515: =S515 -> 10 | AG515: =SUM(Z515:AF515) -> 211 | AH515: =Z515-M515 -> 2 | AI515: =AA515-N515 -> 0 | AJ515: =AB515-O515 -> 0 | AK515: =AC515-P515 -> 0 | AL515: =AD515-Q515 -> 0 | AM515: =AE515-R515 -> 0 | AN515: =AF515-S515 -> 0 | AO515: =AG515-T515 -> 2
A516: =1+A515 -> 513 | B516: 5073 | C516: ចាយ | D516: ស | E516: CHAY | F516: SORN | G516: F | H516: 29683 | I516: 44167 | J516: Production | K516: Line15 | L516: Sewing operator | M516: 192 | N516: 0 | O516: 0 | P516: 0 | Q516: 0 | R516: 7 | S516: 10 | T516: =SUM(M516:S516) -> 209 | Z516: =M516+2 -> 194 | AA516: =N516 -> 0 | AB516: =O516 -> 0 | AC516: =P516 -> 0 | AD516: =Q516 -> 0 | AE516: =R516 -> 7 | AF516: =S516 -> 10 | AG516: =SUM(Z516:AF516) -> 211 | AH516: =Z516-M516 -> 2 | AI516: =AA516-N516 -> 0 | AJ516: =AB516-O516 -> 0 | AK516: =AC516-P516 -> 0 | AL516: =AD516-Q516 -> 0 | AM516: =AE516-R516 -> 0 | AN516: =AF516-S516 -> 0 | AO516: =AG516-T516 -> 2
...

Sheet Office
A1: ល.រ | B1: Factory ID | C1: គោត្តនាម | D1: នាម | E1: គោត្តនាមឡាតាំង | F1: នាមឡាតាំង | G1: ភេទ | H1: ថ្ងៃខែឆ្នាំកំណើត | I1: កាលបរិ. ចូលធ្វើការ | J1: ផ្នែក | K1: ក្រុម | L1: តួនាទី | M1: Salary Report 2021 | U1: Adjust amount | V1: Adjust Date | W1: Evaluator | X1: 2022 Total Marks | Y1: With Comment | Z1: Salary Report 2022
A2: Nº | B2: Factory ID | C2: Khmer Sure name | D2: Khmer Name | E2: English Sure name | F2: Khmer Name | G2: Sex | H2: Birth of Date | I2: Join Date | J2: Department | K2: Group | L2: Position | M2: Basic | N2: Seniority | O2: Skill | P2: Position | Q2: Language | R2: Housing &Transportation | S2: Motivation | T2: Total | U2: 調動金額 | V2: 調動日期 | W2: 評核人 | X2: 2022總分 | Y2: 意見 | Z2: Basic | AA2: Seniority | AB2: Skill | AC2: Position | AD2: Language | AE2: Housing &Transportation | AF2: Motivation | AG2: Total
A3: 排序 | B3: 工號 | E3: 姓名 | G3: 性別 | H3: 生日 | I3: 入職日期 | J3: 部門 | K3: 組別 | L3: 崗位名稱 | M3: 底薪 | N3: 工齡 | O3: 技能 | P3: 職位 | Q3: 語言 | R3: 房屋/交通 | S3: 全勤 | T3: 2021薪資總額 | U3: 調動金額 | V3: 調動日期 | W3: 評核人 | X3: 2022總分 | Y3: 意見 | Z3: 底薪 | AA3: 工齡 | AB3: 技能 | AC3: 職位 | AD3: 語言 | AE3: 房屋/交通 | AF3: 全勤 | AG3: 2022薪資總額
A4: =1 -> 1 | B4: 2037 | C4: =VLOOKUP(B4,All!$B$4:$S$8977,2,FALSE) -> សៀង | D4: =VLOOKUP(B4,All!$B$4:$S$89977,3,FALSE) -> វាសនា | E4: =VLOOKUP(B4,All!$B$4:$S$8977,4,FALSE) -> SEANG | F4: =VLOOKUP(B4,All!$B$4:$S$8977,5,FALSE) -> VEASNA | G4: =VLOOKUP(B4,All!$B$4:$S$8977,6,FALSE) -> M | H4: =VLOOKUP(B4,All!$B$4:$S$8977,7,FALSE) -> 31810 | I4: =VLOOKUP(B4,All!$B$4:$S$8977,8,FALSE) -> 42917 | J4: =VLOOKUP(B4,All!$B$4:$S$8977,9,FALSE) -> Shipping | K4: =VLOOKUP(B4,All!$B$4:$S$8977,10,FALSE) -> Export | L4: =VLOOKUP(B4,All!$B$4:$S$8977,11,FALSE) -> assistant | M4: =VLOOKUP(B4,All!$B$4:$S$8977,12,FALSE) -> 192 | N4: =VLOOKUP(B4,All!$B$4:$S$8977,13,FALSE) -> 5 | O4: =VLOOKUP(B4,All!$B$4:$S$8977,14,FALSE) -> 20 | P4: =VLOOKUP(B4,All!$B$4:$S$8977,15,FALSE) -> 200 | Q4: =VLOOKUP(B4,All!$B$4:$S$8977,16,FALSE) -> 50 | R4: 7 | S4: 10 | T4: =SUM(M4:S4) -> 484 | U4: 30 | V4: 44562 | W4: Jerry | Y4: 出口助理 | Z4: =M4+AH4 -> 194 | AA4: =N4 -> 5 | AB4: =O4 -> 20 | AC4: =P4+U4 -> 230 | AD4: =Q4 -> 50 | AE4: =R4 -> 7 | AF4: =S4 -> 10 | AG4: =SUM(Z4:AF4) -> 516 | AH4: 2 | AI4: =AA4-N4 -> 0 | AJ4: =AB4-O4 -> 0 | AK4: =AC4-P4 -> 30 | AL4: =AD4-Q4 -> 0 | AM4: =AE4-R4 -> 0 | AN4: =AF4-S4 -> 0 | AO4: =AG4-T4 -> 32
A5: =1+A4 -> 2 | B5: 3083 | C5: =VLOOKUP(B5,All!$B$4:$S$8977,2,FALSE) -> សន់ | D5: =VLOOKUP(B5,All!$B$4:$S$89977,3,FALSE) -> សុរ៉ាន់ដា | E5: =VLOOKUP(B5,All!$B$4:$S$8977,4,FALSE) -> Son | F5: =VLOOKUP(B5,All!$B$4:$S$8977,5,FALSE) -> Sorannda | G5: =VLOOKUP(B5,All!$B$4:$S$8977,6,FALSE) -> M | H5: =VLOOKUP(B5,All!$B$4:$S$8977,7,FALSE) -> 34992 | I5: =VLOOKUP(B5,All!$B$4:$S$8977,8,FALSE) -> 43620 | J5: IT | L5: =VLOOKUP(B5,All!$B$4:$S$8977,11,FALSE) -> IT specialist | M5: =VLOOKUP(B5,All!$B$4:$S$8977,12,FALSE) -> 192 | N5: =VLOOKUP(B5,All!$B$4:$S$8977,13,FALSE) -> 3 | O5: =VLOOKUP(B5,All!$B$4:$S$8977,14,FALSE) -> 163 | P5: =VLOOKUP(B5,All!$B$4:$S$8977,15,FALSE) -> 208 | Q5: =VLOOKUP(B5,All!$B$4:$S$8977,16,FALSE) -> 10 | R5: 7 | S5: 10 | T5: =SUM(M5:S5) -> 593 | U5: 30 | V5: 44562 | W5: Jerry | Y5: IT專員 | Z5: =M5+AH5 -> 194 | AA5: =N5 -> 3 | AB5: =O5 -> 163 | AC5: =P5+U5 -> 238 | AD5: =Q5 -> 10 | AE5: =R5 -> 7 | AF5: =S5 -> 10 | AG5: =SUM(Z5:AF5) -> 625 | AH5: 2 | AI5: =AA5-N5 -> 0 | AJ5: =AB5-O5 -> 0 | AK5: =AC5-P5 -> 30 | AL5: =AD5-Q5 -> 0 | AM5: =AE5-R5 -> 0 | AN5: =AF5-S5 -> 0 | AO5: =AG5-T5 -> 32
A6: =1+A5 -> 3 | B6: 3426 | C6: =VLOOKUP(B6,All!$B$4:$S$8977,2,FALSE) -> ប៉ុក | D6: =VLOOKUP(B6,All!$B$4:$S$89977,3,FALSE) -> ដាវុទ្ធា | E6: =VLOOKUP(B6,All!$B$4:$S$8977,4,FALSE) -> POK | F6: =VLOOKUP(B6,All!$B$4:$S$8977,5,FALSE) -> DAVUTHEA | G6: =VLOOKUP(B6,All!$B$4:$S$8977,6,FALSE) -> M | H6: =VLOOKUP(B6,All!$B$4:$S$8977,7,FALSE) -> 34765 | I6: =VLOOKUP(B6,All!$B$4:$S$8977,8,FALSE) -> 43771 | J6: =VLOOKUP(B6,All!$B$4:$S$8977,9,FALSE) -> Production | K6: =VLOOKUP(B6,All!$B$4:$S$8977,10,FALSE) -> Finish good | L6: =VLOOKUP(B6,All!$B$4:$S$8977,11,FALSE) -> assistant | M6: =VLOOKUP(B6,All!$B$4:$S$8977,12,FALSE) -> 192 | N6: =VLOOKUP(B6,All!$B$4:$S$8977,13,FALSE) -> 3 | O6: =VLOOKUP(B6,All!$B$4:$S$8977,14,FALSE) -> 20 | P6: =VLOOKUP(B6,All!$B$4:$S$8977,15,FALSE) -> 30 | Q6: =VLOOKUP(B6,All!$B$4:$S$8977,16,FALSE) -> 0 | R6: 7 | S6: 10 | T6: =SUM(M6:S6) -> 262 | U6: 15 | V6: 44562 | W6: Jerry | Y6: 成品助理 | Z6: =M6+AH6 -> 194 | AA6: =N6 -> 3 | AB6: =O6 -> 20 | AC6: =P6+U6 -> 45 | AD6: =Q6 -> 0 | AE6: =R6 -> 7 | AF6: =S6 -> 10 | AG6: =SUM(Z6:AF6) -> 279 | AH6: 2 | AI6: =AA6-N6 -> 0 | AJ6: =AB6-O6 -> 0 | AK6: =AC6-P6 -> 15 | AL6: =AD6-Q6 -> 0 | AM6: =AE6-R6 -> 0 | AN6: =AF6-S6 -> 0 | AO6: =AG6-T6 -> 17
A7: =1+A6 -> 4 | B7: 4060 | C7: =VLOOKUP(B7,All!$B$4:$S$8977,2,FALSE) -> លី | D7: =VLOOKUP(B7,All!$B$4:$S$89977,3,FALSE) -> ឡេងចេង | E7: =VLOOKUP(B7,All!$B$4:$S$8977,4,FALSE) -> LY | F7: =VLOOKUP(B7,All!$B$4:$S$8977,5,FALSE) -> LENGCHENG | G7: =VLOOKUP(B7,All!$B$4:$S$8977,6,FALSE) -> F | H7: =VLOOKUP(B7,All!$B$4:$S$8977,7,FALSE) -> 33159 | I7: =VLOOKUP(B7,All!$B$4:$S$8977,8,FALSE) -> 43842 | J7: =VLOOKUP(B7,All!$B$4:$S$8977,9,FALSE) -> Production | K7: =VLOOKUP(B7,All!$B$4:$S$8977,10,FALSE) -> Finish good | L7: =VLOOKUP(B7,All!$B$4:$S$8977,11,FALSE) -> assistant | M7: =VLOOKUP(B7,All!$B$4:$S$8977,12,FALSE) -> 192 | N7: =VLOOKUP(B7,All!$B$4:$S$8977,13,FALSE) -> 3 | O7: =VLOOKUP(B7,All!$B$4:$S$8977,14,FALSE) -> 20 | P7: =VLOOKUP(B7,All!$B$4:$S$8977,15,FALSE) -> 43 | Q7: =VLOOKUP(B7,All!$B$4:$S$8977,16,FALSE) -> 20 | R7: 7 | S7: 10 | T7: =SUM(M7:S7) -> 295 | U7: 15 | V7: 44562 | W7: Jerry | Y7: 成品助理 | Z7: =M7+AH7 -> 194 | AA7: =N7 -> 3 | AB7: =O7 -> 20 | AC7: =P7+U7 -> 58 | AD7: =Q7 -> 20 | AE7: =R7 -> 7 | AF7: =S7 -> 10 | AG7: =SUM(Z7:AF7) -> 312 | AH7: 2 | AI7: =AA7-N7 -> 0 | AJ7: =AB7-O7 -> 0 | AK7: =AC7-P7 -> 15 | AL7: =AD7-Q7 -> 0 | AM7: =AE7-R7 -> 0 | AN7: =AF7-S7 -> 0 | AO7: =AG7-T7 -> 17
A8: =1+A7 -> 5 | B8: 2242 | C8: =VLOOKUP(B8,All!$B$4:$S$8977,2,FALSE) -> វ៉ន | D8: =VLOOKUP(B8,All!$B$4:$S$89977,3,FALSE) -> សុភក្តិ | E8: =VLOOKUP(B8,All!$B$4:$S$8977,4,FALSE) -> VORN | F8: =VLOOKUP(B8,All!$B$4:$S$8977,5,FALSE) -> SOPHEAK | G8: =VLOOKUP(B8,All!$B$4:$S$8977,6,FALSE) -> F | H8: =VLOOKUP(B8,All!$B$4:$S$8977,7,FALSE) -> 34837 | I8: =VLOOKUP(B8,All!$B$4:$S$8977,8,FALSE) -> 42962 | J8: =VLOOKUP(B8,All!$B$4:$S$8977,9,FALSE) -> Production | K8: =VLOOKUP(B8,All!$B$4:$S$8977,10,FALSE) -> PC | L8: =VLOOKUP(B8,All!$B$4:$S$8977,11,FALSE) -> PC assistant | M8: =VLOOKUP(B8,All!$B$4:$S$8977,12,FALSE) -> 192 | N8: =VLOOKUP(B8,All!$B$4:$S$8977,13,FALSE) -> 5 | O8: =VLOOKUP(B8,All!$B$4:$S$8977,14,FALSE) -> 0 | P8: =VLOOKUP(B8,All!$B$4:$S$8977,15,FALSE) -> 153 | Q8: =VLOOKUP(B8,All!$B$4:$S$8977,16,FALSE) -> 40 | R8: 7 | S8: 10 | T8: =SUM(M8:S8) -> 407 | U8: 15 | V8: 44562 | W8: Jerry | Y8: 生管助理 | Z8: =M8+AH8 -> 194 | AA8: =N8 -> 5 | AB8: =O8 -> 0 | AC8: =P8+U8 -> 168 | AD8: =Q8 -> 40 | AE8: =R8 -> 7 | AF8: =S8 -> 10 | AG8: =SUM(Z8:AF8) -> 424 | AH8: 2 | AI8: =AA8-N8 -> 0 | AJ8: =AB8-O8 -> 0 | AK8: =AC8-P8 -> 15 | AL8: =AD8-Q8 -> 0 | AM8: =AE8-R8 -> 0 | AN8: =AF8-S8 -> 0 | AO8: =AG8-T8 -> 17
A9: =1+A8 -> 6 | B9: 2612 | C9: =VLOOKUP(B9,All!$B$4:$S$8977,2,FALSE) -> អ៊ុត | D9: =VLOOKUP(B9,All!$B$4:$S$89977,3,FALSE) -> សូរិយា | E9: =VLOOKUP(B9,All!$B$4:$S$8977,4,FALSE) -> UT | F9: =VLOOKUP(B9,All!$B$4:$S$8977,5,FALSE) -> SORIYA | G9: =VLOOKUP(B9,All!$B$4:$S$8977,6,FALSE) -> F | H9: =VLOOKUP(B9,All!$B$4:$S$8977,7,FALSE) -> 36742 | I9: =VLOOKUP(B9,All!$B$4:$S$8977,8,FALSE) -> 43474 | J9: =VLOOKUP(B9,All!$B$4:$S$8977,9,FALSE) -> Production | K9: =VLOOKUP(B9,All!$B$4:$S$8977,10,FALSE) -> PC | L9: =VLOOKUP(B9,All!$B$4:$S$8977,11,FALSE) -> PC clerk | M9: =VLOOKUP(B9,All!$B$4:$S$8977,12,FALSE) -> 192 | N9: =VLOOKUP(B9,All!$B$4:$S$8977,13,FALSE) -> 4 | O9: =VLOOKUP(B9,All!$B$4:$S$8977,14,FALSE) -> 0 | P9: =VLOOKUP(B9,All!$B$4:$S$8977,15,FALSE) -> 61 | Q9: =VLOOKUP(B9,All!$B$4:$S$8977,16,FALSE) -> 0 | R9: 7 | S9: 10 | T9: =SUM(M9:S9) -> 274 | U9: 10 | V9: 44562 | W9: Jerry | Y9: 生管 | Z9: =M9+AH9 -> 194 | AA9: =N9 -> 4 | AB9: =O9 -> 0 | AC9: =P9+U9 -> 71 | AD9: =Q9 -> 0 | AE9: =R9 -> 7 | AF9: =S9 -> 10 | AG9: =SUM(Z9:AF9) -> 286 | AH9: 2 | AI9: =AA9-N9 -> 0 | AJ9: =AB9-O9 -> 0 | AK9: =AC9-P9 -> 10 | AL9: =AD9-Q9 -> 0 | AM9: =AE9-R9 -> 0 | AN9: =AF9-S9 -> 0 | AO9: =AG9-T9 -> 12
A10: =1+A9 -> 7 | B10: 5055 | C10: =VLOOKUP(B10,All!$B$4:$S$8977,2,FALSE) -> វ៉ន | D10: =VLOOKUP(B10,All!$B$4:$S$89977,3,FALSE) -> គីមហុង | E10: =VLOOKUP(B10,All!$B$4:$S$8977,4,FALSE) -> VORN | F10: =VLOOKUP(B10,All!$B$4:$S$8977,5,FALSE) -> KIMHONG | G10: =VLOOKUP(B10,All!$B$4:$S$8977,6,FALSE) -> M | H10: =VLOOKUP(B10,All!$B$4:$S$8977,7,FALSE) -> 36751 | I10: =VLOOKUP(B10,All!$B$4:$S$8977,8,FALSE) -> 44147 | J10: =VLOOKUP(B10,All!$B$4:$S$8977,9,FALSE) -> Production | K10: =VLOOKUP(B10,All!$B$4:$S$8977,10,FALSE) -> PC | L10: =VLOOKUP(B10,All!$B$4:$S$8977,11,FALSE) -> PC clerk | M10: =VLOOKUP(B10,All!$B$4:$S$8977,12,FALSE) -> 192 | N10: =VLOOKUP(B10,All!$B$4:$S$8977,13,FALSE) -> 2 | O10: =VLOOKUP(B10,All!$B$4:$S$8977,14,FALSE) -> 0 | P10: =VLOOKUP(B10,All!$B$4:$S$8977,15,FALSE) -> 18 | Q10: =VLOOKUP(B10,All!$B$4:$S$8977,16,FALSE) -> 0 | R10: 7 | S10: 10 | T10: =SUM(M10:S10) -> 229 | U10: 10 | V10: 44562 | W10: Jerry | Y10: 生管 | Z10: =M10+AH10 -> 194 | AA10: =N10 -> 2 | AB10: =O10 -> 0 | AC10: =P10+U10 -> 28 | AD10: =Q10 -> 0 | AE10: =R10 -> 7 | AF10: =S10 -> 10 | AG10: =SUM(Z10:AF10) -> 241 | AH10: 2 | AI10: =AA10-N10 -> 0 | AJ10: =AB10-O10 -> 0 | AK10: =AC10-P10 -> 10 | AL10: =AD10-Q10 -> 0 | AM10: =AE10-R10 -> 0 | AN10: =AF10-S10 -> 0 | AO10: =AG10-T10 -> 12
A11: =1+A10 -> 8 | B11: 18 | C11: =VLOOKUP(B11,All!$B$4:$S$8977,2,FALSE) -> ស្រី | D11: =VLOOKUP(B11,All!$B$4:$S$89977,3,FALSE) -> ច័ន្ទថុនា | E11: =VLOOKUP(B11,All!$B$4:$S$8977,4,FALSE) -> Srey | F11: =VLOOKUP(B11,All!$B$4:$S$8977,5,FALSE) -> Chanthuna | G11: =VLOOKUP(B11,All!$B$4:$S$8977,6,FALSE) -> M | H11: =VLOOKUP(B11,All!$B$4:$S$8977,7,FALSE) -> 33771 | I11: =VLOOKUP(B11,All!$B$4:$S$8977,8,FALSE) -> 41577 | J11: Production | K11: Marker | L11: =VLOOKUP(B11,All!$B$4:$S$8977,11,FALSE) -> Marker technicial | M11: =VLOOKUP(B11,All!$B$4:$S$8977,12,FALSE) -> 262 | N11: =VLOOKUP(B11,All!$B$4:$S$8977,13,FALSE) -> 9 | O11: =VLOOKUP(B11,All!$B$4:$S$8977,14,FALSE) -> 20 | P11: =VLOOKUP(B11,All!$B$4:$S$8977,15,FALSE) -> 72 | Q11: =VLOOKUP(B11,All!$B$4:$S$8977,16,FALSE) -> 66 | R11: 7 | S11: 10 | T11: =SUM(M11:S11) -> 446 | U11: 40 | V11: 44562 | W11: Jerry | Y11: 馬克技術員 | Z11: =M11+AH11 -> 264 | AA11: =N11 -> 9 | AB11: =O11 -> 20 | AC11: =P11+U11 -> 112 | AD11: =Q11 -> 66 | AE11: =R11 -> 7 | AF11: =S11 -> 10 | AG11: =SUM(Z11:AF11) -> 488 | AH11: 2 | AI11: =AA11-N11 -> 0 | AJ11: =AB11-O11 -> 0 | AK11: =AC11-P11 -> 40 | AL11: =AD11-Q11 -> 0 | AM11: =AE11-R11 -> 0 | AN11: =AF11-S11 -> 0 | AO11: =AG11-T11 -> 42
A12: =1+A11 -> 9 | B12: 1411 | C12: =VLOOKUP(B12,All!$B$4:$S$8977,2,FALSE) -> រូ | D12: =VLOOKUP(B12,All!$B$4:$S$89977,3,FALSE) -> និច | E12: =VLOOKUP(B12,All!$B$4:$S$8977,4,FALSE) -> Ro | F12: =VLOOKUP(B12,All!$B$4:$S$8977,5,FALSE) -> Nich | G12: =VLOOKUP(B12,All!$B$4:$S$8977,6,FALSE) -> F | H12: =VLOOKUP(B12,All!$B$4:$S$8977,7,FALSE) -> 35831 | I12: =VLOOKUP(B12,All!$B$4:$S$8977,8,FALSE) -> 42343 | J12: Production | K12: Sample | L12: =VLOOKUP(B12,All!$B$4:$S$8977,11,FALSE) -> Sample Coordinator | M12: =VLOOKUP(B12,All!$B$4:$S$8977,12,FALSE) -> 192 | N12: =VLOOKUP(B12,All!$B$4:$S$8977,13,FALSE) -> 7 | O12: =VLOOKUP(B12,All!$B$4:$S$8977,14,FALSE) -> 20 | P12: =VLOOKUP(B12,All!$B$4:$S$8977,15,FALSE) -> 85 | Q12: =VLOOKUP(B12,All!$B$4:$S$8977,16,FALSE) -> 30 | R12: 7 | S12: 10 | T12: =SUM(M12:S12) -> 351 | U12: 40 | V12: 44562 | W12: Jerry | Y12: 樣品安排 | Z12: =M12+AH12 -> 194 | AA12: =N12 -> 7 | AB12: =O12 -> 20 | AC12: =P12+U12 -> 125 | AD12: =Q12 -> 30 | AE12: =R12 -> 7 | AF12: =S12 -> 10 | AG12: =SUM(Z12:AF12) -> 393 | AH12: 2 | AI12: =AA12-N12 -> 0 | AJ12: =AB12-O12 -> 0 | AK12: =AC12-P12 -> 40 | AL12: =AD12-Q12 -> 0 | AM12: =AE12-R12 -> 0 | AN12: =AF12-S12 -> 0 | AO12: =AG12-T12 -> 42
T14: =SUM(T4:T13) -> 3341 | U14: =SUM(U4:U13) -> 205 | AG14: =SUM(AG4:AG13) -> 3564 | AH14: =SUM(AH4:AH13) -> 18 | AJ14: =SUM(AJ4:AJ13) -> 0

Sheet WH F&L
A1: ល.រ | B1: Factory ID | C1: គោត្តនាម | D1: នាម | E1: គោត្តនាមឡាតាំង | F1: នាមឡាតាំង | G1: ភេទ | H1: ថ្ងៃខែឆ្នាំកំណើត | I1: កាលបរិ. ចូលធ្វើការ | J1: ផ្នែក | K1: ក្រុម | L1: តួនាទី | M1: Salary Report 2021 | U1: Adjust amount | V1: Adjust Date | W1: Evaluator | X1: 2022 Total Marks | Y1: With Comment | Z1: Salary Report 2022
A2: Nº | B2: Factory ID | C2: Khmer Sure name | D2: Khmer Name | E2: English Sure name | F2: Khmer Name | G2: Sex | H2: Birth of Date | I2: Join Date | J2: Department | K2: Group | L2: Position | M2: Basic | N2: Seniority | O2: Skill | P2: Position | Q2: Language | R2: Housing &Transportation | S2: Motivation | T2: Total | U2: 調動金額 | V2: 調動日期 | W2: 評核人 | X2: 2022總分 | Y2: 意見 | Z2: Basic | AA2: Seniority | AB2: Skill | AC2: Position | AD2: Language | AE2: Housing &Transportation | AF2: Motivation | AG2: Total
A3: 排序 | B3: 工號 | E3: 姓名 | G3: 性別 | H3: 生日 | I3: 入職日期 | J3: 部門 | K3: 組別 | L3: 崗位名稱 | M3: 底薪 | N3: 工齡 | O3: 技能 | P3: 職位 | Q3: 語言 | R3: 房屋/交通 | S3: 全勤 | T3: 2021薪資總額 | U3: 調動金額 | V3: 調動日期 | W3: 評核人 | X3: 2022總分 | Y3: 意見 | Z3: 底薪 | AA3: 工齡 | AB3: 技能 | AC3: 職位 | AD3: 語言 | AE3: 房屋/交通 | AF3: 全勤 | AG3: 2022薪資總額
A4: =1 -> 1 | B4: 2426 | C4: =VLOOKUP(B4,All!$B$4:$S$8977,2,FALSE) -> ផុន | D4: =VLOOKUP(B4,All!$B$4:$S$89977,3,FALSE) -> ភារ៉ា | E4: =VLOOKUP(B4,All!$B$4:$S$8977,4,FALSE) -> PHON | F4: =VLOOKUP(B4,All!$B$4:$S$8977,5,FALSE) -> PHEARA | G4: =VLOOKUP(B4,All!$B$4:$S$8977,6,FALSE) -> M | H4: =VLOOKUP(B4,All!$B$4:$S$8977,7,FALSE) -> 32516 | I4: =VLOOKUP(B4,All!$B$4:$S$8977,8,FALSE) -> 43222 | J4: =VLOOKUP(B4,All!$B$4:$S$8977,9,FALSE) -> Production | K4: =VLOOKUP(B4,All!$B$4:$S$8977,10,FALSE) -> Warehouse Fabric | L4: =VLOOKUP(B4,All!$B$4:$S$8977,11,FALSE) -> Loader | M4: =VLOOKUP(B4,All!$B$4:$S$8977,12,FALSE) -> 192 | N4: =VLOOKUP(B4,All!$B$4:$S$8977,13,FALSE) -> 4 | O4: =VLOOKUP(B4,All!$B$4:$S$8977,14,FALSE) -> 20 | P4: =VLOOKUP(B4,All!$B$4:$S$8977,15,FALSE) -> 25 | Q4: =VLOOKUP(B4,All!$B$4:$S$8977,16,FALSE) -> 0 | R4: 7 | S4: 10 | T4: =SUM(M4:S4) -> 258 | Z4: =M4+AH4 -> 194 | AA4: =N4 -> 4 | AB4: =O4 -> 20 | AC4: =P4 -> 25 | AD4: =Q4 -> 0 | AE4: =R4 -> 7 | AF4: =S4 -> 10 | AG4: =SUM(Z4:AF4) -> 260 | AH4: 2 | AI4: 0 | AJ4: 0 | AK4: 0 | AL4: 0 | AM4: 0 | AN4: 0 | AO4: 2
A5: =1+A4 -> 2 | B5: 2851 | C5: =VLOOKUP(B5,All!$B$4:$S$8977,2,FALSE) -> ផាង | D5: =VLOOKUP(B5,All!$B$4:$S$89977,3,FALSE) -> ហ៊ុយ | E5: =VLOOKUP(B5,All!$B$4:$S$8977,4,FALSE) -> Phang | F5: =VLOOKUP(B5,All!$B$4:$S$8977,5,FALSE) -> Huy | G5: =VLOOKUP(B5,All!$B$4:$S$8977,6,FALSE) -> M | H5: =VLOOKUP(B5,All!$B$4:$S$8977,7,FALSE) -> 35160 | I5: =VLOOKUP(B5,All!$B$4:$S$8977,8,FALSE) -> 43573 | J5: =VLOOKUP(B5,All!$B$4:$S$8977,9,FALSE) -> Production | K5: =VLOOKUP(B5,All!$B$4:$S$8977,10,FALSE) -> Warehouse Fabric | L5: =VLOOKUP(B5,All!$B$4:$S$8977,11,FALSE) -> Loader | M5: =VLOOKUP(B5,All!$B$4:$S$8977,12,FALSE) -> 192 | N5: =VLOOKUP(B5,All!$B$4:$S$8977,13,FALSE) -> 3 | O5: =VLOOKUP(B5,All!$B$4:$S$8977,14,FALSE) -> 0 | P5: =VLOOKUP(B5,All!$B$4:$S$8977,15,FALSE) -> 20 | Q5: =VLOOKUP(B5,All!$B$4:$S$8977,16,FALSE) -> 0 | R5: 7 | S5: 10 | T5: =SUM(M5:S5) -> 232 | Z5: =M5+AH5 -> 194 | AA5: =N5 -> 3 | AB5: =O5 -> 0 | AC5: =P5 -> 20 | AD5: =Q5 -> 0 | AE5: =R5 -> 7 | AF5: =S5 -> 10 | AG5: =SUM(Z5:AF5) -> 234 | AH5: 2 | AI5: 0 | AJ5: 0 | AK5: 0 | AL5: 0 | AM5: 0 | AN5: 0 | AO5: 2
A6: =1+A5 -> 3 | B6: 2966 | C6: =VLOOKUP(B6,All!$B$4:$S$8977,2,FALSE) -> ស្រី | D6: =VLOOKUP(B6,All!$B$4:$S$89977,3,FALSE) -> ភារុណ | E6: =VLOOKUP(B6,All!$B$4:$S$8977,4,FALSE) -> Srey | F6: =VLOOKUP(B6,All!$B$4:$S$8977,5,FALSE) -> Phearun | G6: =VLOOKUP(B6,All!$B$4:$S$8977,6,FALSE) -> M | H6: =VLOOKUP(B6,All!$B$4:$S$8977,7,FALSE) -> 28194 | I6: =VLOOKUP(B6,All!$B$4:$S$8977,8,FALSE) -> 43636 | J6: =VLOOKUP(B6,All!$B$4:$S$8977,9,FALSE) -> Production | K6: =VLOOKUP(B6,All!$B$4:$S$8977,10,FALSE) -> Warehouse Fabric | L6: =VLOOKUP(B6,All!$B$4:$S$8977,11,FALSE) -> Loader | M6: =VLOOKUP(B6,All!$B$4:$S$8977,12,FALSE) -> 192 | N6: =VLOOKUP(B6,All!$B$4:$S$8977,13,FALSE) -> 3 | O6: =VLOOKUP(B6,All!$B$4:$S$8977,14,FALSE) -> 0 | P6: =VLOOKUP(B6,All!$B$4:$S$8977,15,FALSE) -> 0 | Q6: =VLOOKUP(B6,All!$B$4:$S$8977,16,FALSE) -> 0 | R6: 7 | S6: 10 | T6: =SUM(M6:S6) -> 212 | Z6: =M6+AH6 -> 194 | AA6: =N6 -> 3 | AB6: =O6 -> 0 | AC6: =P6 -> 0 | AD6: =Q6 -> 0 | AE6: =R6 -> 7 | AF6: =S6 -> 10 | AG6: =SUM(Z6:AF6) -> 214 | AH6: 2 | AI6: 0 | AJ6: 0 | AK6: 0 | AL6: 0 | AM6: 0 | AN6: 0 | AO6: 2
A7: =1+A6 -> 4 | B7: 3095 | C7: =VLOOKUP(B7,All!$B$4:$S$8977,2,FALSE) -> វន្ត័ | D7: =VLOOKUP(B7,All!$B$4:$S$89977,3,FALSE) -> វណ្ណា | E7: =VLOOKUP(B7,All!$B$4:$S$8977,4,FALSE) -> Vourn | F7: =VLOOKUP(B7,All!$B$4:$S$8977,5,FALSE) -> Vanna | G7: =VLOOKUP(B7,All!$B$4:$S$8977,6,FALSE) -> M | H7: =VLOOKUP(B7,All!$B$4:$S$8977,7,FALSE) -> 33118 | I7: =VLOOKUP(B7,All!$B$4:$S$8977,8,FALSE) -> 43740 | J7: =VLOOKUP(B7,All!$B$4:$S$8977,9,FALSE) -> Production | K7: =VLOOKUP(B7,All!$B$4:$S$8977,10,FALSE) -> Warehouse Fabric | L7: =VLOOKUP(B7,All!$B$4:$S$8977,11,FALSE) -> Loader | M7: =VLOOKUP(B7,All!$B$4:$S$8977,12,FALSE) -> 192 | N7: =VLOOKUP(B7,All!$B$4:$S$8977,13,FALSE) -> 3 | O7: =VLOOKUP(B7,All!$B$4:$S$8977,14,FALSE) -> 0 | P7: =VLOOKUP(B7,All!$B$4:$S$8977,15,FALSE) -> 0 | Q7: =VLOOKUP(B7,All!$B$4:$S$8977,16,FALSE) -> 0 | R7: 7 | S7: 10 | T7: =SUM(M7:S7) -> 212 | Z7: =M7+AH7 -> 194 | AA7: =N7 -> 3 | AB7: =O7 -> 0 | AC7: =P7 -> 0 | AD7: =Q7 -> 0 | AE7: =R7 -> 7 | AF7: =S7 -> 10 | AG7: =SUM(Z7:AF7) -> 214 | AH7: 2 | AI7: 0 | AJ7: 0 | AK7: 0 | AL7: 0 | AM7: 0 | AN7: 0 | AO7: 2
A8: =1+A7 -> 5 | B8: 3205 | C8: =VLOOKUP(B8,All!$B$4:$S$8977,2,FALSE) -> សាន | D8: =VLOOKUP(B8,All!$B$4:$S$89977,3,FALSE) -> វាសនា | E8: =VLOOKUP(B8,All!$B$4:$S$8977,4,FALSE) -> SAN | F8: =VLOOKUP(B8,All!$B$4:$S$8977,5,FALSE) -> VEASNA | G8: =VLOOKUP(B8,All!$B$4:$S$8977,6,FALSE) -> M | H8: =VLOOKUP(B8,All!$B$4:$S$8977,7,FALSE) -> 33340 | I8: =VLOOKUP(B8,All!$B$4:$S$8977,8,FALSE) -> 43740 | J8: =VLOOKUP(B8,All!$B$4:$S$8977,9,FALSE) -> Production | K8: =VLOOKUP(B8,All!$B$4:$S$8977,10,FALSE) -> Warehouse Fabric | L8: =VLOOKUP(B8,All!$B$4:$S$8977,11,FALSE) -> Loader | M8: =VLOOKUP(B8,All!$B$4:$S$8977,12,FALSE) -> 192 | N8: =VLOOKUP(B8,All!$B$4:$S$8977,13,FALSE) -> 3 | O8: =VLOOKUP(B8,All!$B$4:$S$8977,14,FALSE) -> 0 | P8: =VLOOKUP(B8,All!$B$4:$S$8977,15,FALSE) -> 0 | Q8: =VLOOKUP(B8,All!$B$4:$S$8977,16,FALSE) -> 0 | R8: 7 | S8: 10 | T8: =SUM(M8:S8) -> 212 | Z8: =M8+AH8 -> 194 | AA8: =N8 -> 3 | AB8: =O8 -> 0 | AC8: =P8 -> 0 | AD8: =Q8 -> 0 | AE8: =R8 -> 7 | AF8: =S8 -> 10 | AG8: =SUM(Z8:AF8) -> 214 | AH8: 2 | AI8: 0 | AJ8: 0 | AK8: 0 | AL8: 0 | AM8: 0 | AN8: 0 | AO8: 2
A9: =1+A8 -> 6 | B9: 3542 | C9: =VLOOKUP(B9,All!$B$4:$S$8977,2,FALSE) -> ស៊ុន | D9: =VLOOKUP(B9,All!$B$4:$S$89977,3,FALSE) -> ប៊ុនធឿន | E9: =VLOOKUP(B9,All!$B$4:$S$8977,4,FALSE) -> SUN | F9: =VLOOKUP(B9,All!$B$4:$S$8977,5,FALSE) -> BUNTHOEUN | G9: =VLOOKUP(B9,All!$B$4:$S$8977,6,FALSE) -> M | H9: =VLOOKUP(B9,All!$B$4:$S$8977,7,FALSE) -> 34175 | I9: =VLOOKUP(B9,All!$B$4:$S$8977,8,FALSE) -> 43747 | J9: =VLOOKUP(B9,All!$B$4:$S$8977,9,FALSE) -> Production | K9: =VLOOKUP(B9,All!$B$4:$S$8977,10,FALSE) -> Warehouse Fabric | L9: =VLOOKUP(B9,All!$B$4:$S$8977,11,FALSE) -> Loader | M9: =VLOOKUP(B9,All!$B$4:$S$8977,12,FALSE) -> 192 | N9: =VLOOKUP(B9,All!$B$4:$S$8977,13,FALSE) -> 3 | O9: =VLOOKUP(B9,All!$B$4:$S$8977,14,FALSE) -> 0 | P9: =VLOOKUP(B9,All!$B$4:$S$8977,15,FALSE) -> 0 | Q9: =VLOOKUP(B9,All!$B$4:$S$8977,16,FALSE) -> 0 | R9: 7 | S9: 10 | T9: =SUM(M9:S9) -> 212 | Z9: =M9+AH9 -> 194 | AA9: =N9 -> 3 | AB9: =O9 -> 0 | AC9: =P9 -> 0 | AD9: =Q9 -> 0 | AE9: =R9 -> 7 | AF9: =S9 -> 10 | AG9: =SUM(Z9:AF9) -> 214 | AH9: 2 | AI9: 0 | AJ9: 0 | AK9: 0 | AL9: 0 | AM9: 0 | AN9: 0 | AO9: 2
A10: =1+A9 -> 7 | B10: 3647 | C10: =VLOOKUP(B10,All!$B$4:$S$8977,2,FALSE) -> សូ | D10: =VLOOKUP(B10,All!$B$4:$S$89977,3,FALSE) -> សារ៉ាន់ | E10: =VLOOKUP(B10,All!$B$4:$S$8977,4,FALSE) -> SO | F10: =VLOOKUP(B10,All!$B$4:$S$8977,5,FALSE) -> SARANN | G10: =VLOOKUP(B10,All!$B$4:$S$8977,6,FALSE) -> M | H10: =VLOOKUP(B10,All!$B$4:$S$8977,7,FALSE) -> 32782 | I10: =VLOOKUP(B10,All!$B$4:$S$8977,8,FALSE) -> 43754 | J10: =VLOOKUP(B10,All!$B$4:$S$8977,9,FALSE) -> Production | K10: =VLOOKUP(B10,All!$B$4:$S$8977,10,FALSE) -> Warehouse Fabric | L10: =VLOOKUP(B10,All!$B$4:$S$8977,11,FALSE) -> Loader | M10: =VLOOKUP(B10,All!$B$4:$S$8977,12,FALSE) -> 192 | N10: =VLOOKUP(B10,All!$B$4:$S$8977,13,FALSE) -> 3 | O10: =VLOOKUP(B10,All!$B$4:$S$8977,14,FALSE) -> 0 | P10: =VLOOKUP(B10,All!$B$4:$S$8977,15,FALSE) -> 20 | Q10: =VLOOKUP(B10,All!$B$4:$S$8977,16,FALSE) -> 0 | R10: 7 | S10: 10 | T10: =SUM(M10:S10) -> 232 | Z10: =M10+AH10 -> 194 | AA10: =N10 -> 3 | AB10: =O10 -> 0 | AC10: =P10 -> 20 | AD10: =Q10 -> 0 | AE10: =R10 -> 7 | AF10: =S10 -> 10 | AG10: =SUM(Z10:AF10) -> 234 | AH10: 2 | AI10: 0 | AJ10: 0 | AK10: 0 | AL10: 0 | AM10: 0 | AN10: 0 | AO10: 2
A11: =1+A10 -> 8 | B11: 4126 | C11: =VLOOKUP(B11,All!$B$4:$S$8977,2,FALSE) -> មឿន | D11: =VLOOKUP(B11,All!$B$4:$S$89977,3,FALSE) -> នូសុខវិច្ឆកា | E11: =VLOOKUP(B11,All!$B$4:$S$8977,4,FALSE) -> MOEUN | F11: =VLOOKUP(B11,All!$B$4:$S$8977,5,FALSE) -> NOU SOKVICHHIKA | G11: =VLOOKUP(B11,All!$B$4:$S$8977,6,FALSE) -> M | H11: =VLOOKUP(B11,All!$B$4:$S$8977,7,FALSE) -> 34278 | I11: =VLOOKUP(B11,All!$B$4:$S$8977,8,FALSE) -> 43810 | J11: =VLOOKUP(B11,All!$B$4:$S$8977,9,FALSE) -> Production | K11: =VLOOKUP(B11,All!$B$4:$S$8977,10,FALSE) -> Warehouse Fabric | L11: =VLOOKUP(B11,All!$B$4:$S$8977,11,FALSE) -> Loader | M11: =VLOOKUP(B11,All!$B$4:$S$8977,12,FALSE) -> 192 | N11: =VLOOKUP(B11,All!$B$4:$S$8977,13,FALSE) -> 3 | O11: =VLOOKUP(B11,All!$B$4:$S$8977,14,FALSE) -> 0 | P11: =VLOOKUP(B11,All!$B$4:$S$8977,15,FALSE) -> 0 | Q11: =VLOOKUP(B11,All!$B$4:$S$8977,16,FALSE) -> 0 | R11: 7 | S11: 10 | T11: =SUM(M11:S11) -> 212 | Z11: =M11+AH11 -> 194 | AA11: =N11 -> 3 | AB11: =O11 -> 0 | AC11: =P11 -> 0 | AD11: =Q11 -> 0 | AE11: =R11 -> 7 | AF11: =S11 -> 10 | AG11: =SUM(Z11:AF11) -> 214 | AH11: 2 | AI11: 0 | AJ11: 0 | AK11: 0 | AL11: 0 | AM11: 0 | AN11: 0 | AO11: 2
A12: =1+A11 -> 9 | B12: 4138 | C12: =VLOOKUP(B12,All!$B$4:$S$8977,2,FALSE) -> នេត | D12: =VLOOKUP(B12,All!$B$4:$S$89977,3,FALSE) -> ចាន់វ៉ាន់ឆៃ | E12: =VLOOKUP(B12,All!$B$4:$S$8977,4,FALSE) -> NET | F12: =VLOOKUP(B12,All!$B$4:$S$8977,5,FALSE) -> CHANVANCHHAY | G12: =VLOOKUP(B12,All!$B$4:$S$8977,6,FALSE) -> M | H12: =VLOOKUP(B12,All!$B$4:$S$8977,7,FALSE) -> 35345 | I12: =VLOOKUP(B12,All!$B$4:$S$8977,8,FALSE) -> 43822 | J12: =VLOOKUP(B12,All!$B$4:$S$8977,9,FALSE) -> Production | K12: =VLOOKUP(B12,All!$B$4:$S$8977,10,FALSE) -> Warehouse Fabric | L12: =VLOOKUP(B12,All!$B$4:$S$8977,11,FALSE) -> Loader | M12: =VLOOKUP(B12,All!$B$4:$S$8977,12,FALSE) -> 192 | N12: =VLOOKUP(B12,All!$B$4:$S$8977,13,FALSE) -> 3 | O12: =VLOOKUP(B12,All!$B$4:$S$8977,14,FALSE) -> 0 | P12: =VLOOKUP(B12,All!$B$4:$S$8977,15,FALSE) -> 0 | Q12: =VLOOKUP(B12,All!$B$4:$S$8977,16,FALSE) -> 0 | R12: 7 | S12: 10 | T12: =SUM(M12:S12) -> 212 | Z12: =M12+AH12 -> 194 | AA12: =N12 -> 3 | AB12: =O12 -> 0 | AC12: =P12 -> 0 | AD12: =Q12 -> 0 | AE12: =R12 -> 7 | AF12: =S12 -> 10 | AG12: =SUM(Z12:AF12) -> 214 | AH12: 2 | AI12: 0 | AJ12: 0 | AK12: 0 | AL12: 0 | AM12: 0 | AN12: 0 | AO12: 2
A13: =1+A12 -> 10 | B13: 5172 | C13: =VLOOKUP(B13,All!$B$4:$S$8977,2,FALSE) -> អឹម | D13: =VLOOKUP(B13,All!$B$4:$S$89977,3,FALSE) -> ថេ | E13: =VLOOKUP(B13,All!$B$4:$S$8977,4,FALSE) -> OEM | F13: =VLOOKUP(B13,All!$B$4:$S$8977,5,FALSE) -> THE | G13: =VLOOKUP(B13,All!$B$4:$S$8977,6,FALSE) -> M | H13: =VLOOKUP(B13,All!$B$4:$S$8977,7,FALSE) -> 35160 | I13: =VLOOKUP(B13,All!$B$4:$S$8977,8,FALSE) -> 44485 | J13: =VLOOKUP(B13,All!$B$4:$S$8977,9,FALSE) -> Production | K13: =VLOOKUP(B13,All!$B$4:$S$8977,10,FALSE) -> Warehouse Fabric | L13: =VLOOKUP(B13,All!$B$4:$S$8977,11,FALSE) -> Loader | M13: =VLOOKUP(B13,All!$B$4:$S$8977,12,FALSE) -> 187 | N13: =VLOOKUP(B13,All!$B$4:$S$8977,13,FALSE) -> 0 | O13: =VLOOKUP(B13,All!$B$4:$S$8977,14,FALSE) -> 0 | P13: =VLOOKUP(B13,All!$B$4:$S$8977,15,FALSE) -> 0 | Q13: =VLOOKUP(B13,All!$B$4:$S$8977,16,FALSE) -> 0 | R13: 7 | S13: 10 | T13: =SUM(M13:S13) -> 204 | Z13: =M13+AH13 -> 189 | AA13: =N13 -> 0 | AB13: =O13 -> 0 | AC13: =P13 -> 0 | AD13: =Q13 -> 0 | AE13: =R13 -> 7 | AF13: =S13 -> 10 | AG13: =SUM(Z13:AF13) -> 206 | AH13: 2 | AI13: 0 | AJ13: 0 | AK13: 0 | AL13: 0 | AM13: 0 | AN13: 0 | AO13: 2
A14: =1+A13 -> 11 | B14: 5173 | C14: =VLOOKUP(B14,All!$B$4:$S$8977,2,FALSE) -> ណុប | D14: =VLOOKUP(B14,All!$B$4:$S$89977,3,FALSE) -> គីនីន | E14: =VLOOKUP(B14,All!$B$4:$S$8977,4,FALSE) -> NOP | F14: =VLOOKUP(B14,All!$B$4:$S$8977,5,FALSE) -> KININ | G14: =VLOOKUP(B14,All!$B$4:$S$8977,6,FALSE) -> M | H14: =VLOOKUP(B14,All!$B$4:$S$8977,7,FALSE) -> 30729 | I14: =VLOOKUP(B14,All!$B$4:$S$8977,8,FALSE) -> 44485 | J14: =VLOOKUP(B14,All!$B$4:$S$8977,9,FALSE) -> Production | K14: =VLOOKUP(B14,All!$B$4:$S$8977,10,FALSE) -> Warehouse Fabric | L14: =VLOOKUP(B14,All!$B$4:$S$8977,11,FALSE) -> Loader | M14: =VLOOKUP(B14,All!$B$4:$S$8977,12,FALSE) -> 187 | N14: =VLOOKUP(B14,All!$B$4:$S$8977,13,FALSE) -> 0 | O14: =VLOOKUP(B14,All!$B$4:$S$8977,14,FALSE) -> 0 | P14: =VLOOKUP(B14,All!$B$4:$S$8977,15,FALSE) -> 0 | Q14: =VLOOKUP(B14,All!$B$4:$S$8977,16,FALSE) -> 0 | R14: 7 | S14: 10 | T14: =SUM(M14:S14) -> 204 | Z14: =M14+AH14 -> 189 | AA14: =N14 -> 0 | AB14: =O14 -> 0 | AC14: =P14 -> 0 | AD14: =Q14 -> 0 | AE14: =R14 -> 7 | AF14: =S14 -> 10 | AG14: =SUM(Z14:AF14) -> 206 | AH14: 2 | AI14: 0 | AJ14: 0 | AK14: 0 | AL14: 0 | AM14: 0 | AN14: 0 | AO14: 2
T16: =SUM(T4:T14) -> 2402 | AG16: =SUM(AG4:AG14) -> 2424 | AH16: =SUM(AH4:AH14) -> 22 | AI16: =SUM(AI4:AI14) -> 0

Sheet WH Trims
A1: ល.រ | B1: Factory ID | C1: គោត្តនាម | D1: នាម | E1: គោត្តនាមឡាតាំង | F1: នាមឡាតាំង | G1: ភេទ | H1: ថ្ងៃខែឆ្នាំកំណើត | I1: កាលបរិ. ចូលធ្វើការ | J1: ផ្នែក | K1: ក្រុម | L1: តួនាទី | M1: Salary Report 2021 | U1: Adjust amount | V1: Adjust Date | W1: Evaluator | X1: 2022 Total Marks | Y1: With Comment | Z1: Salary Report 2022
A2: Nº | B2: Factory ID | C2: Khmer Sure name | D2: Khmer Name | E2: English Sure name | F2: Khmer Name | G2: Sex | H2: Birth of Date | I2: Join Date | J2: Department | K2: Group | L2: Position | M2: Basic | N2: Seniority | O2: Skill | P2: Position | Q2: Language | R2: Housing &Transportation | S2: Motivation | T2: Total | U2: 調動金額 | V2: 調動日期 | W2: 評核人 | X2: 2022總分 | Y2: 意見 | Z2: Basic | AA2: Seniority | AB2: Skill | AC2: Position | AD2: Language | AE2: Housing &Transportation | AF2: Motivation | AG2: Total
A3: 排序 | B3: 工號 | E3: 姓名 | G3: 性別 | H3: 生日 | I3: 入職日期 | J3: 部門 | K3: 組別 | L3: 崗位名稱 | M3: 底薪 | N3: 工齡 | O3: 技能 | P3: 職位 | Q3: 語言 | R3: 房屋/交通 | S3: 全勤 | T3: 2021薪資總額 | U3: 調動金額 | V3: 調動日期 | W3: 評核人 | X3: 2022總分 | Y3: 意見 | Z3: 底薪 | AA3: 工齡 | AB3: 技能 | AC3: 職位 | AD3: 語言 | AE3: 房屋/交通 | AF3: 全勤 | AG3: 2022薪資總額
A4: =1 -> 1 | B4: 316 | C4: =VLOOKUP(B4,All!$B$4:$S$8977,2,FALSE) -> រិន | D4: =VLOOKUP(B4,All!$B$4:$S$89977,3,FALSE) -> ចាន់ថា | E4: =VLOOKUP(B4,All!$B$4:$S$8977,4,FALSE) -> RIN | F4: =VLOOKUP(B4,All!$B$4:$S$8977,5,FALSE) -> CHANTHA | G4: =VLOOKUP(B4,All!$B$4:$S$8977,6,FALSE) -> F | H4: =VLOOKUP(B4,All!$B$4:$S$8977,7,FALSE) -> 34981 | I4: =VLOOKUP(B4,All!$B$4:$S$8977,8,FALSE) -> 41755 | J4: =VLOOKUP(B4,All!$B$4:$S$8977,9,FALSE) -> Production | K4: =VLOOKUP(B4,All!$B$4:$S$8977,10,FALSE) -> Warehouse Trims | L4: =VLOOKUP(B4,All!$B$4:$S$8977,11,FALSE) -> accessory assistant | M4: =VLOOKUP(B4,All!$B$4:$S$8977,12,FALSE) -> 192 | N4: =VLOOKUP(B4,All!$B$4:$S$8977,13,FALSE) -> 8 | O4: =VLOOKUP(B4,All!$B$4:$S$8977,14,FALSE) -> 20 | P4: =VLOOKUP(B4,All!$B$4:$S$8977,15,FALSE) -> 20 | Q4: =VLOOKUP(B4,All!$B$4:$S$8977,16,FALSE) -> 0 | R4: 7 | S4: 10 | T4: =SUM(M4:S4) -> 257 | Z4: =M4+AH4 -> 194 | AA4: =N4 -> 8 | AB4: =O4 -> 20 | AC4: =P4 -> 20 | AD4: =Q4 -> 0 | AE4: =R4 -> 7 | AF4: =S4 -> 10 | AG4: =SUM(Z4:AF4) -> 259 | AH4: 2 | AI4: 0 | AJ4: 0 | AK4: 0 | AL4: 0 | AM4: 0 | AN4: 0 | AO4: 2
A5: =1+A4 -> 2 | B5: 2974 | C5: =VLOOKUP(B5,All!$B$4:$S$8977,2,FALSE) -> ស៊ុំ | D5: =VLOOKUP(B5,All!$B$4:$S$89977,3,FALSE) -> ហ៊ីង | E5: =VLOOKUP(B5,All!$B$4:$S$8977,4,FALSE) -> Sum | F5: =VLOOKUP(B5,All!$B$4:$S$8977,5,FALSE) -> Hing | G5: =VLOOKUP(B5,All!$B$4:$S$8977,6,FALSE) -> F | H5: =VLOOKUP(B5,All!$B$4:$S$8977,7,FALSE) -> 28470 | I5: =VLOOKUP(B5,All!$B$4:$S$8977,8,FALSE) -> 43636 | J5: =VLOOKUP(B5,All!$B$4:$S$8977,9,FALSE) -> Production | K5: =VLOOKUP(B5,All!$B$4:$S$8977,10,FALSE) -> Warehouse Trims | L5: =VLOOKUP(B5,All!$B$4:$S$8977,11,FALSE) -> accessory assistant | M5: =VLOOKUP(B5,All!$B$4:$S$8977,12,FALSE) -> 192 | N5: =VLOOKUP(B5,All!$B$4:$S$8977,13,FALSE) -> 3 | O5: =VLOOKUP(B5,All!$B$4:$S$8977,14,FALSE) -> 0 | P5: =VLOOKUP(B5,All!$B$4:$S$8977,15,FALSE) -> 0 | Q5: =VLOOKUP(B5,All!$B$4:$S$8977,16,FALSE) -> 0 | R5: 7 | S5: 10 | T5: =SUM(M5:S5) -> 212 | Z5: =M5+AH5 -> 194 | AA5: =N5 -> 3 | AB5: =O5 -> 0 | AC5: =P5 -> 0 | AD5: =Q5 -> 0 | AE5: =R5 -> 7 | AF5: =S5 -> 10 | AG5: =SUM(Z5:AF5) -> 214 | AH5: 2 | AI5: 0 | AJ5: 0 | AK5: 0 | AL5: 0 | AM5: 0 | AN5: 0 | AO5: 2
A6: =1+A5 -> 3 | B6: 3053 | C6: =VLOOKUP(B6,All!$B$4:$S$8977,2,FALSE) -> សន់ | D6: =VLOOKUP(B6,All!$B$4:$S$89977,3,FALSE) -> សុឧត្តម | E6: =VLOOKUP(B6,All!$B$4:$S$8977,4,FALSE) -> Sann | F6: =VLOOKUP(B6,All!$B$4:$S$8977,5,FALSE) -> Sodom | G6: =VLOOKUP(B6,All!$B$4:$S$8977,6,FALSE) -> M | H6: =VLOOKUP(B6,All!$B$4:$S$8977,7,FALSE) -> 36524 | I6: =VLOOKUP(B6,All!$B$4:$S$8977,8,FALSE) -> 43653 | J6: =VLOOKUP(B6,All!$B$4:$S$8977,9,FALSE) -> Production | K6: =VLOOKUP(B6,All!$B$4:$S$8977,10,FALSE) -> Warehouse Trims | L6: =VLOOKUP(B6,All!$B$4:$S$8977,11,FALSE) -> accessory assistant | M6: =VLOOKUP(B6,All!$B$4:$S$8977,12,FALSE) -> 192 | N6: =VLOOKUP(B6,All!$B$4:$S$8977,13,FALSE) -> 3 | O6: =VLOOKUP(B6,All!$B$4:$S$8977,14,FALSE) -> 0 | P6: =VLOOKUP(B6,All!$B$4:$S$8977,15,FALSE) -> 0 | Q6: =VLOOKUP(B6,All!$B$4:$S$8977,16,FALSE) -> 0 | R6: 7 | S6: 10 | T6: =SUM(M6:S6) -> 212 | Z6: =M6+AH6 -> 194 | AA6: =N6 -> 3 | AB6: =O6 -> 0 | AC6: =P6 -> 0 | AD6: =Q6 -> 0 | AE6: =R6 -> 7 | AF6: =S6 -> 10 | AG6: =SUM(Z6:AF6) -> 214 | AH6: 2 | AI6: 0 | AJ6: 0 | AK6: 0 | AL6: 0 | AM6: 0 | AN6: 0 | AO6: 2
A7: =1+A6 -> 4 | B7: 5002 | C7: =VLOOKUP(B7,All!$B$4:$S$8977,2,FALSE) -> អ៊ុក | D7: =VLOOKUP(B7,All!$B$4:$S$89977,3,FALSE) -> ស្រីណូ | E7: =VLOOKUP(B7,All!$B$4:$S$8977,4,FALSE) -> OUK | F7: =VLOOKUP(B7,All!$B$4:$S$8977,5,FALSE) -> SREYNO | G7: =VLOOKUP(B7,All!$B$4:$S$8977,6,FALSE) -> F | H7: =VLOOKUP(B7,All!$B$4:$S$8977,7,FALSE) -> 34713 | I7: =VLOOKUP(B7,All!$B$4:$S$8977,8,FALSE) -> 44139 | J7: =VLOOKUP(B7,All!$B$4:$S$8977,9,FALSE) -> Production | K7: =VLOOKUP(B7,All!$B$4:$S$8977,10,FALSE) -> Warehouse Trims | L7: =VLOOKUP(B7,All!$B$4:$S$8977,11,FALSE) -> accessory assistant | M7: =VLOOKUP(B7,All!$B$4:$S$8977,12,FALSE) -> 192 | N7: =VLOOKUP(B7,All!$B$4:$S$8977,13,FALSE) -> 2 | O7: =VLOOKUP(B7,All!$B$4:$S$8977,14,FALSE) -> 0 | P7: =VLOOKUP(B7,All!$B$4:$S$8977,15,FALSE) -> 0 | Q7: =VLOOKUP(B7,All!$B$4:$S$8977,16,FALSE) -> 0 | R7: 7 | S7: 10 | T7: =SUM(M7:S7) -> 211 | Z7: =M7+AH7 -> 194 | AA7: =N7 -> 2 | AB7: =O7 -> 0 | AC7: =P7 -> 0 | AD7: =Q7 -> 0 | AE7: =R7 -> 7 | AF7: =S7 -> 10 | AG7: =SUM(Z7:AF7) -> 213 | AH7: 2 | AI7: 0 | AJ7: 0 | AK7: 0 | AL7: 0 | AM7: 0 | AN7: 0 | AO7: 2
A8: =1+A7 -> 5 | B8: 5093 | C8: =VLOOKUP(B8,All!$B$4:$S$8977,2,FALSE) -> ស៊ិន​ | D8: =VLOOKUP(B8,All!$B$4:$S$89977,3,FALSE) -> សាវ៉ើន | E8: =VLOOKUP(B8,All!$B$4:$S$8977,4,FALSE) -> SIN | F8: =VLOOKUP(B8,All!$B$4:$S$8977,5,FALSE) -> SAVOEUN | G8: =VLOOKUP(B8,All!$B$4:$S$8977,6,FALSE) -> M | H8: =VLOOKUP(B8,All!$B$4:$S$8977,7,FALSE) -> 35524 | I8: =VLOOKUP(B8,All!$B$4:$S$8977,8,FALSE) -> 44421 | J8: =VLOOKUP(B8,All!$B$4:$S$8977,9,FALSE) -> Production | K8: =VLOOKUP(B8,All!$B$4:$S$8977,10,FALSE) -> Warehouse Trims | L8: =VLOOKUP(B8,All!$B$4:$S$8977,11,FALSE) -> accessory assistant | M8: =VLOOKUP(B8,All!$B$4:$S$8977,12,FALSE) -> 187 | N8: =VLOOKUP(B8,All!$B$4:$S$8977,13,FALSE) -> 0 | O8: =VLOOKUP(B8,All!$B$4:$S$8977,14,FALSE) -> 0 | P8: =VLOOKUP(B8,All!$B$4:$S$8977,15,FALSE) -> 0 | Q8: =VLOOKUP(B8,All!$B$4:$S$8977,16,FALSE) -> 0 | R8: 7 | S8: 10 | T8: =SUM(M8:S8) -> 204 | Z8: =M8+AH8 -> 189 | AA8: =N8 -> 0 | AB8: =O8 -> 0 | AC8: =P8 -> 0 | AD8: =Q8 -> 0 | AE8: =R8 -> 7 | AF8: =S8 -> 10 | AG8: =SUM(Z8:AF8) -> 206 | AH8: 2 | AI8: 0 | AJ8: 0 | AK8: 0 | AL8: 0 | AM8: 0 | AN8: 0 | AO8: 2
A9: =1+A8 -> 6 | B9: 5088 | C9: =VLOOKUP(B9,All!$B$4:$S$8977,2,FALSE) -> ម៉ុស | D9: =VLOOKUP(B9,All!$B$4:$S$89977,3,FALSE) -> ប៊ុនធី | E9: =VLOOKUP(B9,All!$B$4:$S$8977,4,FALSE) -> MOS | F9: =VLOOKUP(B9,All!$B$4:$S$8977,5,FALSE) -> BUNTHY | G9: =VLOOKUP(B9,All!$B$4:$S$8977,6,FALSE) -> M | H9: =VLOOKUP(B9,All!$B$4:$S$8977,7,FALSE) -> 33060 | I9: =VLOOKUP(B9,All!$B$4:$S$8977,8,FALSE) -> 44399 | J9: =VLOOKUP(B9,All!$B$4:$S$8977,9,FALSE) -> Production | K9: =VLOOKUP(B9,All!$B$4:$S$8977,10,FALSE) -> Warehouse Trims | L9: =VLOOKUP(B9,All!$B$4:$S$8977,11,FALSE) -> accessory assistant | M9: =VLOOKUP(B9,All!$B$4:$S$8977,12,FALSE) -> 192 | N9: =VLOOKUP(B9,All!$B$4:$S$8977,13,FALSE) -> 0 | O9: =VLOOKUP(B9,All!$B$4:$S$8977,14,FALSE) -> 0 | P9: =VLOOKUP(B9,All!$B$4:$S$8977,15,FALSE) -> 0 | Q9: =VLOOKUP(B9,All!$B$4:$S$8977,16,FALSE) -> 0 | R9: 7 | S9: 10 | T9: =SUM(M9:S9) -> 209 | Z9: =M9+AH9 -> 194 | AA9: =N9 -> 0 | AB9: =O9 -> 0 | AC9: =P9 -> 0 | AD9: =Q9 -> 0 | AE9: =R9 -> 7 | AF9: =S9 -> 10 | AG9: =SUM(Z9:AF9) -> 211 | AH9: 2 | AI9: 0 | AJ9: 0 | AK9: 0 | AL9: 0 | AM9: 0 | AN9: 0 | AO9: 2
A10: =1+A9 -> 7 | B10: 5089 | C10: =VLOOKUP(B10,All!$B$4:$S$8977,2,FALSE) -> បេន | D10: =VLOOKUP(B10,All!$B$4:$S$89977,3,FALSE) -> ខេមរ៉ា | E10: =VLOOKUP(B10,All!$B$4:$S$8977,4,FALSE) -> BEN | F10: =VLOOKUP(B10,All!$B$4:$S$8977,5,FALSE) -> KHEMRA | G10: =VLOOKUP(B10,All!$B$4:$S$8977,6,FALSE) -> F | H10: =VLOOKUP(B10,All!$B$4:$S$8977,7,FALSE) -> 32234 | I10: =VLOOKUP(B10,All!$B$4:$S$8977,8,FALSE) -> 44400 | J10: =VLOOKUP(B10,All!$B$4:$S$8977,9,FALSE) -> Production | K10: =VLOOKUP(B10,All!$B$4:$S$8977,10,FALSE) -> Warehouse Trims | L10: =VLOOKUP(B10,All!$B$4:$S$8977,11,FALSE) -> accessory assistant | M10: =VLOOKUP(B10,All!$B$4:$S$8977,12,FALSE) -> 192 | N10: =VLOOKUP(B10,All!$B$4:$S$8977,13,FALSE) -> 0 | O10: =VLOOKUP(B10,All!$B$4:$S$8977,14,FALSE) -> 0 | P10: =VLOOKUP(B10,All!$B$4:$S$8977,15,FALSE) -> 0 | Q10: =VLOOKUP(B10,All!$B$4:$S$8977,16,FALSE) -> 0 | R10: 7 | S10: 10 | T10: =SUM(M10:S10) -> 209 | Z10: =M10+AH10 -> 194 | AA10: =N10 -> 0 | AB10: =O10 -> 0 | AC10: =P10 -> 0 | AD10: =Q10 -> 0 | AE10: =R10 -> 7 | AF10: =S10 -> 10 | AG10: =SUM(Z10:AF10) -> 211 | AH10: 2 | AI10: 0 | AJ10: 0 | AK10: 0 | AL10: 0 | AM10: 0 | AN10: 0 | AO10: 2
A11: =1+A10 -> 8 | B11: 5167 | C11: =VLOOKUP(B11,All!$B$4:$S$8977,2,FALSE) -> រូ | D11: =VLOOKUP(B11,All!$B$4:$S$89977,3,FALSE) -> ស្រីនុត | E11: =VLOOKUP(B11,All!$B$4:$S$8977,4,FALSE) -> RU | F11: =VLOOKUP(B11,All!$B$4:$S$8977,5,FALSE) -> SREYNUTH | G11: =VLOOKUP(B11,All!$B$4:$S$8977,6,FALSE) -> F | H11: =VLOOKUP(B11,All!$B$4:$S$8977,7,FALSE) -> 37493 | I11: =VLOOKUP(B11,All!$B$4:$S$8977,8,FALSE) -> 44485 | J11: =VLOOKUP(B11,All!$B$4:$S$8977,9,FALSE) -> Production | K11: =VLOOKUP(B11,All!$B$4:$S$8977,10,FALSE) -> Warehouse Trims | L11: =VLOOKUP(B11,All!$B$4:$S$8977,11,FALSE) -> accessory assistant | M11: =VLOOKUP(B11,All!$B$4:$S$8977,12,FALSE) -> 187 | N11: =VLOOKUP(B11,All!$B$4:$S$8977,13,FALSE) -> 0 | O11: =VLOOKUP(B11,All!$B$4:$S$8977,14,FALSE) -> 0 | P11: =VLOOKUP(B11,All!$B$4:$S$8977,15,FALSE) -> 0 | Q11: =VLOOKUP(B11,All!$B$4:$S$8977,16,FALSE) -> 0 | R11: 7 | S11: 10 | T11: =SUM(M11:S11) -> 204 | Z11: =M11+AH11 -> 189 | AA11: =N11 -> 0 | AB11: =O11 -> 0 | AC11: =P11 -> 0 | AD11: =Q11 -> 0 | AE11: =R11 -> 7 | AF11: =S11 -> 10 | AG11: =SUM(Z11:AF11) -> 206 | AH11: 2 | AI11: 0 | AJ11: 0 | AK11: 0 | AL11: 0 | AM11: 0 | AN11: 0 | AO11: 2
A12: =1+A11 -> 9 | B12: 5174 | C12: =VLOOKUP(B12,All!$B$4:$S$8977,2,FALSE) -> ឃួន | D12: =VLOOKUP(B12,All!$B$4:$S$89977,3,FALSE) -> វាណ្ណា | E12: =VLOOKUP(B12,All!$B$4:$S$8977,4,FALSE) -> KHOUN | F12: =VLOOKUP(B12,All!$B$4:$S$8977,5,FALSE) -> VANNA | G12: =VLOOKUP(B12,All!$B$4:$S$8977,6,FALSE) -> M | H12: =VLOOKUP(B12,All!$B$4:$S$8977,7,FALSE) -> 31564 | I12: =VLOOKUP(B12,All!$B$4:$S$8977,8,FALSE) -> 44485 | J12: =VLOOKUP(B12,All!$B$4:$S$8977,9,FALSE) -> Production | K12: =VLOOKUP(B12,All!$B$4:$S$8977,10,FALSE) -> Warehouse Trims | L12: =VLOOKUP(B12,All!$B$4:$S$8977,11,FALSE) -> accessory assistant | M12: =VLOOKUP(B12,All!$B$4:$S$8977,12,FALSE) -> 187 | N12: =VLOOKUP(B12,All!$B$4:$S$8977,13,FALSE) -> 0 | O12: =VLOOKUP(B12,All!$B$4:$S$8977,14,FALSE) -> 0 | P12: =VLOOKUP(B12,All!$B$4:$S$8977,15,FALSE) -> 0 | Q12: =VLOOKUP(B12,All!$B$4:$S$8977,16,FALSE) -> 0 | R12: 7 | S12: 10 | T12: =SUM(M12:S12) -> 204 | Z12: =M12+AH12 -> 189 | AA12: =N12 -> 0 | AB12: =O12 -> 0 | AC12: =P12 -> 0 | AD12: =Q12 -> 0 | AE12: =R12 -> 7 | AF12: =S12 -> 10 | AG12: =SUM(Z12:AF12) -> 206 | AH12: 2 | AI12: 0 | AJ12: 0 | AK12: 0 | AL12: 0 | AM12: 0 | AN12: 0 | AO12: 2
T14: =SUM(T4:T12) -> 1922 | AG14: =SUM(AG4:AG12) -> 1940 | AH14: =SUM(AH5:AH12) -> 16 | AI14: =SUM(AI5:AI12) -> 0

Sheet Cutting
A1: ល.រ | B1: Factory ID | C1: គោត្តនាម | D1: នាម | E1: គោត្តនាមឡាតាំង | F1: នាមឡាតាំង | G1: ភេទ | H1: ថ្ងៃខែឆ្នាំកំណើត | I1: កាលបរិ. ចូលធ្វើការ | J1: ផ្នែក | K1: ក្រុម | L1: តួនាទី | M1: Salary Report 2021 | U1: Adjust amount | V1: Adjust Date | W1: Evaluator | X1: 2022 Total Marks | Y1: With Comment | Z1: Salary Report 2022
A2: Nº | B2: Factory ID | C2: Khmer Sure name | D2: Khmer Name | E2: English Sure name | F2: Khmer Name | G2: Sex | H2: Birth of Date | I2: Join Date | J2: Department | K2: Group | L2: Position | M2: Basic | N2: Seniority | O2: Skill | P2: Position | Q2: Language | R2: Housing &Transportation | S2: Motivation | T2: Total | U2: 調動金額 | V2: 調動日期 | W2: 評核人 | X2: 2022總分 | Y2: 意見 | Z2: Basic | AA2: Seniority | AB2: Skill | AC2: Position | AD2: Language | AE2: Housing &Transportation | AF2: Motivation | AG2: Total
A3: 排序 | B3: 工號 | E3: 姓名 | G3: 性別 | H3: 生日 | I3: 入職日期 | J3: 部門 | K3: 組別 | L3: 崗位名稱 | M3: 底薪 | N3: 工齡 | O3: 技能 | P3: 職位 | Q3: 語言 | R3: 房屋/交通 | S3: 全勤 | T3: 2021薪資總額 | U3: 調動金額 | V3: 調動日期 | W3: 評核人 | X3: 2022總分 | Y3: 意見 | Z3: 底薪 | AA3: 工齡 | AB3: 技能 | AC3: 職位 | AD3: 語言 | AE3: 房屋/交通 | AF3: 全勤 | AG3: 2022薪資總額
A4: =1 -> 1 | B4: 648 | C4: =VLOOKUP(B4,All!$B$4:$S$8977,2,FALSE) -> ម៉េង | D4: =VLOOKUP(B4,All!$B$4:$S$89977,3,FALSE) -> រដ្ឋា | E4: =VLOOKUP(B4,All!$B$4:$S$8977,4,FALSE) -> MENG | F4: =VLOOKUP(B4,All!$B$4:$S$8977,5,FALSE) -> RATHA | G4: =VLOOKUP(B4,All!$B$4:$S$8977,6,FALSE) -> M | H4: =VLOOKUP(B4,All!$B$4:$S$8977,7,FALSE) -> 34481 | I4: =VLOOKUP(B4,All!$B$4:$S$8977,8,FALSE) -> 41869 | J4: =VLOOKUP(B4,All!$B$4:$S$8977,9,FALSE) -> Production | K4: =VLOOKUP(B4,All!$B$4:$S$8977,10,FALSE) -> Cutting | L4: =VLOOKUP(B4,All!$B$4:$S$8977,11,FALSE) -> Cutter | M4: =VLOOKUP(B4,All!$B$4:$S$8977,12,FALSE) -> 192 | N4: =VLOOKUP(B4,All!$B$4:$S$8977,13,FALSE) -> 8 | O4: =VLOOKUP(B4,All!$B$4:$S$8977,14,FALSE) -> 20 | P4: =VLOOKUP(B4,All!$B$4:$S$8977,15,FALSE) -> 15 | Q4: =VLOOKUP(B4,All!$B$4:$S$8977,16,FALSE) -> 5 | R4: 7 | S4: 10 | T4: =SUM(M4:S4) -> 257 | Z4: =M4+AH4 -> 194 | AA4: =N4 -> 8 | AB4: =O4 -> 20 | AC4: =P4 -> 15 | AD4: =Q4 -> 5 | AE4: =R4 -> 7 | AF4: =S4 -> 10 | AG4: =SUM(Z4:AF4) -> 259 | AH4: 2 | AI4: 0 | AJ4: 0 | AK4: 0 | AL4: 0 | AM4: 0 | AN4: 0 | AO4: 2
A5: =1+A4 -> 2 | B5: 1593 | C5: =VLOOKUP(B5,All!$B$4:$S$8977,2,FALSE) -> ប៊ុន | D5: =VLOOKUP(B5,All!$B$4:$S$89977,3,FALSE) -> ស្រីឃីម | E5: =VLOOKUP(B5,All!$B$4:$S$8977,4,FALSE) -> BUN | F5: =VLOOKUP(B5,All!$B$4:$S$8977,5,FALSE) -> SREI KHIM | G5: =VLOOKUP(B5,All!$B$4:$S$8977,6,FALSE) -> F | H5: =VLOOKUP(B5,All!$B$4:$S$8977,7,FALSE) -> 28495 | I5: =VLOOKUP(B5,All!$B$4:$S$8977,8,FALSE) -> 42597 | J5: =VLOOKUP(B5,All!$B$4:$S$8977,9,FALSE) -> Production | K5: =VLOOKUP(B5,All!$B$4:$S$8977,10,FALSE) -> Cutting | L5: =VLOOKUP(B5,All!$B$4:$S$8977,11,FALSE) -> Cutter | M5: =VLOOKUP(B5,All!$B$4:$S$8977,12,FALSE) -> 192 | N5: =VLOOKUP(B5,All!$B$4:$S$8977,13,FALSE) -> 6 | O5: =VLOOKUP(B5,All!$B$4:$S$8977,14,FALSE) -> 20 | P5: =VLOOKUP(B5,All!$B$4:$S$8977,15,FALSE) -> 0 | Q5: =VLOOKUP(B5,All!$B$4:$S$8977,16,FALSE) -> 0 | R5: 7 | S5: 10 | T5: =SUM(M5:S5) -> 235 | Z5: =M5+AH5 -> 194 | AA5: =N5 -> 6 | AB5: =O5 -> 20 | AC5: =P5 -> 0 | AD5: =Q5 -> 0 | AE5: =R5 -> 7 | AF5: =S5 -> 10 | AG5: =SUM(Z5:AF5) -> 237 | AH5: 2 | AI5: 0 | AJ5: 0 | AK5: 0 | AL5: 0 | AM5: 0 | AN5: 0 | AO5: 2
A6: =1+A5 -> 3 | B6: 1610 | C6: =VLOOKUP(B6,All!$B$4:$S$8977,2,FALSE) -> យ៉ូន | D6: =VLOOKUP(B6,All!$B$4:$S$89977,3,FALSE) -> សំអឿន | E6: =VLOOKUP(B6,All!$B$4:$S$8977,4,FALSE) -> YAUN | F6: =VLOOKUP(B6,All!$B$4:$S$8977,5,FALSE) -> SAMOEUN | G6: =VLOOKUP(B6,All!$B$4:$S$8977,6,FALSE) -> F | H6: =VLOOKUP(B6,All!$B$4:$S$8977,7,FALSE) -> 29710 | I6: =VLOOKUP(B6,All!$B$4:$S$8977,8,FALSE) -> 42618 | J6: =VLOOKUP(B6,All!$B$4:$S$8977,9,FALSE) -> Production | K6: =VLOOKUP(B6,All!$B$4:$S$8977,10,FALSE) -> Cutting | L6: =VLOOKUP(B6,All!$B$4:$S$8977,11,FALSE) -> Cutter | M6: =VLOOKUP(B6,All!$B$4:$S$8977,12,FALSE) -> 192 | N6: =VLOOKUP(B6,All!$B$4:$S$8977,13,FALSE) -> 6 | O6: =VLOOKUP(B6,All!$B$4:$S$8977,14,FALSE) -> 20 | P6: =VLOOKUP(B6,All!$B$4:$S$8977,15,FALSE) -> 0 | Q6: =VLOOKUP(B6,All!$B$4:$S$8977,16,FALSE) -> 0 | R6: 7 | S6: 10 | T6: =SUM(M6:S6) -> 235 | Z6: =M6+AH6 -> 194 | AA6: =N6 -> 6 | AB6: =O6 -> 20 | AC6: =P6 -> 0 | AD6: =Q6 -> 0 | AE6: =R6 -> 7 | AF6: =S6 -> 10 | AG6: =SUM(Z6:AF6) -> 237 | AH6: 2 | AI6: 0 | AJ6: 0 | AK6: 0 | AL6: 0 | AM6: 0 | AN6: 0 | AO6: 2
A7: =1+A6 -> 4 | B7: 1700 | C7: =VLOOKUP(B7,All!$B$4:$S$8977,2,FALSE) -> សូយ | D7: =VLOOKUP(B7,All!$B$4:$S$89977,3,FALSE) -> វ៉ាន់ឌី | E7: =VLOOKUP(B7,All!$B$4:$S$8977,4,FALSE) -> SOUY | F7: =VLOOKUP(B7,All!$B$4:$S$8977,5,FALSE) -> VANDY | G7: =VLOOKUP(B7,All!$B$4:$S$8977,6,FALSE) -> M | H7: =VLOOKUP(B7,All!$B$4:$S$8977,7,FALSE) -> 31093 | I7: =VLOOKUP(B7,All!$B$4:$S$8977,8,FALSE) -> 42661 | J7: =VLOOKUP(B7,All!$B$4:$S$8977,9,FALSE) -> Production | K7: =VLOOKUP(B7,All!$B$4:$S$8977,10,FALSE) -> Cutting | L7: =VLOOKUP(B7,All!$B$4:$S$8977,11,FALSE) -> Cutter | M7: =VLOOKUP(B7,All!$B$4:$S$8977,12,FALSE) -> 192 | N7: =VLOOKUP(B7,All!$B$4:$S$8977,13,FALSE) -> 6 | O7: =VLOOKUP(B7,All!$B$4:$S$8977,14,FALSE) -> 20 | P7: =VLOOKUP(B7,All!$B$4:$S$8977,15,FALSE) -> 24 | Q7: =VLOOKUP(B7,All!$B$4:$S$8977,16,FALSE) -> 0 | R7: 7 | S7: 10 | T7: =SUM(M7:S7) -> 259 | Z7: =M7+AH7 -> 194 | AA7: =N7 -> 6 | AB7: =O7 -> 20 | AC7: =P7 -> 24 | AD7: =Q7 -> 0 | AE7: =R7 -> 7 | AF7: =S7 -> 10 | AG7: =SUM(Z7:AF7) -> 261 | AH7: 2 | AI7: 0 | AJ7: 0 | AK7: 0 | AL7: 0 | AM7: 0 | AN7: 0 | AO7: 2
A8: =1+A7 -> 5 | B8: 1831 | C8: =VLOOKUP(B8,All!$B$4:$S$8977,2,FALSE) -> គឹម | D8: =VLOOKUP(B8,All!$B$4:$S$89977,3,FALSE) -> យឿង | E8: =VLOOKUP(B8,All!$B$4:$S$8977,4,FALSE) -> KIM | F8: =VLOOKUP(B8,All!$B$4:$S$8977,5,FALSE) -> YOEUNG | G8: =VLOOKUP(B8,All!$B$4:$S$8977,6,FALSE) -> F | H8: =VLOOKUP(B8,All!$B$4:$S$8977,7,FALSE) -> 29637 | I8: =VLOOKUP(B8,All!$B$4:$S$8977,8,FALSE) -> 42768 | J8: =VLOOKUP(B8,All!$B$4:$S$8977,9,FALSE) -> Production | K8: =VLOOKUP(B8,All!$B$4:$S$8977,10,FALSE) -> Cutting | L8: =VLOOKUP(B8,All!$B$4:$S$8977,11,FALSE) -> Assist. Cutting | AH8: 2 | AI8: 0 | AJ8: 0 | AK8: 0 | AL8: 0 | AM8: 0 | AN8: 0 | AO8: 2
A9: =1+A8 -> 6 | B9: 1886 | C9: =VLOOKUP(B9,All!$B$4:$S$8977,2,FALSE) -> នាង | D9: =VLOOKUP(B9,All!$B$4:$S$89977,3,FALSE) -> ពោច | E9: =VLOOKUP(B9,All!$B$4:$S$8977,4,FALSE) -> NEANG | F9: =VLOOKUP(B9,All!$B$4:$S$8977,5,FALSE) -> POCH | G9: =VLOOKUP(B9,All!$B$4:$S$8977,6,FALSE) -> M | H9: =VLOOKUP(B9,All!$B$4:$S$8977,7,FALSE) -> 32759 | I9: =VLOOKUP(B9,All!$B$4:$S$8977,8,FALSE) -> 42811 | J9: =VLOOKUP(B9,All!$B$4:$S$8977,9,FALSE) -> Production | K9: =VLOOKUP(B9,All!$B$4:$S$8977,10,FALSE) -> Cutting | L9: =VLOOKUP(B9,All!$B$4:$S$8977,11,FALSE) -> Cutter | M9: =VLOOKUP(B9,All!$B$4:$S$8977,12,FALSE) -> 192 | N9: =VLOOKUP(B9,All!$B$4:$S$8977,13,FALSE) -> 5 | O9: =VLOOKUP(B9,All!$B$4:$S$8977,14,FALSE) -> 20 | P9: =VLOOKUP(B9,All!$B$4:$S$8977,15,FALSE) -> 15 | Q9: =VLOOKUP(B9,All!$B$4:$S$8977,16,FALSE) -> 0 | R9: 7 | S9: 10 | T9: =SUM(M9:S9) -> 249 | Z9: =M9+AH9 -> 194 | AA9: =N9 -> 5 | AB9: =O9 -> 20 | AC9: =P9 -> 15 | AD9: =Q9 -> 0 | AE9: =R9 -> 7 | AF9: =S9 -> 10 | AG9: =SUM(Z9:AF9) -> 251 | AH9: 2 | AI9: 0 | AJ9: 0 | AK9: 0 | AL9: 0 | AM9: 0 | AN9: 0 | AO9: 2
A10: =1+A9 -> 7 | B10: 2305 | C10: =VLOOKUP(B10,All!$B$4:$S$8977,2,FALSE) -> លាម | D10: =VLOOKUP(B10,All!$B$4:$S$89977,3,FALSE) -> វី | E10: =VLOOKUP(B10,All!$B$4:$S$8977,4,FALSE) -> LEAM | F10: =VLOOKUP(B10,All!$B$4:$S$8977,5,FALSE) -> VY | G10: =VLOOKUP(B10,All!$B$4:$S$8977,6,FALSE) -> M | H10: =VLOOKUP(B10,All!$B$4:$S$8977,7,FALSE) -> 25691 | I10: =VLOOKUP(B10,All!$B$4:$S$8977,8,FALSE) -> 43022 | J10: =VLOOKUP(B10,All!$B$4:$S$8977,9,FALSE) -> Production | K10: =VLOOKUP(B10,All!$B$4:$S$8977,10,FALSE) -> Cutting | L10: =VLOOKUP(B10,All!$B$4:$S$8977,11,FALSE) -> spreader | M10: =VLOOKUP(B10,All!$B$4:$S$8977,12,FALSE) -> 192 | N10: =VLOOKUP(B10,All!$B$4:$S$8977,13,FALSE) -> 5 | O10: =VLOOKUP(B10,All!$B$4:$S$8977,14,FALSE) -> 20 | P10: =VLOOKUP(B10,All!$B$4:$S$8977,15,FALSE) -> 23 | Q10: =VLOOKUP(B10,All!$B$4:$S$8977,16,FALSE) -> 0 | R10: 7 | S10: 10 | T10: =SUM(M10:S10) -> 257 | Z10: =M10+AH10 -> 194 | AA10: =N10 -> 5 | AB10: =O10 -> 20 | AC10: =P10 -> 23 | AD10: =Q10 -> 0 | AE10: =R10 -> 7 | AF10: =S10 -> 10 | AG10: =SUM(Z10:AF10) -> 259 | AH10: 2 | AI10: 0 | AJ10: 0 | AK10: 0 | AL10: 0 | AM10: 0 | AN10: 0 | AO10: 2
A11: =1+A10 -> 8 | B11: 2325 | C11: =VLOOKUP(B11,All!$B$4:$S$8977,2,FALSE) -> ស្រី | D11: =VLOOKUP(B11,All!$B$4:$S$89977,3,FALSE) -> លាង | E11: =VLOOKUP(B11,All!$B$4:$S$8977,4,FALSE) -> SRY | F11: =VLOOKUP(B11,All!$B$4:$S$8977,5,FALSE) -> LEANG | G11: =VLOOKUP(B11,All!$B$4:$S$8977,6,FALSE) -> M | H11: =VLOOKUP(B11,All!$B$4:$S$8977,7,FALSE) -> 33004 | I11: =VLOOKUP(B11,All!$B$4:$S$8977,8,FALSE) -> 43050 | J11: =VLOOKUP(B11,All!$B$4:$S$8977,9,FALSE) -> Production | K11: =VLOOKUP(B11,All!$B$4:$S$8977,10,FALSE) -> Cutting | L11: =VLOOKUP(B11,All!$B$4:$S$8977,11,FALSE) -> spreader | M11: =VLOOKUP(B11,All!$B$4:$S$8977,12,FALSE) -> 192 | N11: =VLOOKUP(B11,All!$B$4:$S$8977,13,FALSE) -> 5 | O11: =VLOOKUP(B11,All!$B$4:$S$8977,14,FALSE) -> 20 | P11: =VLOOKUP(B11,All!$B$4:$S$8977,15,FALSE) -> 23 | Q11: =VLOOKUP(B11,All!$B$4:$S$8977,16,FALSE) -> 0 | R11: 7 | S11: 10 | T11: =SUM(M11:S11) -> 257 | Z11: =M11+AH11 -> 194 | AA11: =N11 -> 5 | AB11: =O11 -> 20 | AC11: =P11 -> 23 | AD11: =Q11 -> 0 | AE11: =R11 -> 7 | AF11: =S11 -> 10 | AG11: =SUM(Z11:AF11) -> 259 | AH11: 2 | AI11: 0 | AJ11: 0 | AK11: 0 | AL11: 0 | AM11: 0 | AN11: 0 | AO11: 2
A12: =1+A11 -> 9 | B12: 2444 | C12: =VLOOKUP(B12,All!$B$4:$S$8977,2,FALSE) -> ងី | D12: =VLOOKUP(B12,All!$B$4:$S$89977,3,FALSE) -> ឡាឌី | E12: =VLOOKUP(B12,All!$B$4:$S$8977,4,FALSE) -> Ngy | F12: =VLOOKUP(B12,All!$B$4:$S$8977,5,FALSE) -> Lady | G12: =VLOOKUP(B12,All!$B$4:$S$8977,6,FALSE) -> F | H12: =VLOOKUP(B12,All!$B$4:$S$8977,7,FALSE) -> 26613 | I12: =VLOOKUP(B12,All!$B$4:$S$8977,8,FALSE) -> 43273 | J12: =VLOOKUP(B12,All!$B$4:$S$8977,9,FALSE) -> Production | K12: =VLOOKUP(B12,All!$B$4:$S$8977,10,FALSE) -> Cutting | L12: =VLOOKUP(B12,All!$B$4:$S$8977,11,FALSE) -> spreader | M12: =VLOOKUP(B12,All!$B$4:$S$8977,12,FALSE) -> 192 | N12: =VLOOKUP(B12,All!$B$4:$S$8977,13,FALSE) -> 4 | O12: =VLOOKUP(B12,All!$B$4:$S$8977,14,FALSE) -> 20 | P12: =VLOOKUP(B12,All!$B$4:$S$8977,15,FALSE) -> 0 | Q12: =VLOOKUP(B12,All!$B$4:$S$8977,16,FALSE) -> 0 | R12: 7 | S12: 10 | T12: =SUM(M12:S12) -> 233 | Z12: =M12+AH12 -> 194 | AA12: =N12 -> 4 | AB12: =O12 -> 20 | AC12: =P12 -> 0 | AD12: =Q12 -> 0 | AE12: =R12 -> 7 | AF12: =S12 -> 10 | AG12: =SUM(Z12:AF12) -> 235 | AH12: 2 | AI12: 0 | AJ12: 0 | AK12: 0 | AL12: 0 | AM12: 0 | AN12: 0 | AO12: 2
A13: =1+A12 -> 10 | B13: 2827 | C13: =VLOOKUP(B13,All!$B$4:$S$8977,2,FALSE) -> គុយ | D13: =VLOOKUP(B13,All!$B$4:$S$89977,3,FALSE) -> ខ្លី | E13: =VLOOKUP(B13,All!$B$4:$S$8977,4,FALSE) -> Kuy | F13: =VLOOKUP(B13,All!$B$4:$S$8977,5,FALSE) -> Khley | G13: =VLOOKUP(B13,All!$B$4:$S$8977,6,FALSE) -> F | H13: =VLOOKUP(B13,All!$B$4:$S$8977,7,FALSE) -> 31328 | I13: =VLOOKUP(B13,All!$B$4:$S$8977,8,FALSE) -> 43577 | J13: =VLOOKUP(B13,All!$B$4:$S$8977,9,FALSE) -> Production | K13: =VLOOKUP(B13,All!$B$4:$S$8977,10,FALSE) -> Cutting | L13: =VLOOKUP(B13,All!$B$4:$S$8977,11,FALSE) -> spreader | M13: =VLOOKUP(B13,All!$B$4:$S$8977,12,FALSE) -> 192 | N13: =VLOOKUP(B13,All!$B$4:$S$8977,13,FALSE) -> 3 | O13: =VLOOKUP(B13,All!$B$4:$S$8977,14,FALSE) -> 0 | P13: =VLOOKUP(B13,All!$B$4:$S$8977,15,FALSE) -> 0 | Q13: =VLOOKUP(B13,All!$B$4:$S$8977,16,FALSE) -> 0 | R13: 7 | S13: 10 | T13: =SUM(M13:S13) -> 212 | Z13: =M13+AH13 -> 194 | AA13: =N13 -> 3 | AB13: =O13 -> 0 | AC13: =P13 -> 0 | AD13: =Q13 -> 0 | AE13: =R13 -> 7 | AF13: =S13 -> 10 | AG13: =SUM(Z13:AF13) -> 214 | AH13: 2 | AI13: 0 | AJ13: 0 | AK13: 0 | AL13: 0 | AM13: 0 | AN13: 0 | AO13: 2
A14: =1+A13 -> 11 | B14: 2890 | C14: =VLOOKUP(B14,All!$B$4:$S$8977,2,FALSE) -> សៅ | D14: =VLOOKUP(B14,All!$B$4:$S$89977,3,FALSE) -> តាប់ | E14: =VLOOKUP(B14,All!$B$4:$S$8977,4,FALSE) -> Sao | F14: =VLOOKUP(B14,All!$B$4:$S$8977,5,FALSE) -> Tap | G14: =VLOOKUP(B14,All!$B$4:$S$8977,6,FALSE) -> M | H14: =VLOOKUP(B14,All!$B$4:$S$8977,7,FALSE) -> 34920 | I14: =VLOOKUP(B14,All!$B$4:$S$8977,8,FALSE) -> 43587 | J14: =VLOOKUP(B14,All!$B$4:$S$8977,9,FALSE) -> Production | K14: =VLOOKUP(B14,All!$B$4:$S$8977,10,FALSE) -> Cutting | L14: =VLOOKUP(B14,All!$B$4:$S$8977,11,FALSE) -> spreader | M14: =VLOOKUP(B14,All!$B$4:$S$8977,12,FALSE) -> 192 | N14: =VLOOKUP(B14,All!$B$4:$S$8977,13,FALSE) -> 3 | O14: =VLOOKUP(B14,All!$B$4:$S$8977,14,FALSE) -> 0 | P14: =VLOOKUP(B14,All!$B$4:$S$8977,15,FALSE) -> 0 | Q14: =VLOOKUP(B14,All!$B$4:$S$8977,16,FALSE) -> 0 | R14: 7 | S14: 10 | T14: =SUM(M14:S14) -> 212 | Z14: =M14+AH14 -> 194 | AA14: =N14 -> 3 | AB14: =O14 -> 0 | AC14: =P14 -> 0 | AD14: =Q14 -> 0 | AE14: =R14 -> 7 | AF14: =S14 -> 10 | AG14: =SUM(Z14:AF14) -> 214 | AH14: 2 | AI14: 0 | AJ14: 0 | AK14: 0 | AL14: 0 | AM14: 0 | AN14: 0 | AO14: 2
A15: =1+A14 -> 12 | B15: 2992 | C15: =VLOOKUP(B15,All!$B$4:$S$8977,2,FALSE) -> ប៊ន | D15: =VLOOKUP(B15,All!$B$4:$S$89977,3,FALSE) -> រីករាយ | E15: =VLOOKUP(B15,All!$B$4:$S$8977,4,FALSE) -> Born | F15: =VLOOKUP(B15,All!$B$4:$S$8977,5,FALSE) -> Rikreay | G15: =VLOOKUP(B15,All!$B$4:$S$8977,6,FALSE) -> M | H15: =VLOOKUP(B15,All!$B$4:$S$8977,7,FALSE) -> 36285 | I15: =VLOOKUP(B15,All!$B$4:$S$8977,8,FALSE) -> 43619 | J15: =VLOOKUP(B15,All!$B$4:$S$8977,9,FALSE) -> Production | K15: =VLOOKUP(B15,All!$B$4:$S$8977,10,FALSE) -> Cutting | L15: =VLOOKUP(B15,All!$B$4:$S$8977,11,FALSE) -> spreader | M15: =VLOOKUP(B15,All!$B$4:$S$8977,12,FALSE) -> 192 | N15: =VLOOKUP(B15,All!$B$4:$S$8977,13,FALSE) -> 3 | O15: =VLOOKUP(B15,All!$B$4:$S$8977,14,FALSE) -> 0 | P15: =VLOOKUP(B15,All!$B$4:$S$8977,15,FALSE) -> 0 | Q15: =VLOOKUP(B15,All!$B$4:$S$8977,16,FALSE) -> 0 | R15: 7 | S15: 10 | T15: =SUM(M15:S15) -> 212 | Z15: =M15+AH15 -> 194 | AA15: =N15 -> 3 | AB15: =O15 -> 0 | AC15: =P15 -> 0 | AD15: =Q15 -> 0 | AE15: =R15 -> 7 | AF15: =S15 -> 10 | AG15: =SUM(Z15:AF15) -> 214 | AH15: 2 | AI15: 0 | AJ15: 0 | AK15: 0 | AL15: 0 | AM15: 0 | AN15: 0 | AO15: 2
A16: =1+A15 -> 13 | B16: 3062 | C16: =VLOOKUP(B16,All!$B$4:$S$8977,2,FALSE) -> សៅ | D16: =VLOOKUP(B16,All!$B$4:$S$89977,3,FALSE) -> វ៉ាន | E16: =VLOOKUP(B16,All!$B$4:$S$8977,4,FALSE) -> Sov | F16: =VLOOKUP(B16,All!$B$4:$S$8977,5,FALSE) -> Van | G16: =VLOOKUP(B16,All!$B$4:$S$8977,6,FALSE) -> M | H16: =VLOOKUP(B16,All!$B$4:$S$8977,7,FALSE) -> 32569 | I16: =VLOOKUP(B16,All!$B$4:$S$8977,8,FALSE) -> 43664 | J16: =VLOOKUP(B16,All!$B$4:$S$8977,9,FALSE) -> Production | K16: =VLOOKUP(B16,All!$B$4:$S$8977,10,FALSE) -> Cutting | L16: =VLOOKUP(B16,All!$B$4:$S$8977,11,FALSE) -> spreader | M16: =VLOOKUP(B16,All!$B$4:$S$8977,12,FALSE) -> 192 | N16: =VLOOKUP(B16,All!$B$4:$S$8977,13,FALSE) -> 3 | O16: =VLOOKUP(B16,All!$B$4:$S$8977,14,FALSE) -> 0 | P16: =VLOOKUP(B16,All!$B$4:$S$8977,15,FALSE) -> 0 | Q16: =VLOOKUP(B16,All!$B$4:$S$8977,16,FALSE) -> 0 | R16: 7 | S16: 10 | T16: =SUM(M16:S16) -> 212 | Z16: =M16+AH16 -> 194 | AA16: =N16 -> 3 | AB16: =O16 -> 0 | AC16: =P16 -> 0 | AD16: =Q16 -> 0 | AE16: =R16 -> 7 | AF16: =S16 -> 10 | AG16: =SUM(Z16:AF16) -> 214 | AH16: 2 | AI16: 0 | AJ16: 0 | AK16: 0 | AL16: 0 | AM16: 0 | AN16: 0 | AO16: 2
A17: =1+A16 -> 14 | B17: 3335 | C17: =VLOOKUP(B17,All!$B$4:$S$8977,2,FALSE) -> ស្រី | D17: =VLOOKUP(B17,All!$B$4:$S$89977,3,FALSE) -> សាត | E17: =VLOOKUP(B17,All!$B$4:$S$8977,4,FALSE) -> Srey | F17: =VLOOKUP(B17,All!$B$4:$S$8977,5,FALSE) -> Sat | G17: =VLOOKUP(B17,All!$B$4:$S$8977,6,FALSE) -> M | H17: =VLOOKUP(B17,All!$B$4:$S$8977,7,FALSE) -> 30651 | I17: =VLOOKUP(B17,All!$B$4:$S$8977,8,FALSE) -> 43749 | J17: =VLOOKUP(B17,All!$B$4:$S$8977,9,FALSE) -> Production | K17: =VLOOKUP(B17,All!$B$4:$S$8977,10,FALSE) -> Cutting | L17: =VLOOKUP(B17,All!$B$4:$S$8977,11,FALSE) -> helper | M17: =VLOOKUP(B17,All!$B$4:$S$8977,12,FALSE) -> 192 | N17: =VLOOKUP(B17,All!$B$4:$S$8977,13,FALSE) -> 3 | O17: =VLOOKUP(B17,All!$B$4:$S$8977,14,FALSE) -> 0 | P17: =VLOOKUP(B17,All!$B$4:$S$8977,15,FALSE) -> 0 | Q17: =VLOOKUP(B17,All!$B$4:$S$8977,16,FALSE) -> 0 | R17: 7 | S17: 10 | T17: =SUM(M17:S17) -> 212 | Z17: =M17+AH17 -> 194 | AA17: =N17 -> 3 | AB17: =O17 -> 0 | AC17: =P17 -> 0 | AD17: =Q17 -> 0 | AE17: =R17 -> 7 | AF17: =S17 -> 10 | AG17: =SUM(Z17:AF17) -> 214 | AH17: 2 | AI17: 0 | AJ17: 0 | AK17: 0 | AL17: 0 | AM17: 0 | AN17: 0 | AO17: 2
A18: =1+A17 -> 15 | B18: 3255 | C18: =VLOOKUP(B18,All!$B$4:$S$8977,2,FALSE) -> អ៊ិន | D18: =VLOOKUP(B18,All!$B$4:$S$89977,3,FALSE) -> ចាន់ចាវ | E18: =VLOOKUP(B18,All!$B$4:$S$8977,4,FALSE) -> IN | F18: =VLOOKUP(B18,All!$B$4:$S$8977,5,FALSE) -> CHANCHAV | G18: =VLOOKUP(B18,All!$B$4:$S$8977,6,FALSE) -> M | H18: =VLOOKUP(B18,All!$B$4:$S$8977,7,FALSE) -> 34360 | I18: =VLOOKUP(B18,All!$B$4:$S$8977,8,FALSE) -> 43745 | J18: =VLOOKUP(B18,All!$B$4:$S$8977,9,FALSE) -> Production | K18: =VLOOKUP(B18,All!$B$4:$S$8977,10,FALSE) -> Cutting | L18: =VLOOKUP(B18,All!$B$4:$S$8977,11,FALSE) -> helper | M18: =VLOOKUP(B18,All!$B$4:$S$8977,12,FALSE) -> 192 | N18: =VLOOKUP(B18,All!$B$4:$S$8977,13,FALSE) -> 3 | O18: =VLOOKUP(B18,All!$B$4:$S$8977,14,FALSE) -> 0 | P18: =VLOOKUP(B18,All!$B$4:$S$8977,15,FALSE) -> 20 | Q18: =VLOOKUP(B18,All!$B$4:$S$8977,16,FALSE) -> 0 | R18: 7 | S18: 10 | T18: =SUM(M18:S18) -> 232 | Z18: =M18+AH18 -> 194 | AA18: =N18 -> 3 | AB18: =O18 -> 0 | AC18: =P18 -> 20 | AD18: =Q18 -> 0 | AE18: =R18 -> 7 | AF18: =S18 -> 10 | AG18: =SUM(Z18:AF18) -> 234 | AH18: 2 | AI18: 0 | AJ18: 0 | AK18: 0 | AL18: 0 | AM18: 0 | AN18: 0 | AO18: 2
A19: =1+A18 -> 16 | B19: 3603 | C19: =VLOOKUP(B19,All!$B$4:$S$8977,2,FALSE) -> ជ័យ | D19: =VLOOKUP(B19,All!$B$4:$S$89977,3,FALSE) -> ប៊ុនធឿន | E19: =VLOOKUP(B19,All!$B$4:$S$8977,4,FALSE) -> CHEY | F19: =VLOOKUP(B19,All!$B$4:$S$8977,5,FALSE) -> BUNTHOUEN | G19: =VLOOKUP(B19,All!$B$4:$S$8977,6,FALSE) -> M | H19: =VLOOKUP(B19,All!$B$4:$S$8977,7,FALSE) -> 30900 | I19: =VLOOKUP(B19,All!$B$4:$S$8977,8,FALSE) -> 43753 | J19: =VLOOKUP(B19,All!$B$4:$S$8977,9,FALSE) -> Production | K19: =VLOOKUP(B19,All!$B$4:$S$8977,10,FALSE) -> Cutting | L19: =VLOOKUP(B19,All!$B$4:$S$8977,11,FALSE) -> helper | M19: =VLOOKUP(B19,All!$B$4:$S$8977,12,FALSE) -> 192 | N19: =VLOOKUP(B19,All!$B$4:$S$8977,13,FALSE) -> 3 | O19: =VLOOKUP(B19,All!$B$4:$S$8977,14,FALSE) -> 0 | P19: =VLOOKUP(B19,All!$B$4:$S$8977,15,FALSE) -> 0 | Q19: =VLOOKUP(B19,All!$B$4:$S$8977,16,FALSE) -> 0 | R19: 7 | S19: 10 | T19: =SUM(M19:S19) -> 212 | Z19: =M19+AH19 -> 194 | AA19: =N19 -> 3 | AB19: =O19 -> 0 | AC19: =P19 -> 0 | AD19: =Q19 -> 0 | AE19: =R19 -> 7 | AF19: =S19 -> 10 | AG19: =SUM(Z19:AF19) -> 214 | AH19: 2 | AI19: 0 | AJ19: 0 | AK19: 0 | AL19: 0 | AM19: 0 | AN19: 0 | AO19: 2
A20: =1+A19 -> 17 | B20: 4067 | C20: =VLOOKUP(B20,All!$B$4:$S$8977,2,FALSE) -> ហួន | D20: =VLOOKUP(B20,All!$B$4:$S$89977,3,FALSE) -> ថាន | E20: =VLOOKUP(B20,All!$B$4:$S$8977,4,FALSE) -> HUON | F20: =VLOOKUP(B20,All!$B$4:$S$8977,5,FALSE) -> THAN | G20: =VLOOKUP(B20,All!$B$4:$S$8977,6,FALSE) -> M | H20: =VLOOKUP(B20,All!$B$4:$S$8977,7,FALSE) -> 37057 | I20: =VLOOKUP(B20,All!$B$4:$S$8977,8,FALSE) -> 43846 | J20: =VLOOKUP(B20,All!$B$4:$S$8977,9,FALSE) -> Production | K20: =VLOOKUP(B20,All!$B$4:$S$8977,10,FALSE) -> Cutting | L20: =VLOOKUP(B20,All!$B$4:$S$8977,11,FALSE) -> helper | M20: =VLOOKUP(B20,All!$B$4:$S$8977,12,FALSE) -> 192 | N20: =VLOOKUP(B20,All!$B$4:$S$8977,13,FALSE) -> 3 | O20: =VLOOKUP(B20,All!$B$4:$S$8977,14,FALSE) -> 0 | P20: =VLOOKUP(B20,All!$B$4:$S$8977,15,FALSE) -> 0 | Q20: =VLOOKUP(B20,All!$B$4:$S$8977,16,FALSE) -> 0 | R20: 7 | S20: 10 | T20: =SUM(M20:S20) -> 212 | Z20: =M20+AH20 -> 194 | AA20: =N20 -> 3 | AB20: =O20 -> 0 | AC20: =P20 -> 0 | AD20: =Q20 -> 0 | AE20: =R20 -> 7 | AF20: =S20 -> 10 | AG20: =SUM(Z20:AF20) -> 214 | AH20: 2 | AI20: 0 | AJ20: 0 | AK20: 0 | AL20: 0 | AM20: 0 | AN20: 0 | AO20: 2
... A27: =1+A26 -> 24 | B27: 5178 | C27: =VLOOKUP(B27,All!$B$4:$S$8977,2,FALSE) -> ឌឿប | D27: =VLOOKUP(B27,All!$B$4:$S$89977,3,FALSE) -> មុំហឿន | E27: =VLOOKUP(B27,All!$B$4:$S$8977,4,FALSE) -> DIEB | F27: =VLOOKUP(B27,All!$B$4:$S$8977,5,FALSE) -> MOMHOEUN | G27: =VLOOKUP(B27,All!$B$4:$S$8977,6,FALSE) -> M | H27: =VLOOKUP(B27,All!$B$4:$S$8977,7,FALSE) -> 33865 | I27: =VLOOKUP(B27,All!$B$4:$S$8977,8,FALSE) -> 44488 | J27: =VLOOKUP(B27,All!$B$4:$S$8977,9,FALSE) -> Production | K27: =VLOOKUP(B27,All!$B$4:$S$8977,10,FALSE) -> Cutting | L27: =VLOOKUP(B27,All!$B$4:$S$8977,11,FALSE) -> spreader | M27: =VLOOKUP(B27,All!$B$4:$S$8977,12,FALSE) -> 187 | N27: =VLOOKUP(B27,All!$B$4:$S$8977,13,FALSE) -> 0 | O27: =VLOOKUP(B27,All!$B$4:$S$8977,14,FALSE) -> 0 | P27: =VLOOKUP(B27,All!$B$4:$S$8977,15,FALSE) -> 0 | Q27: =VLOOKUP(B27,All!$B$4:$S$8977,16,FALSE) -> 0 | R27: 7 | S27: 10 | T27: =SUM(M27:S27) -> 204 | Z27: =M27+AH27 -> 189 | AA27: =N27 -> 0 | AB27: =O27 -> 0 | AC27: =P27 -> 0 | AD27: =Q27 -> 0 | AE27: =R27 -> 7 | AF27: =S27 -> 10 | AG27: =SUM(Z27:AF27) -> 206 | AH27: 2 | AI27: 0 | AJ27: 0 | AK27: 0 | AL27: 0 | AM27: 0 | AN27: 0 | AO27: 2
T29: =SUM(T4:T28) -> 5136 | AG29: =SUM(AG4:AG28) -> 5182 | AH29: =SUM(AH4:AH28) -> 48 | AI29: =SUM(AI4:AI28) -> 0

Sheet Machine on line
A1: ល.រ | B1: Factory ID | C1: គោត្តនាម | D1: នាម | E1: គោត្តនាមឡាតាំង | F1: នាមឡាតាំង | G1: ភេទ | H1: ថ្ងៃខែឆ្នាំកំណើត | I1: កាលបរិ. ចូលធ្វើការ | J1: ផ្នែក | K1: ក្រុម | L1: តួនាទី | M1: Salary Report 2021 | U1: Adjust amount | V1: Adjust Date | W1: Evaluator | X1: 2022 Total Marks | Y1: With Comment | Z1: Salary Report 2022
A2: Nº | B2: Factory ID | C2: Khmer Sure name | D2: Khmer Name | E2: English Sure name | F2: Khmer Name | G2: Sex | H2: Birth of Date | I2: Join Date | J2: Department | K2: Group | L2: Position | M2: Basic | N2: Seniority | O2: Skill | P2: Position | Q2: Language | R2: Housing &Transportation | S2: Motivation | T2: Total | U2: 調動金額 | V2: 調動日期 | W2: 評核人 | X2: 2022總分 | Y2: 意見 | Z2: Basic | AA2: Seniority | AB2: Skill | AC2: Position | AD2: Language | AE2: Housing &Transportation | AF2: Motivation | AG2: Total
A3: 排序 | B3: 工號 | E3: 姓名 | G3: 性別 | H3: 生日 | I3: 入職日期 | J3: 部門 | K3: 組別 | L3: 崗位名稱 | M3: 底薪 | N3: 工齡 | O3: 技能 | P3: 職位 | Q3: 語言 | R3: 房屋/交通 | S3: 全勤 | T3: 2021薪資總額 | U3: 調動金額 | V3: 調動日期 | W3: 評核人 | X3: 2022總分 | Y3: 意見 | Z3: 底薪 | AA3: 工齡 | AB3: 技能 | AC3: 職位 | AD3: 語言 | AE3: 房屋/交通 | AF3: 全勤 | AG3: 2022薪資總額
A4: =1 -> 1 | B4: 2679 | C4: =VLOOKUP(B4,All!$B$4:$S$8977,2,FALSE) -> ប៉ោ | D4: =VLOOKUP(B4,All!$B$4:$S$89977,3,FALSE) -> ចន្ទ័តារ៉ា | E4: =VLOOKUP(B4,All!$B$4:$S$8977,4,FALSE) -> Por | F4: =VLOOKUP(B4,All!$B$4:$S$8977,5,FALSE) -> ChanDara | G4: =VLOOKUP(B4,All!$B$4:$S$8977,6,FALSE) -> M | H4: =VLOOKUP(B4,All!$B$4:$S$8977,7,FALSE) -> 26419 | I4: =VLOOKUP(B4,All!$B$4:$S$8977,8,FALSE) -> 43498 | J4: =VLOOKUP(B4,All!$B$4:$S$8977,9,FALSE) -> Production | K4: =VLOOKUP(B4,All!$B$4:$S$8977,10,FALSE) -> Machine on Line | L4: =VLOOKUP(B4,All!$B$4:$S$8977,11,FALSE) -> mechanic | M4: =VLOOKUP(B4,All!$B$4:$S$8977,12,FALSE) -> 192 | N4: =VLOOKUP(B4,All!$B$4:$S$8977,13,FALSE) -> 3 | O4: =VLOOKUP(B4,All!$B$4:$S$8977,14,FALSE) -> 0 | P4: =VLOOKUP(B4,All!$B$4:$S$8977,15,FALSE) -> 148 | Q4: =VLOOKUP(B4,All!$B$4:$S$8977,16,FALSE) -> 0 | R4: 7 | S4: 10 | T4: =SUM(M4:S4) -> 360 | Z4: =M4+AH4 -> 194 | AA4: =N4 -> 3 | AB4: =O4 -> 0 | AC4: =P4 -> 148 | AD4: =Q4 -> 0 | AE4: =R4 -> 7 | AF4: =S4 -> 10 | AG4: =SUM(Z4:AF4) -> 362 | AH4: 2 | AI4: 0 | AJ4: 0 | AK4: 0 | AL4: 0 | AM4: 0 | AN4: 0 | AO4: 2
A5: =1+A4 -> 2 | B5: 2710 | C5: =VLOOKUP(B5,All!$B$4:$S$8977,2,FALSE) -> គង់ | D5: =VLOOKUP(B5,All!$B$4:$S$89977,3,FALSE) -> ភឿន | E5: =VLOOKUP(B5,All!$B$4:$S$8977,4,FALSE) -> Kong | F5: =VLOOKUP(B5,All!$B$4:$S$8977,5,FALSE) -> Phoeun | G5: =VLOOKUP(B5,All!$B$4:$S$8977,6,FALSE) -> M | H5: =VLOOKUP(B5,All!$B$4:$S$8977,7,FALSE) -> 29314 | I5: =VLOOKUP(B5,All!$B$4:$S$8977,8,FALSE) -> 43508 | J5: =VLOOKUP(B5,All!$B$4:$S$8977,9,FALSE) -> Production | K5: =VLOOKUP(B5,All!$B$4:$S$8977,10,FALSE) -> Machine on Line | L5: =VLOOKUP(B5,All!$B$4:$S$8977,11,FALSE) -> mechanic | M5: =VLOOKUP(B5,All!$B$4:$S$8977,12,FALSE) -> 192 | N5: =VLOOKUP(B5,All!$B$4:$S$8977,13,FALSE) -> 3 | O5: =VLOOKUP(B5,All!$B$4:$S$8977,14,FALSE) -> 0 | P5: =VLOOKUP(B5,All!$B$4:$S$8977,15,FALSE) -> 173 | Q5: =VLOOKUP(B5,All!$B$4:$S$8977,16,FALSE) -> 0 | R5: 7 | S5: 10 | T5: =SUM(M5:S5) -> 385 | Z5: =M5+AH5 -> 194 | AA5: =N5 -> 3 | AB5: =O5 -> 0 | AC5: =P5 -> 173 | AD5: =Q5 -> 0 | AE5: =R5 -> 7 | AF5: =S5 -> 10 | AG5: =SUM(Z5:AF5) -> 387 | AH5: 2 | AI5: 0 | AJ5: 0 | AK5: 0 | AL5: 0 | AM5: 0 | AN5: 0 | AO5: 2
A6: =1+A5 -> 3 | B6: 3876 | C6: =VLOOKUP(B6,All!$B$4:$S$8977,2,FALSE) -> ឃៀន | D6: =VLOOKUP(B6,All!$B$4:$S$89977,3,FALSE) -> ខុម | E6: =VLOOKUP(B6,All!$B$4:$S$8977,4,FALSE) -> KHEA | F6: =VLOOKUP(B6,All!$B$4:$S$8977,5,FALSE) -> KHOM | G6: =VLOOKUP(B6,All!$B$4:$S$8977,6,FALSE) -> M | H6: =VLOOKUP(B6,All!$B$4:$S$8977,7,FALSE) -> 29864 | I6: =VLOOKUP(B6,All!$B$4:$S$8977,8,FALSE) -> 43773 | J6: =VLOOKUP(B6,All!$B$4:$S$8977,9,FALSE) -> Production | K6: =VLOOKUP(B6,All!$B$4:$S$8977,10,FALSE) -> Machine on Line | L6: =VLOOKUP(B6,All!$B$4:$S$8977,11,FALSE) -> mechanic | M6: =VLOOKUP(B6,All!$B$4:$S$8977,12,FALSE) -> 192 | N6: =VLOOKUP(B6,All!$B$4:$S$8977,13,FALSE) -> 3 | O6: =VLOOKUP(B6,All!$B$4:$S$8977,14,FALSE) -> 0 | P6: =VLOOKUP(B6,All!$B$4:$S$8977,15,FALSE) -> 168 | Q6: =VLOOKUP(B6,All!$B$4:$S$8977,16,FALSE) -> 0 | R6: 7 | S6: 10 | T6: =SUM(M6:S6) -> 380 | Z6: =M6+AH6 -> 194 | AA6: =N6 -> 3 | AB6: =O6 -> 0 | AC6: =P6 -> 168 | AD6: =Q6 -> 0 | AE6: =R6 -> 7 | AF6: =S6 -> 10 | AG6: =SUM(Z6:AF6) -> 382 | AH6: 2 | AI6: 0 | AJ6: 0 | AK6: 0 | AL6: 0 | AM6: 0 | AN6: 0 | AO6: 2
A7: =1+A6 -> 4 | B7: 4007 | C7: =VLOOKUP(B7,All!$B$4:$S$8977,2,FALSE) -> ខៀវ | D7: =VLOOKUP(B7,All!$B$4:$S$89977,3,FALSE) -> ខី | E7: =VLOOKUP(B7,All!$B$4:$S$8977,4,FALSE) -> KHIEV | F7: =VLOOKUP(B7,All!$B$4:$S$8977,5,FALSE) -> KHEY | G7: =VLOOKUP(B7,All!$B$4:$S$8977,6,FALSE) -> M | H7: =VLOOKUP(B7,All!$B$4:$S$8977,7,FALSE) -> 34416 | I7: =VLOOKUP(B7,All!$B$4:$S$8977,8,FALSE) -> 43834 | J7: =VLOOKUP(B7,All!$B$4:$S$8977,9,FALSE) -> Production | K7: =VLOOKUP(B7,All!$B$4:$S$8977,10,FALSE) -> Machine on Line | L7: =VLOOKUP(B7,All!$B$4:$S$8977,11,FALSE) -> mechanic | M7: =VLOOKUP(B7,All!$B$4:$S$8977,12,FALSE) -> 192 | N7: =VLOOKUP(B7,All!$B$4:$S$8977,13,FALSE) -> 3 | O7: =VLOOKUP(B7,All!$B$4:$S$8977,14,FALSE) -> 0 | P7: =VLOOKUP(B7,All!$B$4:$S$8977,15,FALSE) -> 160 | Q7: =VLOOKUP(B7,All!$B$4:$S$8977,16,FALSE) -> 0 | R7: 7 | S7: 10 | T7: =SUM(M7:S7) -> 372 | Z7: =M7+AH7 -> 194 | AA7: =N7 -> 3 | AB7: =O7 -> 0 | AC7: =P7 -> 160 | AD7: =Q7 -> 0 | AE7: =R7 -> 7 | AF7: =S7 -> 10 | AG7: =SUM(Z7:AF7) -> 374 | AH7: 2 | AI7: 0 | AJ7: 0 | AK7: 0 | AL7: 0 | AM7: 0 | AN7: 0 | AO7: 2
A8: =1+A7 -> 5 | B8: 4059 | C8: =VLOOKUP(B8,All!$B$4:$S$8977,2,FALSE) -> នូត | D8: =VLOOKUP(B8,All!$B$4:$S$89977,3,FALSE) -> មេសា | E8: =VLOOKUP(B8,All!$B$4:$S$8977,4,FALSE) -> NUTH | F8: =VLOOKUP(B8,All!$B$4:$S$8977,5,FALSE) -> MASA | G8: =VLOOKUP(B8,All!$B$4:$S$8977,6,FALSE) -> M | H8: =VLOOKUP(B8,All!$B$4:$S$8977,7,FALSE) -> 33335 | I8: =VLOOKUP(B8,All!$B$4:$S$8977,8,FALSE) -> 43840 | J8: =VLOOKUP(B8,All!$B$4:$S$8977,9,FALSE) -> Production | K8: =VLOOKUP(B8,All!$B$4:$S$8977,10,FALSE) -> Machine on Line | L8: =VLOOKUP(B8,All!$B$4:$S$8977,11,FALSE) -> mechanic | M8: =VLOOKUP(B8,All!$B$4:$S$8977,12,FALSE) -> 192 | N8: =VLOOKUP(B8,All!$B$4:$S$8977,13,FALSE) -> 3 | O8: =VLOOKUP(B8,All!$B$4:$S$8977,14,FALSE) -> 0 | P8: =VLOOKUP(B8,All!$B$4:$S$8977,15,FALSE) -> 140 | Q8: =VLOOKUP(B8,All!$B$4:$S$8977,16,FALSE) -> 0 | R8: 7 | S8: 10 | T8: =SUM(M8:S8) -> 352 | Z8: =M8+AH8 -> 194 | AA8: =N8 -> 3 | AB8: =O8 -> 0 | AC8: =P8 -> 140 | AD8: =Q8 -> 0 | AE8: =R8 -> 7 | AF8: =S8 -> 10 | AG8: =SUM(Z8:AF8) -> 354 | AH8: 2 | AI8: 0 | AJ8: 0 | AK8: 0 | AL8: 0 | AM8: 0 | AN8: 0 | AO8: 2
A9: =1+A8 -> 6 | B9: 4079 | C9: =VLOOKUP(B9,All!$B$4:$S$8977,2,FALSE) -> ចាន់ | D9: =VLOOKUP(B9,All!$B$4:$S$89977,3,FALSE) -> ស្រៀង | E9: =VLOOKUP(B9,All!$B$4:$S$8977,4,FALSE) -> CHAN | F9: =VLOOKUP(B9,All!$B$4:$S$8977,5,FALSE) -> SREANG | G9: =VLOOKUP(B9,All!$B$4:$S$8977,6,FALSE) -> M | H9: =VLOOKUP(B9,All!$B$4:$S$8977,7,FALSE) -> 33487 | I9: =VLOOKUP(B9,All!$B$4:$S$8977,8,FALSE) -> 43856 | J9: =VLOOKUP(B9,All!$B$4:$S$8977,9,FALSE) -> Production | K9: =VLOOKUP(B9,All!$B$4:$S$8977,10,FALSE) -> Machine on Line | L9: =VLOOKUP(B9,All!$B$4:$S$8977,11,FALSE) -> mechanic | M9: =VLOOKUP(B9,All!$B$4:$S$8977,12,FALSE) -> 192 | N9: =VLOOKUP(B9,All!$B$4:$S$8977,13,FALSE) -> 2 | O9: =VLOOKUP(B9,All!$B$4:$S$8977,14,FALSE) -> 0 | P9: =VLOOKUP(B9,All!$B$4:$S$8977,15,FALSE) -> 140 | Q9: =VLOOKUP(B9,All!$B$4:$S$8977,16,FALSE) -> 0 | R9: 7 | S9: 10 | T9: =SUM(M9:S9) -> 351 | Z9: =M9+AH9 -> 194 | AA9: =N9 -> 2 | AB9: =O9 -> 0 | AC9: =P9 -> 140 | AD9: =Q9 -> 0 | AE9: =R9 -> 7 | AF9: =S9 -> 10 | AG9: =SUM(Z9:AF9) -> 353 | AH9: 2 | AI9: 0 | AJ9: 0 | AK9: 0 | AL9: 0 | AM9: 0 | AN9: 0 | AO9: 2
T11: =SUM(T4:T9) -> 2200 | AG11: =SUM(AG4:AG9) -> 2212 | AH11: =SUM(AH4:AH9) -> 12 | AI11: =SUM(AI4:AI9) -> 0

Sheet Leader& Supervisor
A1: VRT Salary Report
A2: ល.រ | B2: Factory ID | C2: គោត្តនាម | D2: នាម | E2: គោត្តនាមឡាតាំង | F2: នាមឡាតាំង | G2: ភេទ | H2: ថ្ងៃខែឆ្នាំកំណើត | I2: កាលបរិ. ចូលធ្វើការ | J2: ផ្នែក | K2: ក្រុម | L2: តួនាទី | M2: Salary Report 2021 | U2: Adjust amount | V2: Adjust Date | W2: Evaluator | X2: 2022 Total Marks | Y2: With Comment | Z2: Salary Report 2022
A3: Nº | B3: Factory ID | C3: Khmer Sure name | D3: Khmer Name | E3: English Sure name | F3: Khmer Name | G3: Sex | H3: Birth of Date | I3: Join Date | J3: Department | K3: Group | L3: Position | M3: Basic | N3: Seniority | O3: Skill | P3: Position | Q3: Language | R3: Housing &Transportation | S3: Motivation | T3: Total | U3: 調動金額 | V3: 調動日期 | W3: 評核人 | X3: 2022總分 | Y3: 意見 | Z3: Basic | AA3: Seniority | AB3: Skill | AC3: Position | AD3: Language | AE3: Housing &Transportation | AF3: Motivation | AG3: Total
A4: 排序 | B4: 工號 | E4: 姓名 | G4: 性別 | H4: 生日 | I4: 入職日期 | J4: 部門 | K4: 組別 | L4: 崗位名稱 | M4: 底薪 | N4: 工齡 | O4: 技能 | P4: 職位 | Q4: 語言 | R4: 房屋/交通 | S4: 全勤 | T4: 2021薪資總額 | U4: 調動金額 | V4: 調動日期 | W4: 評核人 | X4: 2022總分 | Y4: 意見 | Z4: 底薪 | AA4: 工齡 | AB4: 技能 | AC4: 職位 | AD4: 語言 | AE4: 房屋/交通 | AF4: 全勤 | AG4: 2022薪資總額
A5: =1 -> 1 | B5: 10 | C5: =VLOOKUP(B5,All!$B$4:$S$8977,2,FALSE) -> ញ៉ិល | D5: =VLOOKUP(B5,All!$B$4:$S$89977,3,FALSE) -> ចន័្នធា | E5: =VLOOKUP(B5,All!$B$4:$S$8977,4,FALSE) -> NHEL | F5: =VLOOKUP(B5,All!$B$4:$S$8977,5,FALSE) -> CHANTHEA | G5: =VLOOKUP(B5,All!$B$4:$S$8977,6,FALSE) -> F | H5: =VLOOKUP(B5,All!$B$4:$S$8977,7,FALSE) -> 30135 | I5: =VLOOKUP(B5,All!$B$4:$S$8977,8,FALSE) -> 41575 | J5: Production | K5: Sewing | L5: Supervisor | M5: =VLOOKUP(B5,All!$B$4:$S$8977,12,FALSE) -> 192 | N5: =VLOOKUP(B5,All!$B$4:$S$8977,13,FALSE) -> 9 | O5: =VLOOKUP(B5,All!$B$4:$S$8977,14,FALSE) -> 20 | P5: =VLOOKUP(B5,All!$B$4:$S$8977,15,FALSE) -> 195 | Q5: =VLOOKUP(B5,All!$B$4:$S$8977,16,FALSE) -> 75 | R5: 7 | S5: 10 | T5: =SUM(M5:S5) -> 508 | U5: 30 | V5: 44562 | W5: Jerry | Y5: 大組長 | Z5: =M5+2 -> 194 | AA5: =N5 -> 9 | AB5: =O5 -> 20 | AC5: =P5+U5 -> 225 | AD5: =Q5 -> 75 | AE5: =R5 -> 7 | AF5: =S5 -> 10 | AG5: =SUM(Z5:AF5) -> 540 | AH5: =Z5-M5 -> 2 | AI5: =AA5-N5 -> 0 | AJ5: =AB5-O5 -> 0 | AK5: =AC5-P5 -> 30 | AL5: =AD5-Q5 -> 0 | AM5: =AE5-R5 -> 0 | AN5: =AF5-S5 -> 0 | AO5: =AG5-T5 -> 32
A6: =1+A5 -> 2 | B6: 30 | C6: =VLOOKUP(B6,All!$B$4:$S$8977,2,FALSE) -> ភោក | D6: =VLOOKUP(B6,All!$B$4:$S$89977,3,FALSE) -> ស៊ីណា | E6: =VLOOKUP(B6,All!$B$4:$S$8977,4,FALSE) -> Phouk | F6: =VLOOKUP(B6,All!$B$4:$S$8977,5,FALSE) -> Sina | G6: =VLOOKUP(B6,All!$B$4:$S$8977,6,FALSE) -> F | H6: =VLOOKUP(B6,All!$B$4:$S$8977,7,FALSE) -> 29927 | I6: =VLOOKUP(B6,All!$B$4:$S$8977,8,FALSE) -> 41579 | J6: Production | K6: Sewing | L6: Supervisor | M6: =VLOOKUP(B6,All!$B$4:$S$8977,12,FALSE) -> 192 | N6: =VLOOKUP(B6,All!$B$4:$S$8977,13,FALSE) -> 9 | O6: =VLOOKUP(B6,All!$B$4:$S$8977,14,FALSE) -> 20 | P6: =VLOOKUP(B6,All!$B$4:$S$8977,15,FALSE) -> 175 | Q6: =VLOOKUP(B6,All!$B$4:$S$8977,16,FALSE) -> 75 | R6: 7 | S6: 10 | T6: =SUM(M6:S6) -> 488 | U6: 30 | V6: 44562 | W6: Jerry | Y6: 大組長 | Z6: =M6+2 -> 194 | AA6: =N6 -> 9 | AB6: =O6 -> 20 | AC6: =P6+U6 -> 205 | AD6: =Q6 -> 75 | AE6: =R6 -> 7 | AF6: =S6 -> 10 | AG6: =SUM(Z6:AF6) -> 520 | AH6: =Z6-M6 -> 2 | AI6: =AA6-N6 -> 0 | AJ6: =AB6-O6 -> 0 | AK6: =AC6-P6 -> 30 | AL6: =AD6-Q6 -> 0 | AM6: =AE6-R6 -> 0 | AN6: =AF6-S6 -> 0 | AO6: =AG6-T6 -> 32
A7: =1+A6 -> 3 | B7: 32 | C7: =VLOOKUP(B7,All!$B$4:$S$8977,2,FALSE) -> ហៀ | D7: =VLOOKUP(B7,All!$B$4:$S$89977,3,FALSE) -> ហឿង | E7: =VLOOKUP(B7,All!$B$4:$S$8977,4,FALSE) -> Hear | F7: =VLOOKUP(B7,All!$B$4:$S$8977,5,FALSE) -> Hoeung | G7: =VLOOKUP(B7,All!$B$4:$S$8977,6,FALSE) -> F | H7: =VLOOKUP(B7,All!$B$4:$S$8977,7,FALSE) -> 27885 | I7: =VLOOKUP(B7,All!$B$4:$S$8977,8,FALSE) -> 41579 | J7: Production | K7: Sewing | L7: Supervisor | M7: =VLOOKUP(B7,All!$B$4:$S$8977,12,FALSE) -> 192 | N7: =VLOOKUP(B7,All!$B$4:$S$8977,13,FALSE) -> 9 | O7: =VLOOKUP(B7,All!$B$4:$S$8977,14,FALSE) -> 0 | P7: =VLOOKUP(B7,All!$B$4:$S$8977,15,FALSE) -> 260 | Q7: =VLOOKUP(B7,All!$B$4:$S$8977,16,FALSE) -> 50 | R7: 7 | S7: 10 | T7: =SUM(M7:S7) -> 528 | U7: 30 | V7: 44562 | W7: Jerry | Y7: 大組長 | Z7: =M7+2 -> 194 | AA7: =N7 -> 9 | AB7: =O7 -> 0 | AC7: =P7+U7 -> 290 | AD7: =Q7 -> 50 | AE7: =R7 -> 7 | AF7: =S7 -> 10 | AG7: =SUM(Z7:AF7) -> 560 | AH7: =Z7-M7 -> 2 | AI7: =AA7-N7 -> 0 | AJ7: =AB7-O7 -> 0 | AK7: =AC7-P7 -> 30 | AL7: =AD7-Q7 -> 0 | AM7: =AE7-R7 -> 0 | AN7: =AF7-S7 -> 0 | AO7: =AG7-T7 -> 32
A8: =1+A7 -> 4 | B8: 39 | C8: =VLOOKUP(B8,All!$B$4:$S$8977,2,FALSE) -> អ៊ឹម | D8: =VLOOKUP(B8,All!$B$4:$S$89977,3,FALSE) -> ស្រីល័ក្ខ | E8: =VLOOKUP(B8,All!$B$4:$S$8977,4,FALSE) -> Oem | F8: =VLOOKUP(B8,All!$B$4:$S$8977,5,FALSE) -> Srey Leak | G8: =VLOOKUP(B8,All!$B$4:$S$8977,6,FALSE) -> F | H8: =VLOOKUP(B8,All!$B$4:$S$8977,7,FALSE) -> 32600 | I8: =VLOOKUP(B8,All!$B$4:$S$8977,8,FALSE) -> 41579 | J8: Production | K8: Sewing/QC | L8: Supervisor | T8: =SUM(M8:S8) -> 0 | Y8: 大組長 | Z8: =M8 -> 0 | AA8: =N8 -> 0 | AB8: =O8 -> 0 | AC8: =P8+U8 -> 0 | AD8: =Q8 -> 0 | AE8: =R8 -> 0 | AF8: =S8 -> 0 | AG8: =SUM(Z8:AF8) -> 0 | AH8: =Z8-M8 -> 0 | AI8: =AA8-N8 -> 0 | AJ8: =AB8-O8 -> 0 | AK8: =AC8-P8 -> 0 | AL8: =AD8-Q8 -> 0 | AM8: =AE8-R8 -> 0 | AN8: =AF8-S8 -> 0 | AO8: =AG8-T8 -> 0
A9: =1+A8 -> 5 | B9: 3233 | C9: =VLOOKUP(B9,All!$B$4:$S$8977,2,FALSE) -> ហង្ស | D9: =VLOOKUP(B9,All!$B$4:$S$89977,3,FALSE) -> ចិន | E9: =VLOOKUP(B9,All!$B$4:$S$8977,4,FALSE) -> HANG | F9: =VLOOKUP(B9,All!$B$4:$S$8977,5,FALSE) -> CHIN | G9: =VLOOKUP(B9,All!$B$4:$S$8977,6,FALSE) -> F | H9: =VLOOKUP(B9,All!$B$4:$S$8977,7,FALSE) -> 30075 | I9: =VLOOKUP(B9,All!$B$4:$S$8977,8,FALSE) -> 43745 | J9: Production | K9: Supervisor | L9: Supervisor | M9: =VLOOKUP(B9,All!$B$4:$S$8977,12,FALSE) -> 192 | N9: =VLOOKUP(B9,All!$B$4:$S$8977,13,FALSE) -> 3 | O9: =VLOOKUP(B9,All!$B$4:$S$8977,14,FALSE) -> 0 | P9: =VLOOKUP(B9,All!$B$4:$S$8977,15,FALSE) -> 85 | Q9: =VLOOKUP(B9,All!$B$4:$S$8977,16,FALSE) -> 150 | R9: 7 | S9: 10 | T9: =SUM(M9:S9) -> 447 | U9: 30 | V9: 44562 | W9: Jerry | Y9: 大組長 | Z9: =M9+2 -> 194 | AA9: =N9 -> 3 | AB9: =O9 -> 0 | AC9: =P9+U9 -> 115 | AD9: =Q9 -> 150 | AE9: =R9 -> 7 | AF9: =S9 -> 10 | AG9: =SUM(Z9:AF9) -> 479 | AH9: =Z9-M9 -> 2 | AI9: =AA9-N9 -> 0 | AJ9: =AB9-O9 -> 0 | AK9: =AC9-P9 -> 30 | AL9: =AD9-Q9 -> 0 | AM9: =AE9-R9 -> 0 | AN9: =AF9-S9 -> 0 | AO9: =AG9-T9 -> 32
A10: =1+A9 -> 6 | B10: 161 | C10: =VLOOKUP(B10,All!$B$4:$S$8977,2,FALSE) -> សែត | D10: =VLOOKUP(B10,All!$B$4:$S$89977,3,FALSE) -> មឿន | E10: =VLOOKUP(B10,All!$B$4:$S$8977,4,FALSE) -> Set | F10: =VLOOKUP(B10,All!$B$4:$S$8977,5,FALSE) -> moeun | G10: =VLOOKUP(B10,All!$B$4:$S$8977,6,FALSE) -> F | H10: =VLOOKUP(B10,All!$B$4:$S$8977,7,FALSE) -> 34710 | I10: =VLOOKUP(B10,All!$B$4:$S$8977,8,FALSE) -> 41674 | J10: Production | K10: Line 1 | L10: Leader Line 1 | M10: =VLOOKUP(B10,All!$B$4:$S$8977,12,FALSE) -> 192 | N10: =VLOOKUP(B10,All!$B$4:$S$8977,13,FALSE) -> 8 | O10: =VLOOKUP(B10,All!$B$4:$S$8977,14,FALSE) -> 20 | P10: =VLOOKUP(B10,All!$B$4:$S$8977,15,FALSE) -> 45 | Q10: =VLOOKUP(B10,All!$B$4:$S$8977,16,FALSE) -> 0 | R10: 7 | S10: 10 | T10: =SUM(M10:S10) -> 282 | U10: 15 | V10: 44562 | W10: Jerry | Y10: 組長 | Z10: =M10+2 -> 194 | AA10: =N10 -> 8 | AB10: =O10 -> 20 | AC10: =P10+U10 -> 60 | AD10: =Q10 -> 0 | AE10: =R10 -> 7 | AF10: =S10 -> 10 | AG10: =SUM(Z10:AF10) -> 299 | AH10: =Z10-M10 -> 2 | AI10: =AA10-N10 -> 0 | AJ10: =AB10-O10 -> 0 | AK10: =AC10-P10 -> 15 | AL10: =AD10-Q10 -> 0 | AM10: =AE10-R10 -> 0 | AN10: =AF10-S10 -> 0 | AO10: =AG10-T10 -> 17
A11: =1+A10 -> 7 | B11: 521 | C11: =VLOOKUP(B11,All!$B$4:$S$8977,2,FALSE) -> ភា | D11: =VLOOKUP(B11,All!$B$4:$S$89977,3,FALSE) -> ទន | E11: =VLOOKUP(B11,All!$B$4:$S$8977,4,FALSE) -> PHEA | F11: =VLOOKUP(B11,All!$B$4:$S$8977,5,FALSE) -> THHON | G11: =VLOOKUP(B11,All!$B$4:$S$8977,6,FALSE) -> F | H11: =VLOOKUP(B11,All!$B$4:$S$8977,7,FALSE) -> 33817 | I11: =VLOOKUP(B11,All!$B$4:$S$8977,8,FALSE) -> 41825 | J11: Production | K11: Line2 | L11: Leader Line 2 | M11: =VLOOKUP(B11,All!$B$4:$S$8977,12,FALSE) -> 192 | N11: =VLOOKUP(B11,All!$B$4:$S$8977,13,FALSE) -> 8 | O11: =VLOOKUP(B11,All!$B$4:$S$8977,14,FALSE) -> 20 | P11: =VLOOKUP(B11,All!$B$4:$S$8977,15,FALSE) -> 45 | Q11: =VLOOKUP(B11,All!$B$4:$S$8977,16,FALSE) -> 0 | R11: 7 | S11: 10 | T11: =SUM(M11:S11) -> 282 | U11: 15 | V11: 44562 | W11: Jerry | Y11: 組長 | Z11: =M11+2 -> 194 | AA11: =N11 -> 8 | AB11: =O11 -> 20 | AC11: =P11+U11 -> 60 | AD11: =Q11 -> 0 | AE11: =R11 -> 7 | AF11: =S11 -> 10 | AG11: =SUM(Z11:AF11) -> 299 | AH11: =Z11-M11 -> 2 | AI11: =AA11-N11 -> 0 | AJ11: =AB11-O11 -> 0 | AK11: =AC11-P11 -> 15 | AL11: =AD11-Q11 -> 0 | AM11: =AE11-R11 -> 0 | AN11: =AF11-S11 -> 0 | AO11: =AG11-T11 -> 17
A12: =1+A11 -> 8 | B12: 3227 | C12: =VLOOKUP(B12,All!$B$4:$S$8977,2,FALSE) -> សឺន | D12: =VLOOKUP(B12,All!$B$4:$S$89977,3,FALSE) -> សំណា | E12: =VLOOKUP(B12,All!$B$4:$S$8977,4,FALSE) -> SEUN | F12: =VLOOKUP(B12,All!$B$4:$S$8977,5,FALSE) -> SAMNA | G12: =VLOOKUP(B12,All!$B$4:$S$8977,6,FALSE) -> M | H12: =VLOOKUP(B12,All!$B$4:$S$8977,7,FALSE) -> 34552 | I12: =VLOOKUP(B12,All!$B$4:$S$8977,8,FALSE) -> 43742 | J12: Production | K12: Line 5 | L12: Leader Line 5 | M12: =VLOOKUP(B12,All!$B$4:$S$8977,12,FALSE) -> 192 | N12: =VLOOKUP(B12,All!$B$4:$S$8977,13,FALSE) -> 3 | O12: =VLOOKUP(B12,All!$B$4:$S$8977,14,FALSE) -> 0 | P12: =VLOOKUP(B12,All!$B$4:$S$8977,15,FALSE) -> 45 | Q12: =VLOOKUP(B12,All!$B$4:$S$8977,16,FALSE) -> 0 | R12: 7 | S12: 10 | T12: =SUM(M12:S12) -> 257 | U12: 15 | V12: 44562 | W12: Jerry | Y12: 組長 | Z12: =M12+2 -> 194 | AA12: =N12 -> 3 | AB12: =O12 -> 0 | AC12: =P12+U12 -> 60 | AD12: =Q12 -> 0 | AE12: =R12 -> 7 | AF12: =S12 -> 10 | AG12: =SUM(Z12:AF12) -> 274 | AH12: =Z12-M12 -> 2 | AI12: =AA12-N12 -> 0 | AJ12: =AB12-O12 -> 0 | AK12: =AC12-P12 -> 15 | AL12: =AD12-Q12 -> 0 | AM12: =AE12-R12 -> 0 | AN12: =AF12-S12 -> 0 | AO12: =AG12-T12 -> 17
A13: =1+A12 -> 9 | B13: 3960 | C13: =VLOOKUP(B13,All!$B$4:$S$8977,2,FALSE) -> ហង់ | D13: =VLOOKUP(B13,All!$B$4:$S$89977,3,FALSE) -> ចាន់នី | E13: =VLOOKUP(B13,All!$B$4:$S$8977,4,FALSE) -> HANG | F13: =VLOOKUP(B13,All!$B$4:$S$8977,5,FALSE) -> CHANNY | G13: =VLOOKUP(B13,All!$B$4:$S$8977,6,FALSE) -> F | H13: =VLOOKUP(B13,All!$B$4:$S$8977,7,FALSE) -> 31483 | I13: =VLOOKUP(B13,All!$B$4:$S$8977,8,FALSE) -> 43820 | J13: Production | K13: Line 6 | L13: Leader Line 6 | M13: =VLOOKUP(B13,All!$B$4:$S$8977,12,FALSE) -> 192 | N13: =VLOOKUP(B13,All!$B$4:$S$8977,13,FALSE) -> 3 | O13: =VLOOKUP(B13,All!$B$4:$S$8977,14,FALSE) -> 0 | P13: =VLOOKUP(B13,All!$B$4:$S$8977,15,FALSE) -> 45 | Q13: =VLOOKUP(B13,All!$B$4:$S$8977,16,FALSE) -> 0 | R13: 7 | S13: 10 | T13: =SUM(M13:S13) -> 257 | U13: 15 | V13: 44562 | W13: Jerry | Y13: 組長 | Z13: =M13+2 -> 194 | AA13: =N13 -> 3 | AB13: =O13 -> 0 | AC13: =P13+U13 -> 60 | AD13: =Q13 -> 0 | AE13: =R13 -> 7 | AF13: =S13 -> 10 | AG13: =SUM(Z13:AF13) -> 274 | AH13: =Z13-M13 -> 2 | AI13: =AA13-N13 -> 0 | AJ13: =AB13-O13 -> 0 | AK13: =AC13-P13 -> 15 | AL13: =AD13-Q13 -> 0 | AM13: =AE13-R13 -> 0 | AN13: =AF13-S13 -> 0 | AO13: =AG13-T13 -> 17
A14: =1+A13 -> 10 | B14: 3047 | C14: =VLOOKUP(B14,All!$B$4:$S$8977,2,FALSE) -> ឯម | D14: =VLOOKUP(B14,All!$B$4:$S$89977,3,FALSE) -> ម៉ាច | E14: =VLOOKUP(B14,All!$B$4:$S$8977,4,FALSE) -> Em | F14: =VLOOKUP(B14,All!$B$4:$S$8977,5,FALSE) -> Mach | G14: =VLOOKUP(B14,All!$B$4:$S$8977,6,FALSE) -> F | H14: =VLOOKUP(B14,All!$B$4:$S$8977,7,FALSE) -> 33765 | I14: =VLOOKUP(B14,All!$B$4:$S$8977,8,FALSE) -> 43648 | J14: Production | K14: Line 8 | L14: Leader Line 8 | M14: =VLOOKUP(B14,All!$B$4:$S$8977,12,FALSE) -> 192 | N14: =VLOOKUP(B14,All!$B$4:$S$8977,13,FALSE) -> 3 | O14: =VLOOKUP(B14,All!$B$4:$S$8977,14,FALSE) -> 0 | P14: =VLOOKUP(B14,All!$B$4:$S$8977,15,FALSE) -> 45 | Q14: =VLOOKUP(B14,All!$B$4:$S$8977,16,FALSE) -> 0 | R14: 7 | S14: 10 | T14: =SUM(M14:S14) -> 257 | U14: 15 | V14: 44562 | W14: Jerry | Y14: 組長 | Z14: =M14+2 -> 194 | AA14: =N14 -> 3 | AB14: =O14 -> 0 | AC14: =P14+U14 -> 60 | AD14: =Q14 -> 0 | AE14: =R14 -> 7 | AF14: =S14 -> 10 | AG14: =SUM(Z14:AF14) -> 274 | AH14: =Z14-M14 -> 2 | AI14: =AA14-N14 -> 0 | AJ14: =AB14-O14 -> 0 | AK14: =AC14-P14 -> 15 | AL14: =AD14-Q14 -> 0 | AM14: =AE14-R14 -> 0 | AN14: =AF14-S14 -> 0 | AO14: =AG14-T14 -> 17
A15: =1+A14 -> 11 | B15: 1569 | C15: =VLOOKUP(B15,All!$B$4:$S$8977,2,FALSE) -> សន | D15: =VLOOKUP(B15,All!$B$4:$S$89977,3,FALSE) -> ស៊ីណាត | E15: =VLOOKUP(B15,All!$B$4:$S$8977,4,FALSE) -> SORN | F15: =VLOOKUP(B15,All!$B$4:$S$8977,5,FALSE) -> SINAT | G15: =VLOOKUP(B15,All!$B$4:$S$8977,6,FALSE) -> F | H15: =VLOOKUP(B15,All!$B$4:$S$8977,7,FALSE) -> 31659 | I15: =VLOOKUP(B15,All!$B$4:$S$8977,8,FALSE) -> 42565 | J15: Production | K15: Line 9 | L15: Leader Line 9 | M15: =VLOOKUP(B15,All!$B$4:$S$8977,12,FALSE) -> 192 | N15: =VLOOKUP(B15,All!$B$4:$S$8977,13,FALSE) -> 6 | O15: =VLOOKUP(B15,All!$B$4:$S$8977,14,FALSE) -> 20 | P15: =VLOOKUP(B15,All!$B$4:$S$8977,15,FALSE) -> 45 | Q15: =VLOOKUP(B15,All!$B$4:$S$8977,16,FALSE) -> 0 | R15: 7 | S15: 10 | T15: =SUM(M15:S15) -> 280 | U15: 15 | V15: 44562 | W15: Jerry | Y15: 組長 | Z15: =M15+2 -> 194 | AA15: =N15 -> 6 | AB15: =O15 -> 20 | AC15: =P15+U15 -> 60 | AD15: =Q15 -> 0 | AE15: =R15 -> 7 | AF15: =S15 -> 10 | AG15: =SUM(Z15:AF15) -> 297 | AH15: =Z15-M15 -> 2 | AI15: =AA15-N15 -> 0 | AJ15: =AB15-O15 -> 0 | AK15: =AC15-P15 -> 15 | AL15: =AD15-Q15 -> 0 | AM15: =AE15-R15 -> 0 | AN15: =AF15-S15 -> 0 | AO15: =AG15-T15 -> 17
A16: =1+A15 -> 12 | B16: 909 | C16: =VLOOKUP(B16,All!$B$4:$S$8977,2,FALSE) -> ភឹម | D16: =VLOOKUP(B16,All!$B$4:$S$89977,3,FALSE) -> ឡាន | E16: =VLOOKUP(B16,All!$B$4:$S$8977,4,FALSE) -> PHOEM | F16: =VLOOKUP(B16,All!$B$4:$S$8977,5,FALSE) -> LAN | G16: =VLOOKUP(B16,All!$B$4:$S$8977,6,FALSE) -> F | H16: =VLOOKUP(B16,All!$B$4:$S$8977,7,FALSE) -> 31851 | I16: =VLOOKUP(B16,All!$B$4:$S$8977,8,FALSE) -> 42122 | J16: Production | K16: Line 10 | L16: Leader Line 10 | M16: =VLOOKUP(B16,All!$B$4:$S$8977,12,FALSE) -> 192 | N16: =VLOOKUP(B16,All!$B$4:$S$8977,13,FALSE) -> 7 | O16: =VLOOKUP(B16,All!$B$4:$S$8977,14,FALSE) -> 20 | P16: =VLOOKUP(B16,All!$B$4:$S$8977,15,FALSE) -> 30 | Q16: =VLOOKUP(B16,All!$B$4:$S$8977,16,FALSE) -> 0 | R16: 7 | S16: 10 | T16: =SUM(M16:S16) -> 266 | U16: 15 | V16: 44562 | W16: Jerry | Y16: 組長 | Z16: =M16+2 -> 194 | AA16: =N16 -> 7 | AB16: =O16 -> 20 | AC16: =P16+U16 -> 45 | AD16: =Q16 -> 0 | AE16: =R16 -> 7 | AF16: =S16 -> 10 | AG16: =SUM(Z16:AF16) -> 283 | AH16: =Z16-M16 -> 2 | AI16: =AA16-N16 -> 0 | AJ16: =AB16-O16 -> 0 | AK16: =AC16-P16 -> 15 | AL16: =AD16-Q16 -> 0 | AM16: =AE16-R16 -> 0 | AN16: =AF16-S16 -> 0 | AO16: =AG16-T16 -> 17
A17: =1+A16 -> 13 | B17: 762 | C17: =VLOOKUP(B17,All!$B$4:$S$8977,2,FALSE) -> ម៉ី | D17: =VLOOKUP(B17,All!$B$4:$S$89977,3,FALSE) -> លក្ខិណា | E17: =VLOOKUP(B17,All!$B$4:$S$8977,4,FALSE) -> MEY | F17: =VLOOKUP(B17,All!$B$4:$S$8977,5,FALSE) -> LEAKHENA | G17: =VLOOKUP(B17,All!$B$4:$S$8977,6,FALSE) -> F | H17: =VLOOKUP(B17,All!$B$4:$S$8977,7,FALSE) -> 30440 | I17: =VLOOKUP(B17,All!$B$4:$S$8977,8,FALSE) -> 41981 | J17: Production | K17: Line 11 | L17: Leader Line 11 | M17: =VLOOKUP(B17,All!$B$4:$S$8977,12,FALSE) -> 192 | N17: =VLOOKUP(B17,All!$B$4:$S$8977,13,FALSE) -> 8 | O17: =VLOOKUP(B17,All!$B$4:$S$8977,14,FALSE) -> 20 | P17: =VLOOKUP(B17,All!$B$4:$S$8977,15,FALSE) -> 35 | Q17: =VLOOKUP(B17,All!$B$4:$S$8977,16,FALSE) -> 0 | R17: 7 | S17: 10 | T17: =SUM(M17:S17) -> 272 | U17: 15 | V17: 44562 | W17: Jerry | Y17: 組長 | Z17: =M17+2 -> 194 | AA17: =N17 -> 8 | AB17: =O17 -> 20 | AC17: =P17+U17 -> 50 | AD17: =Q17 -> 0 | AE17: =R17 -> 7 | AF17: =S17 -> 10 | AG17: =SUM(Z17:AF17) -> 289 | AH17: =Z17-M17 -> 2 | AI17: =AA17-N17 -> 0 | AJ17: =AB17-O17 -> 0 | AK17: =AC17-P17 -> 15 | AL17: =AD17-Q17 -> 0 | AM17: =AE17-R17 -> 0 | AN17: =AF17-S17 -> 0 | AO17: =AG17-T17 -> 17
A18: =1+A17 -> 14 | B18: 3359 | C18: =VLOOKUP(B18,All!$B$4:$S$8977,2,FALSE) -> ឈឹម | D18: =VLOOKUP(B18,All!$B$4:$S$89977,3,FALSE) -> ដានី | E18: =VLOOKUP(B18,All!$B$4:$S$8977,4,FALSE) -> CHHOEM | F18: =VLOOKUP(B18,All!$B$4:$S$8977,5,FALSE) -> DANY | G18: =VLOOKUP(B18,All!$B$4:$S$8977,6,FALSE) -> F | H18: =VLOOKUP(B18,All!$B$4:$S$8977,7,FALSE) -> 34182 | I18: =VLOOKUP(B18,All!$B$4:$S$8977,8,FALSE) -> 43755 | J18: Production | K18: Line 15 | L18: Leader Line 15 | M18: =VLOOKUP(B18,All!$B$4:$S$8977,12,FALSE) -> 192 | N18: =VLOOKUP(B18,All!$B$4:$S$8977,13,FALSE) -> 3 | O18: =VLOOKUP(B18,All!$B$4:$S$8977,14,FALSE) -> 0 | P18: =VLOOKUP(B18,All!$B$4:$S$8977,15,FALSE) -> 30 | Q18: =VLOOKUP(B18,All!$B$4:$S$8977,16,FALSE) -> 0 | R18: 7 | S18: 10 | T18: =SUM(M18:S18) -> 242 | U18: 15 | V18: 44562 | W18: Jerry | Y18: 組長 | Z18: =M18+2 -> 194 | AA18: =N18 -> 3 | AB18: =O18 -> 0 | AC18: =P18+U18 -> 45 | AD18: =Q18 -> 0 | AE18: =R18 -> 7 | AF18: =S18 -> 10 | AG18: =SUM(Z18:AF18) -> 259 | AH18: =Z18-M18 -> 2 | AI18: =AA18-N18 -> 0 | AJ18: =AB18-O18 -> 0 | AK18: =AC18-P18 -> 15 | AL18: =AD18-Q18 -> 0 | AM18: =AE18-R18 -> 0 | AN18: =AF18-S18 -> 0 | AO18: =AG18-T18 -> 17
A19: =1+A18 -> 15 | B19: 5013 | C19: =VLOOKUP(B19,All!$B$4:$S$8977,2,FALSE) -> អោក | D19: =VLOOKUP(B19,All!$B$4:$S$89977,3,FALSE) -> ឈុនអេង | E19: =VLOOKUP(B19,All!$B$4:$S$8977,4,FALSE) -> OAK | F19: =VLOOKUP(B19,All!$B$4:$S$8977,5,FALSE) -> CHHUN ENG | G19: =VLOOKUP(B19,All!$B$4:$S$8977,6,FALSE) -> F | H19: =VLOOKUP(B19,All!$B$4:$S$8977,7,FALSE) -> 30212 | I19: =VLOOKUP(B19,All!$B$4:$S$8977,8,FALSE) -> 44140 | J19: Production | K19: Line12 | L19: Leader Line 12 | M19: =VLOOKUP(B19,All!$B$4:$S$8977,12,FALSE) -> 192 | N19: =VLOOKUP(B19,All!$B$4:$S$8977,13,FALSE) -> 2 | O19: =VLOOKUP(B19,All!$B$4:$S$8977,14,FALSE) -> 0 | P19: =VLOOKUP(B19,All!$B$4:$S$8977,15,FALSE) -> 30 | Q19: =VLOOKUP(B19,All!$B$4:$S$8977,16,FALSE) -> 0 | R19: 7 | S19: 10 | T19: =SUM(M19:S19) -> 241 | U19: 15 | V19: 44562 | W19: Jerry | Y19: 組長 | Z19: =M19+2 -> 194 | AA19: =N19 -> 2 | AB19: =O19 -> 0 | AC19: =P19+U19 -> 45 | AD19: =Q19 -> 0 | AE19: =R19 -> 7 | AF19: =S19 -> 10 | AG19: =SUM(Z19:AF19) -> 258 | AH19: =Z19-M19 -> 2 | AI19: =AA19-N19 -> 0 | AJ19: =AB19-O19 -> 0 | AK19: =AC19-P19 -> 15 | AL19: =AD19-Q19 -> 0 | AM19: =AE19-R19 -> 0 | AN19: =AF19-S19 -> 0 | AO19: =AG19-T19 -> 17
A20: =1+A19 -> 16 | B20: 74 | C20: =VLOOKUP(B20,All!$B$4:$S$8977,2,FALSE) -> ពេជ | D20: =VLOOKUP(B20,All!$B$4:$S$89977,3,FALSE) -> សោភា | E20: =VLOOKUP(B20,All!$B$4:$S$8977,4,FALSE) -> Pich | F20: =VLOOKUP(B20,All!$B$4:$S$8977,5,FALSE) -> Sophea | G20: =VLOOKUP(B20,All!$B$4:$S$8977,6,FALSE) -> F | H20: =VLOOKUP(B20,All!$B$4:$S$8977,7,FALSE) -> 29108 | I20: =VLOOKUP(B20,All!$B$4:$S$8977,8,FALSE) -> 41598 | J20: Production | K20: Line 17 | L20: Leader Line 17 | M20: =VLOOKUP(B20,All!$B$4:$S$8977,12,FALSE) -> 192 | N20: =VLOOKUP(B20,All!$B$4:$S$8977,13,FALSE) -> 9 | O20: =VLOOKUP(B20,All!$B$4:$S$8977,14,FALSE) -> 20 | P20: =VLOOKUP(B20,All!$B$4:$S$8977,15,FALSE) -> 47 | Q20: =VLOOKUP(B20,All!$B$4:$S$8977,16,FALSE) -> 15 | R20: 7 | S20: 10 | T20: =SUM(M20:S20) -> 300 | U20: 15 | V20: 44562 | W20: Jerry | Y20: 組長 | Z20: =M20+2 -> 194 | AA20: =N20 -> 9 | AB20: =O20 -> 20 | AC20: =P20+U20 -> 62 | AD20: =Q20 -> 15 | AE20: =R20 -> 7 | AF20: =S20 -> 10 | AG20: =SUM(Z20:AF20) -> 317 | AH20: =Z20-M20 -> 2 | AI20: =AA20-N20 -> 0 | AJ20: =AB20-O20 -> 0 | AK20: =AC20-P20 -> 15 | AL20: =AD20-Q20 -> 0 | AM20: =AE20-R20 -> 0 | AN20: =AF20-S20 -> 0 | AO20: =AG20-T20 -> 17
... A41: =1+A40 -> 37 | B41: 603 | C41: =VLOOKUP(B41,All!$B$4:$S$8977,2,FALSE) -> ខេង | D41: =VLOOKUP(B41,All!$B$4:$S$89977,3,FALSE) -> មួយគៀង | E41: =VLOOKUP(B41,All!$B$4:$S$8977,4,FALSE) -> KHENG | F41: =VLOOKUP(B41,All!$B$4:$S$8977,5,FALSE) -> MOUY KEAN | G41: =VLOOKUP(B41,All!$B$4:$S$8977,6,FALSE) -> F | H41: =VLOOKUP(B41,All!$B$4:$S$8977,7,FALSE) -> 35349 | I41: =VLOOKUP(B41,All!$B$4:$S$8977,8,FALSE) -> 41837 | J41: Production | K41: Line3 | L41: Assist.Line 3 | M41: =VLOOKUP(B41,All!$B$4:$S$8977,12,FALSE) -> 192 | N41: =VLOOKUP(B41,All!$B$4:$S$8977,13,FALSE) -> 8 | O41: =VLOOKUP(B41,All!$B$4:$S$8977,14,FALSE) -> 20 | P41: =VLOOKUP(B41,All!$B$4:$S$8977,15,FALSE) -> 10 | Q41: =VLOOKUP(B41,All!$B$4:$S$8977,16,FALSE) -> 0 | R41: 7 | S41: 10 | T41: =SUM(M41:S41) -> 247 | U41: 5 | V41: 44562 | W41: Jerry | Y41: 助理 | Z41: =M41+2 -> 194 | AA41: =N41 -> 8 | AB41: =O41 -> 20 | AC41: =P41+U41 -> 15 | AD41: =Q41 -> 0 | AE41: =R41 -> 7 | AF41: =S41 -> 10 | AG41: =SUM(Z41:AF41) -> 254 | AH41: =Z41-M41 -> 2 | AI41: =AA41-N41 -> 0 | AJ41: =AB41-O41 -> 0 | AK41: =AC41-P41 -> 5 | AL41: =AD41-Q41 -> 0 | AM41: =AE41-R41 -> 0 | AN41: =AF41-S41 -> 0 | AO41: =AG41-T41 -> 7
A42: =1+A41 -> 38 | B42: 5008 | C42: =VLOOKUP(B42,All!$B$4:$S$8977,2,FALSE) -> រាំង | D42: =VLOOKUP(B42,All!$B$4:$S$89977,3,FALSE) -> ទៀន | E42: =VLOOKUP(B42,All!$B$4:$S$8977,4,FALSE) -> RANG | F42: =VLOOKUP(B42,All!$B$4:$S$8977,5,FALSE) -> TIEN | G42: =VLOOKUP(B42,All!$B$4:$S$8977,6,FALSE) -> F | H42: =VLOOKUP(B42,All!$B$4:$S$8977,7,FALSE) -> 34852 | I42: =VLOOKUP(B42,All!$B$4:$S$8977,8,FALSE) -> 44139 | J42: Production | K42: Line 5 | L42: Assist.Line 5 | M42: =VLOOKUP(B42,All!$B$4:$S$8977,12,FALSE) -> 192 | N42: 0 | O42: =VLOOKUP(B42,All!$B$4:$S$8977,14,FALSE) -> 0 | P42: =VLOOKUP(B42,All!$B$4:$S$8977,15,FALSE) -> 10 | Q42: =VLOOKUP(B42,All!$B$4:$S$8977,16,FALSE) -> 0 | R42: 7 | S42: 10 | T42: =SUM(M42:S42) -> 219 | U42: 5 | V42: 44562 | W42: Jerry | Y42: 助理 | Z42: =M42+2 -> 194 | AA42: =N42 -> 0 | AB42: =O42 -> 0 | AC42: =P42+U42 -> 15 | AD42: =Q42 -> 0 | AE42: =R42 -> 7 | AF42: =S42 -> 10 | AG42: =SUM(Z42:AF42) -> 226 | AH42: =Z42-M42 -> 2 | AI42: =AA42-N42 -> 0 | AJ42: =AB42-O42 -> 0 | AK42: =AC42-P42 -> 5 | AL42: =AD42-Q42 -> 0 | AM42: =AE42-R42 -> 0 | AN42: =AF42-S42 -> 0 | AO42: =AG42-T42 -> 7
A43: =1+A42 -> 39 | B43: 3964 | C43: =VLOOKUP(B43,All!$B$4:$S$8977,2,FALSE) -> ហ៊ិន | D43: =VLOOKUP(B43,All!$B$4:$S$89977,3,FALSE) -> រិទ្ធ | E43: =VLOOKUP(B43,All!$B$4:$S$8977,4,FALSE) -> HIN | F43: =VLOOKUP(B43,All!$B$4:$S$8977,5,FALSE) -> RITH | G43: =VLOOKUP(B43,All!$B$4:$S$8977,6,FALSE) -> F | H43: =VLOOKUP(B43,All!$B$4:$S$8977,7,FALSE) -> 34091 | I43: =VLOOKUP(B43,All!$B$4:$S$8977,8,FALSE) -> 43821 | J43: Production | K43: Line 6 | L43: Assist.Line 6 | M43: =VLOOKUP(B43,All!$B$4:$S$8977,12,FALSE) -> 192 | N43: =VLOOKUP(B43,All!$B$4:$S$8977,13,FALSE) -> 3 | O43: =VLOOKUP(B43,All!$B$4:$S$8977,14,FALSE) -> 0 | P43: =VLOOKUP(B43,All!$B$4:$S$8977,15,FALSE) -> 10 | Q43: =VLOOKUP(B43,All!$B$4:$S$8977,16,FALSE) -> 0 | R43: 7 | S43: 10 | T43: =SUM(M43:S43) -> 222 | U43: 5 | V43: 44562 | W43: Jerry | Y43: 助理 | Z43: =M43+2 -> 194 | AA43: =N43 -> 3 | AB43: =O43 -> 0 | AC43: =P43+U43 -> 15 | AD43: =Q43 -> 0 | AE43: =R43 -> 7 | AF43: =S43 -> 10 | AG43: =SUM(Z43:AF43) -> 229 | AH43: =Z43-M43 -> 2 | AI43: =AA43-N43 -> 0 | AJ43: =AB43-O43 -> 0 | AK43: =AC43-P43 -> 5 | AL43: =AD43-Q43 -> 0 | AM43: =AE43-R43 -> 0 | AN43: =AF43-S43 -> 0 | AO43: =AG43-T43 -> 7
A44: =1+A43 -> 40 | B44: 2940 | C44: =VLOOKUP(B44,All!$B$4:$S$8977,2,FALSE) -> ទ្រី | D44: =VLOOKUP(B44,All!$B$4:$S$89977,3,FALSE) -> ស៊ាកម៉េង | E44: =VLOOKUP(B44,All!$B$4:$S$8977,4,FALSE) -> Try | F44: =VLOOKUP(B44,All!$B$4:$S$8977,5,FALSE) -> SeakMeng | G44: =VLOOKUP(B44,All!$B$4:$S$8977,6,FALSE) -> F | H44: =VLOOKUP(B44,All!$B$4:$S$8977,7,FALSE) -> 35251 | I44: =VLOOKUP(B44,All!$B$4:$S$8977,8,FALSE) -> 43596 | J44: Production | K44: Line 8 | L44: Assist.Line 8 | M44: =VLOOKUP(B44,All!$B$4:$S$8977,12,FALSE) -> 192 | N44: =VLOOKUP(B44,All!$B$4:$S$8977,13,FALSE) -> 3 | O44: =VLOOKUP(B44,All!$B$4:$S$8977,14,FALSE) -> 0 | P44: =VLOOKUP(B44,All!$B$4:$S$8977,15,FALSE) -> 10 | Q44: =VLOOKUP(B44,All!$B$4:$S$8977,16,FALSE) -> 0 | R44: 7 | S44: 10 | T44: =SUM(M44:S44) -> 222 | U44: 5 | V44: 44562 | W44: Jerry | Y44: 助理 | Z44: =M44+2 -> 194 | AA44: =N44 -> 3 | AB44: =O44 -> 0 | AC44: =P44+U44 -> 15 | AD44: =Q44 -> 0 | AE44: =R44 -> 7 | AF44: =S44 -> 10 | AG44: =SUM(Z44:AF44) -> 229 | AH44: =Z44-M44 -> 2 | AI44: =AA44-N44 -> 0 | AJ44: =AB44-O44 -> 0 | AK44: =AC44-P44 -> 5 | AL44: =AD44-Q44 -> 0 | AM44: =AE44-R44 -> 0 | AN44: =AF44-S44 -> 0 | AO44: =AG44-T44 -> 7
A45: =1+A44 -> 41 | B45: 2043 | C45: =VLOOKUP(B45,All!$B$4:$S$8977,2,FALSE) -> ចុង | D45: =VLOOKUP(B45,All!$B$4:$S$89977,3,FALSE) -> សុខជា | E45: =VLOOKUP(B45,All!$B$4:$S$8977,4,FALSE) -> CHONG | F45: =VLOOKUP(B45,All!$B$4:$S$8977,5,FALSE) -> SOCHEA | G45: =VLOOKUP(B45,All!$B$4:$S$8977,6,FALSE) -> F | H45: =VLOOKUP(B45,All!$B$4:$S$8977,7,FALSE) -> 34037 | I45: =VLOOKUP(B45,All!$B$4:$S$8977,8,FALSE) -> 42920 | J45: Production | K45: Line 9 | L45: Assist.Line 9 | M45: =VLOOKUP(B45,All!$B$4:$S$8977,12,FALSE) -> 192 | N45: =VLOOKUP(B45,All!$B$4:$S$8977,13,FALSE) -> 5 | O45: =VLOOKUP(B45,All!$B$4:$S$8977,14,FALSE) -> 20 | P45: =VLOOKUP(B45,All!$B$4:$S$8977,15,FALSE) -> 10 | Q45: =VLOOKUP(B45,All!$B$4:$S$8977,16,FALSE) -> 0 | R45: 7 | S45: 10 | T45: =SUM(M45:S45) -> 244 | U45: 5 | V45: 44562 | W45: Jerry | Y45: 助理 | Z45: =M45+2 -> 194 | AA45: =N45 -> 5 | AB45: =O45 -> 20 | AC45: =P45+U45 -> 15 | AD45: =Q45 -> 0 | AE45: =R45 -> 7 | AF45: =S45 -> 10 | AG45: =SUM(Z45:AF45) -> 251 | AH45: =Z45-M45 -> 2 | AI45: =AA45-N45 -> 0 | AJ45: =AB45-O45 -> 0 | AK45: =AC45-P45 -> 5 | AL45: =AD45-Q45 -> 0 | AM45: =AE45-R45 -> 0 | AN45: =AF45-S45 -> 0 | AO45: =AG45-T45 -> 7
A46: =1+A45 -> 42 | B46: 3263 | C46: =VLOOKUP(B46,All!$B$4:$S$8977,2,FALSE) -> ឃូ | D46: =VLOOKUP(B46,All!$B$4:$S$89977,3,FALSE) -> ចន្ទ័តុលា | E46: =VLOOKUP(B46,All!$B$4:$S$8977,4,FALSE) -> KHOU | F46: =VLOOKUP(B46,All!$B$4:$S$8977,5,FALSE) -> CHANTOLA | G46: =VLOOKUP(B46,All!$B$4:$S$8977,6,FALSE) -> F | H46: =VLOOKUP(B46,All!$B$4:$S$8977,7,FALSE) -> 32800 | I46: =VLOOKUP(B46,All!$B$4:$S$8977,8,FALSE) -> 43746 | J46: Production | K46: Line 11 | L46: Assist.Line 11 | M46: =VLOOKUP(B46,All!$B$4:$S$8977,12,FALSE) -> 192 | N46: =VLOOKUP(B46,All!$B$4:$S$8977,13,FALSE) -> 3 | O46: =VLOOKUP(B46,All!$B$4:$S$8977,14,FALSE) -> 0 | P46: =VLOOKUP(B46,All!$B$4:$S$8977,15,FALSE) -> 10 | Q46: =VLOOKUP(B46,All!$B$4:$S$8977,16,FALSE) -> 0 | R46: 7 | S46: 10 | T46: =SUM(M46:S46) -> 222 | U46: 5 | V46: 44562 | W46: Jerry | Y46: 助理 | Z46: =M46+2 -> 194 | AA46: =N46 -> 3 | AB46: =O46 -> 0 | AC46: =P46+U46 -> 15 | AD46: =Q46 -> 0 | AE46: =R46 -> 7 | AF46: =S46 -> 10 | AG46: =SUM(Z46:AF46) -> 229 | AH46: =Z46-M46 -> 2 | AI46: =AA46-N46 -> 0 | AJ46: =AB46-O46 -> 0 | AK46: =AC46-P46 -> 5 | AL46: =AD46-Q46 -> 0 | AM46: =AE46-R46 -> 0 | AN46: =AF46-S46 -> 0 | AO46: =AG46-T46 -> 7
A47: =1+A46 -> 43 | B47: 3486 | C47: =VLOOKUP(B47,All!$B$4:$S$8977,2,FALSE) -> សេក | D47: =VLOOKUP(B47,All!$B$4:$S$89977,3,FALSE) -> សំភ័ស្ស | E47: =VLOOKUP(B47,All!$B$4:$S$8977,4,FALSE) -> SEK | F47: =VLOOKUP(B47,All!$B$4:$S$8977,5,FALSE) -> SAMPHOIS | G47: =VLOOKUP(B47,All!$B$4:$S$8977,6,FALSE) -> F | H47: =VLOOKUP(B47,All!$B$4:$S$8977,7,FALSE) -> 35662 | I47: =VLOOKUP(B47,All!$B$4:$S$8977,8,FALSE) -> 43786 | J47: Production | K47: Line 17 | L47: Assist.Line 17 | M47: =VLOOKUP(B47,All!$B$4:$S$8977,12,FALSE) -> 192 | N47: =VLOOKUP(B47,All!$B$4:$S$8977,13,FALSE) -> 3 | O47: =VLOOKUP(B47,All!$B$4:$S$8977,14,FALSE) -> 0 | P47: =VLOOKUP(B47,All!$B$4:$S$8977,15,FALSE) -> 10 | Q47: =VLOOKUP(B47,All!$B$4:$S$8977,16,FALSE) -> 0 | R47: 7 | S47: 10 | T47: =SUM(M47:S47) -> 222 | U47: 5 | V47: 44562 | W47: Jerry | Y47: 助理 | Z47: =M47+2 -> 194 | AA47: =N47 -> 3 | AB47: =O47 -> 0 | AC47: =P47+U47 -> 15 | AD47: =Q47 -> 0 | AE47: =R47 -> 7 | AF47: =S47 -> 10 | AG47: =SUM(Z47:AF47) -> 229 | AH47: =Z47-M47 -> 2 | AI47: =AA47-N47 -> 0 | AJ47: =AB47-O47 -> 0 | AK47: =AC47-P47 -> 5 | AL47: =AD47-Q47 -> 0 | AM47: =AE47-R47 -> 0 | AN47: =AF47-S47 -> 0 | AO47: =AG47-T47 -> 7
A48: =1+A47 -> 44 | B48: 1711 | C48: =VLOOKUP(B48,All!$B$4:$S$8977,2,FALSE) -> អ៊ុង | D48: =VLOOKUP(B48,All!$B$4:$S$89977,3,FALSE) -> ភេទ | E48: =VLOOKUP(B48,All!$B$4:$S$8977,4,FALSE) -> UNG | F48: =VLOOKUP(B48,All!$B$4:$S$8977,5,FALSE) -> PHET | G48: =VLOOKUP(B48,All!$B$4:$S$8977,6,FALSE) -> F | H48: =VLOOKUP(B48,All!$B$4:$S$8977,7,FALSE) -> 31446 | I48: =VLOOKUP(B48,All!$B$4:$S$8977,8,FALSE) -> 42665 | J48: Production | K48: Line 18 | L48: Assist.Line 18 | M48: =VLOOKUP(B48,All!$B$4:$S$8977,12,FALSE) -> 192 | N48: =VLOOKUP(B48,All!$B$4:$S$8977,13,FALSE) -> 6 | O48: =VLOOKUP(B48,All!$B$4:$S$8977,14,FALSE) -> 20 | P48: =VLOOKUP(B48,All!$B$4:$S$8977,15,FALSE) -> 15 | Q48: =VLOOKUP(B48,All!$B$4:$S$8977,16,FALSE) -> 0 | R48: 7 | S48: 10 | T48: =SUM(M48:S48) -> 250 | U48: 5 | V48: 44562 | W48: Jerry | Y48: 助理 | Z48: =M48+2 -> 194 | AA48: =N48 -> 6 | AB48: =O48 -> 20 | AC48: =P48+U48 -> 20 | AD48: =Q48 -> 0 | AE48: =R48 -> 7 | AF48: =S48 -> 10 | AG48: =SUM(Z48:AF48) -> 257 | AH48: =Z48-M48 -> 2 | AI48: =AA48-N48 -> 0 | AJ48: =AB48-O48 -> 0 | AK48: =AC48-P48 -> 5 | AL48: =AD48-Q48 -> 0 | AM48: =AE48-R48 -> 0 | AN48: =AF48-S48 -> 0 | AO48: =AG48-T48 -> 7
A49: =1+A48 -> 45 | B49: 44 | C49: =VLOOKUP(B49,All!$B$4:$S$8977,2,FALSE) -> ប៊ុន | D49: =VLOOKUP(B49,All!$B$4:$S$89977,3,FALSE) -> គឹមសែ | E49: =VLOOKUP(B49,All!$B$4:$S$8977,4,FALSE) -> Bun | F49: =VLOOKUP(B49,All!$B$4:$S$8977,5,FALSE) -> Kimse | G49: =VLOOKUP(B49,All!$B$4:$S$8977,6,FALSE) -> F | H49: =VLOOKUP(B49,All!$B$4:$S$8977,7,FALSE) -> 31836 | I49: =VLOOKUP(B49,All!$B$4:$S$8977,8,FALSE) -> 41579 | J49: Production | K49: Line19 | L49: Assist.Line 19 | M49: =VLOOKUP(B49,All!$B$4:$S$8977,12,FALSE) -> 192 | N49: =VLOOKUP(B49,All!$B$4:$S$8977,13,FALSE) -> 9 | O49: =VLOOKUP(B49,All!$B$4:$S$8977,14,FALSE) -> 20 | P49: =VLOOKUP(B49,All!$B$4:$S$8977,15,FALSE) -> 30 | Q49: =VLOOKUP(B49,All!$B$4:$S$8977,16,FALSE) -> 10 | R49: 7 | S49: 10 | T49: =SUM(M49:S49) -> 278 | U49: 5 | V49: 44562 | W49: Jerry | Y49: 助理 | Z49: =M49+2 -> 194 | AA49: =N49 -> 9 | AB49: =O49 -> 20 | AC49: =P49+U49 -> 35 | AD49: =Q49 -> 10 | AE49: =R49 -> 7 | AF49: =S49 -> 10 | AG49: =SUM(Z49:AF49) -> 285 | AH49: =Z49-M49 -> 2 | AI49: =AA49-N49 -> 0 | AJ49: =AB49-O49 -> 0 | AK49: =AC49-P49 -> 5 | AL49: =AD49-Q49 -> 0 | AM49: =AE49-R49 -> 0 | AN49: =AF49-S49 -> 0 | AO49: =AG49-T49 -> 7
A50: =1+A49 -> 46 | B50: 1727 | C50: =VLOOKUP(B50,All!$B$4:$S$8977,2,FALSE) -> សុន | D50: =VLOOKUP(B50,All!$B$4:$S$89977,3,FALSE) -> រដ្ឋា | E50: =VLOOKUP(B50,All!$B$4:$S$8977,4,FALSE) -> SUN | F50: =VLOOKUP(B50,All!$B$4:$S$8977,5,FALSE) -> RATHA | G50: =VLOOKUP(B50,All!$B$4:$S$8977,6,FALSE) -> F | H50: =VLOOKUP(B50,All!$B$4:$S$8977,7,FALSE) -> 32694 | I50: =VLOOKUP(B50,All!$B$4:$S$8977,8,FALSE) -> 42676 | J50: Production | K50: Line 20 | L50: Assist.Line 20 | M50: =VLOOKUP(B50,All!$B$4:$S$8977,12,FALSE) -> 192 | N50: =VLOOKUP(B50,All!$B$4:$S$8977,13,FALSE) -> 6 | O50: =VLOOKUP(B50,All!$B$4:$S$8977,14,FALSE) -> 20 | P50: =VLOOKUP(B50,All!$B$4:$S$8977,15,FALSE) -> 10 | Q50: =VLOOKUP(B50,All!$B$4:$S$8977,16,FALSE) -> 0 | R50: 7 | S50: 10 | T50: =SUM(M50:S50) -> 245 | U50: 5 | V50: 44562 | W50: Jerry | Y50: 助理 | Z50: =M50+2 -> 194 | AA50: =N50 -> 6 | AB50: =O50 -> 20 | AC50: =P50+U50 -> 15 | AD50: =Q50 -> 0 | AE50: =R50 -> 7 | AF50: =S50 -> 10 | AG50: =SUM(Z50:AF50) -> 252 | AH50: =Z50-M50 -> 2 | AI50: =AA50-N50 -> 0 | AJ50: =AB50-O50 -> 0 | AK50: =AC50-P50 -> 5 | AL50: =AD50-Q50 -> 0 | AM50: =AE50-R50 -> 0 | AN50: =AF50-S50 -> 0 | AO50: =AG50-T50 -> 7
A51: =1+A50 -> 47 | B51: 2403 | C51: =VLOOKUP(B51,All!$B$4:$S$8977,2,FALSE) -> ផាន | D51: =VLOOKUP(B51,All!$B$4:$S$89977,3,FALSE) -> សុខឡាយ | E51: =VLOOKUP(B51,All!$B$4:$S$8977,4,FALSE) -> PHAN | F51: =VLOOKUP(B51,All!$B$4:$S$8977,5,FALSE) -> SOKLAIY | G51: =VLOOKUP(B51,All!$B$4:$S$8977,6,FALSE) -> F | H51: =VLOOKUP(B51,All!$B$4:$S$8977,7,FALSE) -> 35098 | I51: =VLOOKUP(B51,All!$B$4:$S$8977,8,FALSE) -> 43166 | J51: Production | K51: Line 21 | L51: Assist.Line 21 | M51: =VLOOKUP(B51,All!$B$4:$S$8977,12,FALSE) -> 192 | N51: =VLOOKUP(B51,All!$B$4:$S$8977,13,FALSE) -> 4 | O51: =VLOOKUP(B51,All!$B$4:$S$8977,14,FALSE) -> 20 | P51: =VLOOKUP(B51,All!$B$4:$S$8977,15,FALSE) -> 10 | Q51: =VLOOKUP(B51,All!$B$4:$S$8977,16,FALSE) -> 0 | R51: 7 | S51: 10 | T51: =SUM(M51:S51) -> 243 | U51: 5 | V51: 44562 | W51: Jerry | Y51: 助理 | Z51: =M51+2 -> 194 | AA51: =N51 -> 4 | AB51: =O51 -> 20 | AC51: =P51+U51 -> 15 | AD51: =Q51 -> 0 | AE51: =R51 -> 7 | AF51: =S51 -> 10 | AG51: =SUM(Z51:AF51) -> 250 | AH51: =Z51-M51 -> 2 | AI51: =AA51-N51 -> 0 | AJ51: =AB51-O51 -> 0 | AK51: =AC51-P51 -> 5 | AL51: =AD51-Q51 -> 0 | AM51: =AE51-R51 -> 0 | AN51: =AF51-S51 -> 0 | AO51: =AG51-T51 -> 7
A52: =1+A51 -> 48 | B52: 4117 | C52: =VLOOKUP(B52,All!$B$4:$S$8977,2,FALSE) -> អ៊ាប | D52: =VLOOKUP(B52,All!$B$4:$S$89977,3,FALSE) -> សុភ័ស | E52: =VLOOKUP(B52,All!$B$4:$S$8977,4,FALSE) -> EAP | F52: =VLOOKUP(B52,All!$B$4:$S$8977,5,FALSE) -> SOPHAS | G52: =VLOOKUP(B52,All!$B$4:$S$8977,6,FALSE) -> F | H52: =VLOOKUP(B52,All!$B$4:$S$8977,7,FALSE) -> 36649 | I52: =VLOOKUP(B52,All!$B$4:$S$8977,8,FALSE) -> 43802 | J52: Production | K52: Sample | L52: Assist.Sample | M52: =VLOOKUP(B52,All!$B$4:$S$8977,12,FALSE) -> 192 | N52: =VLOOKUP(B52,All!$B$4:$S$8977,13,FALSE) -> 3 | O52: =VLOOKUP(B52,All!$B$4:$S$8977,14,FALSE) -> 0 | P52: =VLOOKUP(B52,All!$B$4:$S$8977,15,FALSE) -> 10 | Q52: =VLOOKUP(B52,All!$B$4:$S$8977,16,FALSE) -> 0 | R52: 7 | S52: 10 | T52: =SUM(M52:S52) -> 222 | U52: 5 | V52: 44562 | W52: Jerry | Y52: 樣品助理 | Z52: =M52+2 -> 194 | AA52: =N52 -> 3 | AB52: =O52 -> 0 | AC52: =P52+U52 -> 15 | AD52: =Q52 -> 0 | AE52: =R52 -> 7 | AF52: =S52 -> 10 | AG52: =SUM(Z52:AF52) -> 229 | AH52: =Z52-M52 -> 2 | AI52: =AA52-N52 -> 0 | AJ52: =AB52-O52 -> 0 | AK52: =AC52-P52 -> 5 | AL52: =AD52-Q52 -> 0 | AM52: =AE52-R52 -> 0 | AN52: =AF52-S52 -> 0 | AO52: =AG52-T52 -> 7
A53: =1+A52 -> 49 | B53: 404 | C53: =VLOOKUP(B53,All!$B$4:$S$8977,2,FALSE) -> គង់ | D53: =VLOOKUP(B53,All!$B$4:$S$89977,3,FALSE) -> ស្រស់ | E53: =VLOOKUP(B53,All!$B$4:$S$8977,4,FALSE) -> KONG | F53: =VLOOKUP(B53,All!$B$4:$S$8977,5,FALSE) -> SROS | G53: =VLOOKUP(B53,All!$B$4:$S$8977,6,FALSE) -> F | H53: =VLOOKUP(B53,All!$B$4:$S$8977,7,FALSE) -> 34116 | I53: =VLOOKUP(B53,All!$B$4:$S$8977,8,FALSE) -> 41793 | J53: Production | K53: Packing | L53: Assist.Packing | M53: =VLOOKUP(B53,All!$B$4:$S$8977,12,FALSE) -> 192 | N53: =VLOOKUP(B53,All!$B$4:$S$8977,13,FALSE) -> 8 | O53: =VLOOKUP(B53,All!$B$4:$S$8977,14,FALSE) -> 20 | P53: =VLOOKUP(B53,All!$B$4:$S$8977,15,FALSE) -> 10 | Q53: =VLOOKUP(B53,All!$B$4:$S$8977,16,FALSE) -> 0 | R53: 7 | S53: 10 | T53: =SUM(M53:S53) -> 247 | U53: 5 | V53: 44562 | W53: Jerry | Y53: 包裝助理 | Z53: =M53+2 -> 194 | AA53: =N53 -> 8 | AB53: =O53 -> 20 | AC53: =P53+U53 -> 15 | AD53: =Q53 -> 0 | AE53: =R53 -> 7 | AF53: =S53 -> 10 | AG53: =SUM(Z53:AF53) -> 254 | AH53: =Z53-M53 -> 2 | AI53: =AA53-N53 -> 0 | AJ53: =AB53-O53 -> 0 | AK53: =AC53-P53 -> 5 | AL53: =AD53-Q53 -> 0 | AM53: =AE53-R53 -> 0 | AN53: =AF53-S53 -> 0 | AO53: =AG53-T53 -> 7
A54: =1+A53 -> 50 | B54: 1497 | C54: =VLOOKUP(B54,All!$B$4:$S$8977,2,FALSE) -> គង់ | D54: =VLOOKUP(B54,All!$B$4:$S$89977,3,FALSE) -> គា | E54: =VLOOKUP(B54,All!$B$4:$S$8977,4,FALSE) -> KONG | F54: =VLOOKUP(B54,All!$B$4:$S$8977,5,FALSE) -> KEA | G54: =VLOOKUP(B54,All!$B$4:$S$8977,6,FALSE) -> F | H54: =VLOOKUP(B54,All!$B$4:$S$8977,7,FALSE) -> 34920 | I54: =VLOOKUP(B54,All!$B$4:$S$8977,8,FALSE) -> 42445 | J54: Production | K54: QC | L54: Assist.QC B | M54: =VLOOKUP(B54,All!$B$4:$S$8977,12,FALSE) -> 192 | N54: =VLOOKUP(B54,All!$B$4:$S$8977,13,FALSE) -> 6 | O54: =VLOOKUP(B54,All!$B$4:$S$8977,14,FALSE) -> 20 | P54: =VLOOKUP(B54,All!$B$4:$S$8977,15,FALSE) -> 20 | Q54: =VLOOKUP(B54,All!$B$4:$S$8977,16,FALSE) -> 0 | R54: 7 | S54: 10 | T54: =SUM(M54:S54) -> 255 | U54: 5 | V54: 44562 | W54: Jerry | Y54: 品檢助理 | Z54: =M54+2 -> 194 | AA54: =N54 -> 6 | AB54: =O54 -> 20 | AC54: =P54+U54 -> 25 | AD54: =Q54 -> 0 | AE54: =R54 -> 7 | AF54: =S54 -> 10 | AG54: =SUM(Z54:AF54) -> 262 | AH54: =Z54-M54 -> 2 | AI54: =AA54-N54 -> 0 | AJ54: =AB54-O54 -> 0 | AK54: =AC54-P54 -> 5 | AL54: =AD54-Q54 -> 0 | AM54: =AE54-R54 -> 0 | AN54: =AF54-S54 -> 0 | AO54: =AG54-T54 -> 7
A55: =1+A54 -> 51 | B55: 3205 | E55: =VLOOKUP(B55,All!$B$4:$S$8977,4,FALSE) -> SAN | F55: =VLOOKUP(B55,All!$B$4:$S$8977,5,FALSE) -> VEASNA | G55: =VLOOKUP(B55,All!$B$4:$S$8977,6,FALSE) -> M | H55: =VLOOKUP(B55,All!$B$4:$S$8977,7,FALSE) -> 33340 | I55: =VLOOKUP(B55,All!$B$4:$S$8977,8,FALSE) -> 43740 | J55: Production | K55: Packing A | L55: Packer | M55: =VLOOKUP(B55,All!$B$4:$S$8977,12,FALSE) -> 192 | N55: 0 | O55: =VLOOKUP(B55,All!$B$4:$S$8977,14,FALSE) -> 0 | P55: =VLOOKUP(B55,All!$B$4:$S$8977,15,FALSE) -> 0 | Q55: =VLOOKUP(B55,All!$B$4:$S$8977,16,FALSE) -> 0 | R55: 7 | S55: 10 | T55: =SUM(M55:S55) -> 209 | U55: 5 | V55: 44562 | W55: Jerry | Y55: 包裝助理 | Z55: =M55+2 -> 194 | AA55: =N55 -> 0 | AB55: =O55 -> 0 | AC55: =P55+U55 -> 5 | AD55: =Q55 -> 0 | AE55: =R55 -> 7 | AF55: =S55 -> 10 | AG55: =SUM(Z55:AF55) -> 216 | AP55: New Add
A56: =1+A55 -> 52 | B56: 1831 | C56: =VLOOKUP(B56,All!$B$4:$S$8977,2,FALSE) -> គឹម | D56: =VLOOKUP(B56,All!$B$4:$S$89977,3,FALSE) -> យឿង | E56: =VLOOKUP(B56,All!$B$4:$S$8977,4,FALSE) -> KIM | F56: =VLOOKUP(B56,All!$B$4:$S$8977,5,FALSE) -> YOEUNG | G56: =VLOOKUP(B56,All!$B$4:$S$8977,6,FALSE) -> F | H56: =VLOOKUP(B56,All!$B$4:$S$8977,7,FALSE) -> 29637 | I56: =VLOOKUP(B56,All!$B$4:$S$8977,8,FALSE) -> 42768 | J56: Production | K56: Cutting | L56: Assist. Cutting | M56: =VLOOKUP(B56,All!$B$4:$S$8977,12,FALSE) -> 192 | N56: =VLOOKUP(B56,All!$B$4:$S$8977,13,FALSE) -> 5 | O56: =VLOOKUP(B56,All!$B$4:$S$8977,14,FALSE) -> 20 | P56: =VLOOKUP(B56,All!$B$4:$S$8977,15,FALSE) -> 10 | Q56: =VLOOKUP(B56,All!$B$4:$S$8977,16,FALSE) -> 0 | R56: 7 | S56: 10 | T56: =SUM(M56:S56) -> 244 | U56: 5 | V56: 44562 | W56: Jerry | Y56: 裁剪助理 | Z56: =M56+2 -> 194 | AA56: =N56 -> 5 | AB56: =O56 -> 20 | AC56: =P56+U56 -> 15 | AD56: =Q56 -> 0 | AE56: =R56 -> 7 | AF56: =S56 -> 10 | AG56: =SUM(Z56:AF56) -> 251 | AH56: =Z56-M56 -> 2 | AI56: =AA56-N56 -> 0 | AJ56: =AB56-O56 -> 0 | AK56: =AC56-P56 -> 5 | AL56: =AD56-Q56 -> 0 | AM56: =AE56-R56 -> 0 | AN56: =AF56-S56 -> 0 | AO56: =AG56-T56 -> 7
A57: =1+A56 -> 53 | B57: 4092 | C57: =VLOOKUP(B57,All!$B$4:$S$8977,2,FALSE) -> សុខ | D57: =VLOOKUP(B57,All!$B$4:$S$89977,3,FALSE) -> សិលា | E57: =VLOOKUP(B57,All!$B$4:$S$8977,4,FALSE) -> SOK | F57: =VLOOKUP(B57,All!$B$4:$S$8977,5,FALSE) -> SELA | G57: =VLOOKUP(B57,All!$B$4:$S$8977,6,FALSE) -> F | H57: =VLOOKUP(B57,All!$B$4:$S$8977,7,FALSE) -> 37479 | I57: =VLOOKUP(B57,All!$B$4:$S$8977,8,FALSE) -> 44035 | J57: Production | K57: Weahours | L57: Assist. Warehouse | M57: =VLOOKUP(B57,All!$B$4:$S$8977,12,FALSE) -> 192 | N57: =VLOOKUP(B57,All!$B$4:$S$8977,13,FALSE) -> 2 | O57: =VLOOKUP(B57,All!$B$4:$S$8977,14,FALSE) -> 0 | P57: =VLOOKUP(B57,All!$B$4:$S$8977,15,FALSE) -> 30 | Q57: =VLOOKUP(B57,All!$B$4:$S$8977,16,FALSE) -> 0 | R57: 7 | S57: 10 | T57: =SUM(M57:S57) -> 241 | U57: 5 | V57: 44562 | W57: Jerry | Y57: 倉庫助理 | Z57: =M57+2 -> 194 | AA57: =N57 -> 2 | AB57: =O57 -> 0 | AC57: =P57+U57 -> 35 | AD57: =Q57 -> 0 | AE57: =R57 -> 7 | AF57: =S57 -> 10 | AG57: =SUM(Z57:AF57) -> 248 | AH57: =Z57-M57 -> 2 | AI57: =AA57-N57 -> 0 | AJ57: =AB57-O57 -> 0 | AK57: =AC57-P57 -> 5 | AL57: =AD57-Q57 -> 0 | AM57: =AE57-R57 -> 0 | AN57: =AF57-S57 -> 0 | AO57: =AG57-T57 -> 7
T58: =SUM(T5:T57) -> 15386 | U58: =SUM(U5:U57) -> 650 | AG58: =SUM(AG5:AG57) -> 16140 | AH58: =SUM(AH5:AH57) -> 102 | AI58: =SUM(AI5:AI57) -> 0 | AJ58: =SUM(AJ5:AJ57) -> 0 | AK58: =SUM(AK5:AK57) -> 645

Sheet Production
A1: ល.រ | B1: Factory ID | C1: គោត្តនាម | D1: នាម | E1: គោត្តនាមឡាតាំង | F1: នាមឡាតាំង | G1: ភេទ | H1: ថ្ងៃខែឆ្នាំកំណើត | I1: កាលបរិ. ចូលធ្វើការ | J1: ផ្នែក | K1: ក្រុម | L1: តួនាទី | M1: Salary Report 2021 | U1: Adjust amount | V1: Adjust Date | W1: Evaluator | X1: 2022 Total Marks | Y1: With Comment | Z1: Salary Report 2022
A2: Nº | B2: Factory ID | C2: Khmer Sure name | D2: Khmer Name | E2: English Sure name | F2: Khmer Name | G2: Sex | H2: Birth of Date | I2: Join Date | J2: Department | K2: Group | L2: Position | M2: Basic | N2: Seniority | O2: Skill | P2: Position | Q2: Language | R2: Housing &Transportation | S2: Motivation | T2: Total | U2: 調動金額 | V2: 調動日期 | W2: 評核人 | X2: 2022總分 | Y2: 意見 | Z2: Basic | AA2: Seniority | AB2: Skill | AC2: Position | AD2: Language | AE2: Housing &Transportation | AF2: Motivation | AG2: Total
A3: 排序 | B3: 工號 | E3: 姓名 | G3: 性別 | H3: 生日 | I3: 入職日期 | J3: 部門 | K3: 組別 | L3: 崗位名稱 | M3: 底薪 | N3: 工齡 | O3: 技能 | P3: 職位 | Q3: 語言 | R3: 房屋/交通 | S3: 全勤 | T3: 2021薪資總額 | U3: 調動金額 | V3: 調動日期 | W3: 評核人 | X3: 2022總分 | Y3: 意見 | Z3: 底薪 | AA3: 工齡 | AB3: 技能 | AC3: 職位 | AD3: 語言 | AE3: 房屋/交通 | AF3: 全勤 | AG3: 2022薪資總額
A4: =1 -> 1 | B4: 47 | C4: =VLOOKUP(B4,All!$B$4:$S$8977,2,FALSE) -> ឃុន | D4: =VLOOKUP(B4,All!$B$4:$S$89977,3,FALSE) -> សាខន | E4: =VLOOKUP(B4,All!$B$4:$S$8977,4,FALSE) -> Khun | F4: =VLOOKUP(B4,All!$B$4:$S$8977,5,FALSE) -> Sakhân | G4: =VLOOKUP(B4,All!$B$4:$S$8977,6,FALSE) -> F | H4: =VLOOKUP(B4,All!$B$4:$S$8977,7,FALSE) -> 24152 | I4: =VLOOKUP(B4,All!$B$4:$S$8977,8,FALSE) -> 41583 | J4: =VLOOKUP(B4,All!$B$4:$S$8977,9,FALSE) -> Production | K4: =VLOOKUP(B4,All!$B$4:$S$8977,10,FALSE) -> Line8 | L4: =VLOOKUP(B4,All!$B$4:$S$8977,11,FALSE) -> Sewing operator | M4: =VLOOKUP(B4,All!$B$4:$S$8977,12,FALSE) -> 199 | N4: =VLOOKUP(B4,All!$B$4:$S$8977,13,FALSE) -> 9 | O4: =VLOOKUP(B4,All!$B$4:$S$8977,14,FALSE) -> 20 | P4: =VLOOKUP(B4,All!$B$4:$S$8977,15,FALSE) -> 0 | Q4: =VLOOKUP(B4,All!$B$4:$S$8977,16,FALSE) -> 0 | R4: 7 | S4: 10 | T4: =SUM(M4:S4) -> 245 | Z4: =M4+AH4 -> 201 | AA4: =N4 -> 9 | AB4: =O4 -> 20 | AC4: =P4 -> 0 | AD4: =Q4 -> 0 | AE4: =R4 -> 7 | AF4: =S4 -> 10 | AG4: =SUM(Z4:AF4) -> 247 | AH4: 2 | AI4: 0 | AJ4: 0 | AK4: 0 | AL4: 0 | AM4: 0 | AN4: 0 | AO4: 2
A5: =1+A4 -> 2 | B5: 67 | C5: =VLOOKUP(B5,All!$B$4:$S$8977,2,FALSE) -> ហុង | D5: =VLOOKUP(B5,All!$B$4:$S$89977,3,FALSE) -> សេងចន្នី | E5: =VLOOKUP(B5,All!$B$4:$S$8977,4,FALSE) -> HONG | F5: =VLOOKUP(B5,All!$B$4:$S$8977,5,FALSE) -> SENG CHANNY | G5: =VLOOKUP(B5,All!$B$4:$S$8977,6,FALSE) -> F | H5: =VLOOKUP(B5,All!$B$4:$S$8977,7,FALSE) -> 30439 | I5: =VLOOKUP(B5,All!$B$4:$S$8977,8,FALSE) -> 41591 | J5: =VLOOKUP(B5,All!$B$4:$S$8977,9,FALSE) -> Production | K5: =VLOOKUP(B5,All!$B$4:$S$8977,10,FALSE) -> Line9 | L5: =VLOOKUP(B5,All!$B$4:$S$8977,11,FALSE) -> Sewing operator | M5: =VLOOKUP(B5,All!$B$4:$S$8977,12,FALSE) -> 192 | N5: =VLOOKUP(B5,All!$B$4:$S$8977,13,FALSE) -> 9 | O5: =VLOOKUP(B5,All!$B$4:$S$8977,14,FALSE) -> 20 | P5: =VLOOKUP(B5,All!$B$4:$S$8977,15,FALSE) -> 0 | Q5: =VLOOKUP(B5,All!$B$4:$S$8977,16,FALSE) -> 0 | R5: 7 | S5: 10 | T5: =SUM(M5:S5) -> 238 | Z5: =M5+AH5 -> 194 | AA5: =N5 -> 9 | AB5: =O5 -> 20 | AC5: =P5 -> 0 | AD5: =Q5 -> 0 | AE5: =R5 -> 7 | AF5: =S5 -> 10 | AG5: =SUM(Z5:AF5) -> 240 | AH5: 2 | AI5: 0 | AJ5: 0 | AK5: 0 | AL5: 0 | AM5: 0 | AN5: 0 | AO5: 2
A6: =1+A5 -> 3 | B6: 69 | C6: =VLOOKUP(B6,All!$B$4:$S$8977,2,FALSE) -> ធង | D6: =VLOOKUP(B6,All!$B$4:$S$89977,3,FALSE) -> អួន | E6: =VLOOKUP(B6,All!$B$4:$S$8977,4,FALSE) -> THORNG | F6: =VLOOKUP(B6,All!$B$4:$S$8977,5,FALSE) -> UON | G6: =VLOOKUP(B6,All!$B$4:$S$8977,6,FALSE) -> F | H6: =VLOOKUP(B6,All!$B$4:$S$8977,7,FALSE) -> 29285 | I6: =VLOOKUP(B6,All!$B$4:$S$8977,8,FALSE) -> 41591 | J6: =VLOOKUP(B6,All!$B$4:$S$8977,9,FALSE) -> Production | K6: =VLOOKUP(B6,All!$B$4:$S$8977,10,FALSE) -> Line21 | L6: =VLOOKUP(B6,All!$B$4:$S$8977,11,FALSE) -> Sewing operator | M6: =VLOOKUP(B6,All!$B$4:$S$8977,12,FALSE) -> 192 | N6: =VLOOKUP(B6,All!$B$4:$S$8977,13,FALSE) -> 9 | O6: =VLOOKUP(B6,All!$B$4:$S$8977,14,FALSE) -> 20 | P6: =VLOOKUP(B6,All!$B$4:$S$8977,15,FALSE) -> 0 | Q6: =VLOOKUP(B6,All!$B$4:$S$8977,16,FALSE) -> 0 | R6: 7 | S6: 10 | T6: =SUM(M6:S6) -> 238 | Z6: =M6+AH6 -> 194 | AA6: =N6 -> 9 | AB6: =O6 -> 20 | AC6: =P6 -> 0 | AD6: =Q6 -> 0 | AE6: =R6 -> 7 | AF6: =S6 -> 10 | AG6: =SUM(Z6:AF6) -> 240 | AH6: 2 | AI6: 0 | AJ6: 0 | AK6: 0 | AL6: 0 | AM6: 0 | AN6: 0 | AO6: 2
A7: =1+A6 -> 4 | B7: 78 | C7: =VLOOKUP(B7,All!$B$4:$S$8977,2,FALSE) -> ម៉ូវ | D7: =VLOOKUP(B7,All!$B$4:$S$89977,3,FALSE) -> សុធឿន | E7: =VLOOKUP(B7,All!$B$4:$S$8977,4,FALSE) -> MOUV | F7: =VLOOKUP(B7,All!$B$4:$S$8977,5,FALSE) -> SOTHOEUNRN | G7: =VLOOKUP(B7,All!$B$4:$S$8977,6,FALSE) -> F | H7: =VLOOKUP(B7,All!$B$4:$S$8977,7,FALSE) -> 31630 | I7: =VLOOKUP(B7,All!$B$4:$S$8977,8,FALSE) -> 41598 | J7: =VLOOKUP(B7,All!$B$4:$S$8977,9,FALSE) -> Production | K7: =VLOOKUP(B7,All!$B$4:$S$8977,10,FALSE) -> Line10 | L7: =VLOOKUP(B7,All!$B$4:$S$8977,11,FALSE) -> Sewing operator | M7: =VLOOKUP(B7,All!$B$4:$S$8977,12,FALSE) -> 192 | N7: =VLOOKUP(B7,All!$B$4:$S$8977,13,FALSE) -> 9 | O7: =VLOOKUP(B7,All!$B$4:$S$8977,14,FALSE) -> 20 | P7: =VLOOKUP(B7,All!$B$4:$S$8977,15,FALSE) -> 0 | Q7: =VLOOKUP(B7,All!$B$4:$S$8977,16,FALSE) -> 0 | R7: 7 | S7: 10 | T7: =SUM(M7:S7) -> 238 | Z7: =M7+AH7 -> 194 | AA7: =N7 -> 9 | AB7: =O7 -> 20 | AC7: =P7 -> 0 | AD7: =Q7 -> 0 | AE7: =R7 -> 7 | AF7: =S7 -> 10 | AG7: =SUM(Z7:AF7) -> 240 | AH7: 2 | AI7: 0 | AJ7: 0 | AK7: 0 | AL7: 0 | AM7: 0 | AN7: 0 | AO7: 2
A8: =1+A7 -> 5 | B8: 81 | C8: =VLOOKUP(B8,All!$B$4:$S$8977,2,FALSE) -> វ៉ន | D8: =VLOOKUP(B8,All!$B$4:$S$89977,3,FALSE) -> ភា | E8: =VLOOKUP(B8,All!$B$4:$S$8977,4,FALSE) -> Vorn | F8: =VLOOKUP(B8,All!$B$4:$S$8977,5,FALSE) -> Phea | G8: =VLOOKUP(B8,All!$B$4:$S$8977,6,FALSE) -> F | H8: =VLOOKUP(B8,All!$B$4:$S$8977,7,FALSE) -> 28299 | I8: =VLOOKUP(B8,All!$B$4:$S$8977,8,FALSE) -> 41599 | J8: =VLOOKUP(B8,All!$B$4:$S$8977,9,FALSE) -> Production | K8: =VLOOKUP(B8,All!$B$4:$S$8977,10,FALSE) -> Line10 | L8: =VLOOKUP(B8,All!$B$4:$S$8977,11,FALSE) -> Sewing operator | M8: =VLOOKUP(B8,All!$B$4:$S$8977,12,FALSE) -> 192 | N8: =VLOOKUP(B8,All!$B$4:$S$8977,13,FALSE) -> 9 | O8: =VLOOKUP(B8,All!$B$4:$S$8977,14,FALSE) -> 20 | P8: =VLOOKUP(B8,All!$B$4:$S$8977,15,FALSE) -> 0 | Q8: =VLOOKUP(B8,All!$B$4:$S$8977,16,FALSE) -> 0 | R8: 7 | S8: 10 | T8: =SUM(M8:S8) -> 238 | Z8: =M8+AH8 -> 194 | AA8: =N8 -> 9 | AB8: =O8 -> 20 | AC8: =P8 -> 0 | AD8: =Q8 -> 0 | AE8: =R8 -> 7 | AF8: =S8 -> 10 | AG8: =SUM(Z8:AF8) -> 240 | AH8: 2 | AI8: 0 | AJ8: 0 | AK8: 0 | AL8: 0 | AM8: 0 | AN8: 0 | AO8: 2
A9: =1+A8 -> 6 | B9: 90 | C9: =VLOOKUP(B9,All!$B$4:$S$8977,2,FALSE) -> ហឿង | D9: =VLOOKUP(B9,All!$B$4:$S$89977,3,FALSE) -> សុខឡាង | E9: =VLOOKUP(B9,All!$B$4:$S$8977,4,FALSE) -> HOEUNG | F9: =VLOOKUP(B9,All!$B$4:$S$8977,5,FALSE) -> SOK LANG | G9: =VLOOKUP(B9,All!$B$4:$S$8977,6,FALSE) -> F | H9: =VLOOKUP(B9,All!$B$4:$S$8977,7,FALSE) -> 33244 | I9: =VLOOKUP(B9,All!$B$4:$S$8977,8,FALSE) -> 41598 | J9: =VLOOKUP(B9,All!$B$4:$S$8977,9,FALSE) -> Production | K9: =VLOOKUP(B9,All!$B$4:$S$8977,10,FALSE) -> Line10 | L9: =VLOOKUP(B9,All!$B$4:$S$8977,11,FALSE) -> Sewing operator | M9: =VLOOKUP(B9,All!$B$4:$S$8977,12,FALSE) -> 192 | N9: =VLOOKUP(B9,All!$B$4:$S$8977,13,FALSE) -> 9 | O9: =VLOOKUP(B9,All!$B$4:$S$8977,14,FALSE) -> 20 | P9: =VLOOKUP(B9,All!$B$4:$S$8977,15,FALSE) -> 0 | Q9: =VLOOKUP(B9,All!$B$4:$S$8977,16,FALSE) -> 0 | R9: 7 | S9: 10 | T9: =SUM(M9:S9) -> 238 | Z9: =M9+AH9 -> 194 | AA9: =N9 -> 9 | AB9: =O9 -> 20 | AC9: =P9 -> 0 | AD9: =Q9 -> 0 | AE9: =R9 -> 7 | AF9: =S9 -> 10 | AG9: =SUM(Z9:AF9) -> 240 | AH9: 2 | AI9: 0 | AJ9: 0 | AK9: 0 | AL9: 0 | AM9: 0 | AN9: 0 | AO9: 2
A10: =1+A9 -> 7 | B10: 113 | C10: =VLOOKUP(B10,All!$B$4:$S$8977,2,FALSE) -> អៀម | D10: =VLOOKUP(B10,All!$B$4:$S$89977,3,FALSE) -> សារីម | E10: =VLOOKUP(B10,All!$B$4:$S$8977,4,FALSE) -> IEM | F10: =VLOOKUP(B10,All!$B$4:$S$8977,5,FALSE) -> SARIM | G10: =VLOOKUP(B10,All!$B$4:$S$8977,6,FALSE) -> F | H10: =VLOOKUP(B10,All!$B$4:$S$8977,7,FALSE) -> 29385 | I10: =VLOOKUP(B10,All!$B$4:$S$8977,8,FALSE) -> 41612 | J10: =VLOOKUP(B10,All!$B$4:$S$8977,9,FALSE) -> Production | K10: =VLOOKUP(B10,All!$B$4:$S$8977,10,FALSE) -> Line1 | L10: =VLOOKUP(B10,All!$B$4:$S$8977,11,FALSE) -> Sewing operator | M10: =VLOOKUP(B10,All!$B$4:$S$8977,12,FALSE) -> 192 | N10: =VLOOKUP(B10,All!$B$4:$S$8977,13,FALSE) -> 9 | O10: =VLOOKUP(B10,All!$B$4:$S$8977,14,FALSE) -> 20 | P10: =VLOOKUP(B10,All!$B$4:$S$8977,15,FALSE) -> 0 | Q10: =VLOOKUP(B10,All!$B$4:$S$8977,16,FALSE) -> 0 | R10: 7 | S10: 10 | T10: =SUM(M10:S10) -> 238 | Z10: =M10+AH10 -> 194 | AA10: =N10 -> 9 | AB10: =O10 -> 20 | AC10: =P10 -> 0 | AD10: =Q10 -> 0 | AE10: =R10 -> 7 | AF10: =S10 -> 10 | AG10: =SUM(Z10:AF10) -> 240 | AH10: 2 | AI10: 0 | AJ10: 0 | AK10: 0 | AL10: 0 | AM10: 0 | AN10: 0 | AO10: 2
A11: =1+A10 -> 8 | B11: 146 | C11: =VLOOKUP(B11,All!$B$4:$S$8977,2,FALSE) -> ទៀប | D11: =VLOOKUP(B11,All!$B$4:$S$89977,3,FALSE) -> សូនី | E11: =VLOOKUP(B11,All!$B$4:$S$8977,4,FALSE) -> Teab | F11: =VLOOKUP(B11,All!$B$4:$S$8977,5,FALSE) -> sony | G11: =VLOOKUP(B11,All!$B$4:$S$8977,6,FALSE) -> F | H11: =VLOOKUP(B11,All!$B$4:$S$8977,7,FALSE) -> 25950 | I11: =VLOOKUP(B11,All!$B$4:$S$8977,8,FALSE) -> 41619 | J11: =VLOOKUP(B11,All!$B$4:$S$8977,9,FALSE) -> Production | K11: =VLOOKUP(B11,All!$B$4:$S$8977,10,FALSE) -> Line2 | L11: =VLOOKUP(B11,All!$B$4:$S$8977,11,FALSE) -> Sewing operator | M11: =VLOOKUP(B11,All!$B$4:$S$8977,12,FALSE) -> 192 | N11: =VLOOKUP(B11,All!$B$4:$S$8977,13,FALSE) -> 9 | O11: =VLOOKUP(B11,All!$B$4:$S$8977,14,FALSE) -> 20 | P11: =VLOOKUP(B11,All!$B$4:$S$8977,15,FALSE) -> 0 | Q11: =VLOOKUP(B11,All!$B$4:$S$8977,16,FALSE) -> 0 | R11: 7 | S11: 10 | T11: =SUM(M11:S11) -> 238 | Z11: =M11+AH11 -> 194 | AA11: =N11 -> 9 | AB11: =O11 -> 20 | AC11: =P11 -> 0 | AD11: =Q11 -> 0 | AE11: =R11 -> 7 | AF11: =S11 -> 10 | AG11: =SUM(Z11:AF11) -> 240 | AH11: 2 | AI11: 0 | AJ11: 0 | AK11: 0 | AL11: 0 | AM11: 0 | AN11: 0 | AO11: 2
A12: =1+A11 -> 9 | B12: 176 | C12: =VLOOKUP(B12,All!$B$4:$S$8977,2,FALSE) -> ឃុំ | D12: =VLOOKUP(B12,All!$B$4:$S$89977,3,FALSE) -> ផល្លី | E12: =VLOOKUP(B12,All!$B$4:$S$8977,4,FALSE) -> khom | F12: =VLOOKUP(B12,All!$B$4:$S$8977,5,FALSE) -> pholy | G12: =VLOOKUP(B12,All!$B$4:$S$8977,6,FALSE) -> F | H12: =VLOOKUP(B12,All!$B$4:$S$8977,7,FALSE) -> 29575 | I12: =VLOOKUP(B12,All!$B$4:$S$8977,8,FALSE) -> 41683 | J12: =VLOOKUP(B12,All!$B$4:$S$8977,9,FALSE) -> Production | K12: =VLOOKUP(B12,All!$B$4:$S$8977,10,FALSE) -> Line15 | L12: =VLOOKUP(B12,All!$B$4:$S$8977,11,FALSE) -> Sewing operator | M12: =VLOOKUP(B12,All!$B$4:$S$8977,12,FALSE) -> 192 | N12: =VLOOKUP(B12,All!$B$4:$S$8977,13,FALSE) -> 8 | O12: =VLOOKUP(B12,All!$B$4:$S$8977,14,FALSE) -> 25 | P12: =VLOOKUP(B12,All!$B$4:$S$8977,15,FALSE) -> 0 | Q12: =VLOOKUP(B12,All!$B$4:$S$8977,16,FALSE) -> 0 | R12: 7 | S12: 10 | T12: =SUM(M12:S12) -> 242 | Z12: =M12+AH12 -> 194 | AA12: =N12 -> 8 | AB12: =O12 -> 25 | AC12: =P12 -> 0 | AD12: =Q12 -> 0 | AE12: =R12 -> 7 | AF12: =S12 -> 10 | AG12: =SUM(Z12:AF12) -> 244 | AH12: 2 | AI12: 0 | AJ12: 0 | AK12: 0 | AL12: 0 | AM12: 0 | AN12: 0 | AO12: 2
A13: =1+A12 -> 10 | B13: 224 | C13: =VLOOKUP(B13,All!$B$4:$S$8977,2,FALSE) -> ជឿន | D13: =VLOOKUP(B13,All!$B$4:$S$89977,3,FALSE) -> រឿម | E13: =VLOOKUP(B13,All!$B$4:$S$8977,4,FALSE) -> Choeun | F13: =VLOOKUP(B13,All!$B$4:$S$8977,5,FALSE) -> Roeum | G13: =VLOOKUP(B13,All!$B$4:$S$8977,6,FALSE) -> F | H13: =VLOOKUP(B13,All!$B$4:$S$8977,7,FALSE) -> 28491 | I13: =VLOOKUP(B13,All!$B$4:$S$8977,8,FALSE) -> 41702 | J13: =VLOOKUP(B13,All!$B$4:$S$8977,9,FALSE) -> Production | K13: =VLOOKUP(B13,All!$B$4:$S$8977,10,FALSE) -> Line2 | L13: =VLOOKUP(B13,All!$B$4:$S$8977,11,FALSE) -> Sewing operator | M13: =VLOOKUP(B13,All!$B$4:$S$8977,12,FALSE) -> 192 | N13: =VLOOKUP(B13,All!$B$4:$S$8977,13,FALSE) -> 8 | O13: =VLOOKUP(B13,All!$B$4:$S$8977,14,FALSE) -> 20 | P13: =VLOOKUP(B13,All!$B$4:$S$8977,15,FALSE) -> 0 | Q13: =VLOOKUP(B13,All!$B$4:$S$8977,16,FALSE) -> 0 | R13: 7 | S13: 10 | T13: =SUM(M13:S13) -> 237 | Z13: =M13+AH13 -> 194 | AA13: =N13 -> 8 | AB13: =O13 -> 20 | AC13: =P13 -> 0 | AD13: =Q13 -> 0 | AE13: =R13 -> 7 | AF13: =S13 -> 10 | AG13: =SUM(Z13:AF13) -> 239 | AH13: 2 | AI13: 0 | AJ13: 0 | AK13: 0 | AL13: 0 | AM13: 0 | AN13: 0 | AO13: 2
A14: =1+A13 -> 11 | B14: 226 | C14: =VLOOKUP(B14,All!$B$4:$S$8977,2,FALSE) -> រស់ | D14: =VLOOKUP(B14,All!$B$4:$S$89977,3,FALSE) -> ផល្លី | E14: =VLOOKUP(B14,All!$B$4:$S$8977,4,FALSE) -> Ros | F14: =VLOOKUP(B14,All!$B$4:$S$8977,5,FALSE) -> Poly | G14: =VLOOKUP(B14,All!$B$4:$S$8977,6,FALSE) -> F | H14: =VLOOKUP(B14,All!$B$4:$S$8977,7,FALSE) -> 30275 | I14: =VLOOKUP(B14,All!$B$4:$S$8977,8,FALSE) -> 41702 | J14: =VLOOKUP(B14,All!$B$4:$S$8977,9,FALSE) -> Production | K14: =VLOOKUP(B14,All!$B$4:$S$8977,10,FALSE) -> Line2 | L14: =VLOOKUP(B14,All!$B$4:$S$8977,11,FALSE) -> Sewing operator | M14: =VLOOKUP(B14,All!$B$4:$S$8977,12,FALSE) -> 192 | N14: =VLOOKUP(B14,All!$B$4:$S$8977,13,FALSE) -> 8 | O14: =VLOOKUP(B14,All!$B$4:$S$8977,14,FALSE) -> 20 | P14: =VLOOKUP(B14,All!$B$4:$S$8977,15,FALSE) -> 0 | Q14: =VLOOKUP(B14,All!$B$4:$S$8977,16,FALSE) -> 0 | R14: 7 | S14: 10 | T14: =SUM(M14:S14) -> 237 | Z14: =M14+AH14 -> 194 | AA14: =N14 -> 8 | AB14: =O14 -> 20 | AC14: =P14 -> 0 | AD14: =Q14 -> 0 | AE14: =R14 -> 7 | AF14: =S14 -> 10 | AG14: =SUM(Z14:AF14) -> 239 | AH14: 2 | AI14: 0 | AJ14: 0 | AK14: 0 | AL14: 0 | AM14: 0 | AN14: 0 | AO14: 2
A15: =1+A14 -> 12 | B15: 271 | C15: =VLOOKUP(B15,All!$B$4:$S$8977,2,FALSE) -> វុន | D15: =VLOOKUP(B15,All!$B$4:$S$89977,3,FALSE) -> តាំង | E15: =VLOOKUP(B15,All!$B$4:$S$8977,4,FALSE) -> VUN | F15: =VLOOKUP(B15,All!$B$4:$S$8977,5,FALSE) -> TAING | G15: =VLOOKUP(B15,All!$B$4:$S$8977,6,FALSE) -> F | H15: =VLOOKUP(B15,All!$B$4:$S$8977,7,FALSE) -> 29064 | I15: =VLOOKUP(B15,All!$B$4:$S$8977,8,FALSE) -> 41730 | J15: =VLOOKUP(B15,All!$B$4:$S$8977,9,FALSE) -> Production | K15: =VLOOKUP(B15,All!$B$4:$S$8977,10,FALSE) -> Line17 | L15: =VLOOKUP(B15,All!$B$4:$S$8977,11,FALSE) -> Sewing operator | M15: =VLOOKUP(B15,All!$B$4:$S$8977,12,FALSE) -> 192 | N15: =VLOOKUP(B15,All!$B$4:$S$8977,13,FALSE) -> 8 | O15: =VLOOKUP(B15,All!$B$4:$S$8977,14,FALSE) -> 20 | P15: =VLOOKUP(B15,All!$B$4:$S$8977,15,FALSE) -> 0 | Q15: =VLOOKUP(B15,All!$B$4:$S$8977,16,FALSE) -> 0 | R15: 7 | S15: 10 | T15: =SUM(M15:S15) -> 237 | Z15: =M15+AH15 -> 194 | AA15: =N15 -> 8 | AB15: =O15 -> 20 | AC15: =P15 -> 0 | AD15: =Q15 -> 0 | AE15: =R15 -> 7 | AF15: =S15 -> 10 | AG15: =SUM(Z15:AF15) -> 239 | AH15: 2 | AI15: 0 | AJ15: 0 | AK15: 0 | AL15: 0 | AM15: 0 | AN15: 0 | AO15: 2
A16: =1+A15 -> 13 | B16: 283 | C16: =VLOOKUP(B16,All!$B$4:$S$8977,2,FALSE) -> កែវ | D16: =VLOOKUP(B16,All!$B$4:$S$89977,3,FALSE) -> ពុទ្ធា | E16: =VLOOKUP(B16,All!$B$4:$S$8977,4,FALSE) -> KEO | F16: =VLOOKUP(B16,All!$B$4:$S$8977,5,FALSE) -> PUTHEA | G16: =VLOOKUP(B16,All!$B$4:$S$8977,6,FALSE) -> F | H16: =VLOOKUP(B16,All!$B$4:$S$8977,7,FALSE) -> 34151 | I16: =VLOOKUP(B16,All!$B$4:$S$8977,8,FALSE) -> 41750 | J16: =VLOOKUP(B16,All!$B$4:$S$8977,9,FALSE) -> Production | K16: =VLOOKUP(B16,All!$B$4:$S$8977,10,FALSE) -> Line21 | L16: =VLOOKUP(B16,All!$B$4:$S$8977,11,FALSE) -> Sewing operator | M16: =VLOOKUP(B16,All!$B$4:$S$8977,12,FALSE) -> 192 | N16: =VLOOKUP(B16,All!$B$4:$S$8977,13,FALSE) -> 8 | O16: =VLOOKUP(B16,All!$B$4:$S$8977,14,FALSE) -> 20 | P16: =VLOOKUP(B16,All!$B$4:$S$8977,15,FALSE) -> 0 | Q16: =VLOOKUP(B16,All!$B$4:$S$8977,16,FALSE) -> 0 | R16: 7 | S16: 10 | T16: =SUM(M16:S16) -> 237 | Z16: =M16+AH16 -> 194 | AA16: =N16 -> 8 | AB16: =O16 -> 20 | AC16: =P16 -> 0 | AD16: =Q16 -> 0 | AE16: =R16 -> 7 | AF16: =S16 -> 10 | AG16: =SUM(Z16:AF16) -> 239 | AH16: 2 | AI16: 0 | AJ16: 0 | AK16: 0 | AL16: 0 | AM16: 0 | AN16: 0 | AO16: 2
... A420: =1+A419 -> 417 | B420: 5138 | C420: =VLOOKUP(B420,All!$B$4:$S$8977,2,FALSE) -> សុខ | D420: =VLOOKUP(B420,All!$B$4:$S$89977,3,FALSE) -> ដានី | E420: =VLOOKUP(B420,All!$B$4:$S$8977,4,FALSE) -> SOK | F420: =VLOOKUP(B420,All!$B$4:$S$8977,5,FALSE) -> DANY | G420: =VLOOKUP(B420,All!$B$4:$S$8977,6,FALSE) -> F | H420: =VLOOKUP(B420,All!$B$4:$S$8977,7,FALSE) -> 36134 | I420: =VLOOKUP(B420,All!$B$4:$S$8977,8,FALSE) -> 44455 | J420: =VLOOKUP(B420,All!$B$4:$S$8977,9,FALSE) -> Production | K420: =VLOOKUP(B420,All!$B$4:$S$8977,10,FALSE) -> Line 7 | L420: =VLOOKUP(B420,All!$B$4:$S$8977,11,FALSE) -> Sewing operator | M420: =VLOOKUP(B420,All!$B$4:$S$8977,12,FALSE) -> 192 | N420: =VLOOKUP(B420,All!$B$4:$S$8977,13,FALSE) -> 0 | O420: =VLOOKUP(B420,All!$B$4:$S$8977,14,FALSE) -> 0 | P420: =VLOOKUP(B420,All!$B$4:$S$8977,15,FALSE) -> 0 | Q420: =VLOOKUP(B420,All!$B$4:$S$8977,16,FALSE) -> 0 | R420: 7 | S420: 10 | T420: =SUM(M420:S420) -> 209 | Z420: =M420+AH420 -> 194 | AA420: =N420 -> 0 | AB420: =O420 -> 0 | AC420: =P420 -> 0 | AD420: =Q420 -> 0 | AE420: =R420 -> 7 | AF420: =S420 -> 10 | AG420: =SUM(Z420:AF420) -> 211 | AH420: 2 | AI420: 0 | AJ420: 0 | AK420: 0 | AL420: 0 | AM420: 0 | AN420: 0 | AO420: 2
A421: =1+A420 -> 418 | B421: 5140 | C421: =VLOOKUP(B421,All!$B$4:$S$8977,2,FALSE) -> ឌី | D421: =VLOOKUP(B421,All!$B$4:$S$89977,3,FALSE) -> សុខឡៅ | E421: =VLOOKUP(B421,All!$B$4:$S$8977,4,FALSE) -> DY | F421: =VLOOKUP(B421,All!$B$4:$S$8977,5,FALSE) -> SOKLAO | G421: =VLOOKUP(B421,All!$B$4:$S$8977,6,FALSE) -> F | H421: =VLOOKUP(B421,All!$B$4:$S$8977,7,FALSE) -> 35353 | I421: =VLOOKUP(B421,All!$B$4:$S$8977,8,FALSE) -> 44455 | J421: =VLOOKUP(B421,All!$B$4:$S$8977,9,FALSE) -> Production | K421: =VLOOKUP(B421,All!$B$4:$S$8977,10,FALSE) -> Line5 | L421: =VLOOKUP(B421,All!$B$4:$S$8977,11,FALSE) -> Sewing operator | M421: =VLOOKUP(B421,All!$B$4:$S$8977,12,FALSE) -> 187 | N421: =VLOOKUP(B421,All!$B$4:$S$8977,13,FALSE) -> 0 | O421: =VLOOKUP(B421,All!$B$4:$S$8977,14,FALSE) -> 0 | P421: =VLOOKUP(B421,All!$B$4:$S$8977,15,FALSE) -> 0 | Q421: =VLOOKUP(B421,All!$B$4:$S$8977,16,FALSE) -> 0 | R421: 7 | S421: 10 | T421: =SUM(M421:S421) -> 204 | Z421: =M421+AH421+5 -> 194 | AA421: =N421 -> 0 | AB421: =O421 -> 0 | AC421: =P421 -> 0 | AD421: =Q421 -> 0 | AE421: =R421 -> 7 | AF421: =S421 -> 10 | AG421: =SUM(Z421:AF421) -> 211 | AH421: 2 | AI421: 0 | AJ421: 0 | AK421: 0 | AL421: 0 | AM421: 0 | AN421: 0 | AO421: 2
A422: =1+A421 -> 419 | B422: 5142 | C422: =VLOOKUP(B422,All!$B$4:$S$8977,2,FALSE) -> ស៊ុត | D422: =VLOOKUP(B422,All!$B$4:$S$89977,3,FALSE) -> សុផន | E422: =VLOOKUP(B422,All!$B$4:$S$8977,4,FALSE) -> SOTH | F422: =VLOOKUP(B422,All!$B$4:$S$8977,5,FALSE) -> SOPHORN | G422: =VLOOKUP(B422,All!$B$4:$S$8977,6,FALSE) -> F | H422: =VLOOKUP(B422,All!$B$4:$S$8977,7,FALSE) -> 31481 | I422: =VLOOKUP(B422,All!$B$4:$S$8977,8,FALSE) -> 44457 | J422: =VLOOKUP(B422,All!$B$4:$S$8977,9,FALSE) -> Production | K422: =VLOOKUP(B422,All!$B$4:$S$8977,10,FALSE) -> QC B | L422: =VLOOKUP(B422,All!$B$4:$S$8977,11,FALSE) -> Inspector | M422: =VLOOKUP(B422,All!$B$4:$S$8977,12,FALSE) -> 187 | N422: =VLOOKUP(B422,All!$B$4:$S$8977,13,FALSE) -> 0 | O422: =VLOOKUP(B422,All!$B$4:$S$8977,14,FALSE) -> 0 | P422: =VLOOKUP(B422,All!$B$4:$S$8977,15,FALSE) -> 0 | Q422: =VLOOKUP(B422,All!$B$4:$S$8977,16,FALSE) -> 0 | R422: 7 | S422: 10 | T422: =SUM(M422:S422) -> 204 | Z422: =M422+AH422+5 -> 194 | AA422: =N422 -> 0 | AB422: =O422 -> 0 | AC422: =P422 -> 0 | AD422: =Q422 -> 0 | AE422: =R422 -> 7 | AF422: =S422 -> 10 | AG422: =SUM(Z422:AF422) -> 211 | AH422: 2 | AI422: 0 | AJ422: 0 | AK422: 0 | AL422: 0 | AM422: 0 | AN422: 0 | AO422: 2
A423: =1+A422 -> 420 | B423: 5143 | C423: =VLOOKUP(B423,All!$B$4:$S$8977,2,FALSE) -> ផូន | D423: =VLOOKUP(B423,All!$B$4:$S$89977,3,FALSE) -> អេន | E423: =VLOOKUP(B423,All!$B$4:$S$8977,4,FALSE) -> PHAUN | F423: =VLOOKUP(B423,All!$B$4:$S$8977,5,FALSE) -> EN | G423: =VLOOKUP(B423,All!$B$4:$S$8977,6,FALSE) -> F | H423: =VLOOKUP(B423,All!$B$4:$S$8977,7,FALSE) -> 33094 | I423: =VLOOKUP(B423,All!$B$4:$S$8977,8,FALSE) -> 44457 | J423: =VLOOKUP(B423,All!$B$4:$S$8977,9,FALSE) -> Production | K423: =VLOOKUP(B423,All!$B$4:$S$8977,10,FALSE) -> Line 7 | L423: =VLOOKUP(B423,All!$B$4:$S$8977,11,FALSE) -> Sewing operator | M423: =VLOOKUP(B423,All!$B$4:$S$8977,12,FALSE) -> 187 | N423: =VLOOKUP(B423,All!$B$4:$S$8977,13,FALSE) -> 0 | O423: =VLOOKUP(B423,All!$B$4:$S$8977,14,FALSE) -> 0 | P423: =VLOOKUP(B423,All!$B$4:$S$8977,15,FALSE) -> 0 | Q423: =VLOOKUP(B423,All!$B$4:$S$8977,16,FALSE) -> 0 | R423: 7 | S423: 10 | T423: =SUM(M423:S423) -> 204 | Z423: =M423+AH423+5 -> 194 | AA423: =N423 -> 0 | AB423: =O423 -> 0 | AC423: =P423 -> 0 | AD423: =Q423 -> 0 | AE423: =R423 -> 7 | AF423: =S423 -> 10 | AG423: =SUM(Z423:AF423) -> 211 | AH423: 2 | AI423: 0 | AJ423: 0 | AK423: 0 | AL423: 0 | AM423: 0 | AN423: 0 | AO423: 2
A424: =1+A423 -> 421 | B424: 5144 | C424: =VLOOKUP(B424,All!$B$4:$S$8977,2,FALSE) -> ម៉ិក | D424: =VLOOKUP(B424,All!$B$4:$S$89977,3,FALSE) -> ស្រីកែវ | E424: =VLOOKUP(B424,All!$B$4:$S$8977,4,FALSE) -> MIK | F424: =VLOOKUP(B424,All!$B$4:$S$8977,5,FALSE) -> SREY KEO | G424: =VLOOKUP(B424,All!$B$4:$S$8977,6,FALSE) -> F | H424: =VLOOKUP(B424,All!$B$4:$S$8977,7,FALSE) -> 35433 | I424: =VLOOKUP(B424,All!$B$4:$S$8977,8,FALSE) -> 44457 | J424: =VLOOKUP(B424,All!$B$4:$S$8977,9,FALSE) -> Production | K424: =VLOOKUP(B424,All!$B$4:$S$8977,10,FALSE) -> Line 7 | L424: =VLOOKUP(B424,All!$B$4:$S$8977,11,FALSE) -> Sewing operator | M424: =VLOOKUP(B424,All!$B$4:$S$8977,12,FALSE) -> 187 | N424: =VLOOKUP(B424,All!$B$4:$S$8977,13,FALSE) -> 0 | O424: =VLOOKUP(B424,All!$B$4:$S$8977,14,FALSE) -> 0 | P424: =VLOOKUP(B424,All!$B$4:$S$8977,15,FALSE) -> 0 | Q424: =VLOOKUP(B424,All!$B$4:$S$8977,16,FALSE) -> 0 | R424: 7 | S424: 10 | T424: =SUM(M424:S424) -> 204 | Z424: =M424+AH424+5 -> 194 | AA424: =N424 -> 0 | AB424: =O424 -> 0 | AC424: =P424 -> 0 | AD424: =Q424 -> 0 | AE424: =R424 -> 7 | AF424: =S424 -> 10 | AG424: =SUM(Z424:AF424) -> 211 | AH424: 2 | AI424: 0 | AJ424: 0 | AK424: 0 | AL424: 0 | AM424: 0 | AN424: 0 | AO424: 2
A425: =1+A424 -> 422 | B425: 5145 | C425: =VLOOKUP(B425,All!$B$4:$S$8977,2,FALSE) -> ភាន | D425: =VLOOKUP(B425,All!$B$4:$S$89977,3,FALSE) -> ភីរ៉ា | E425: =VLOOKUP(B425,All!$B$4:$S$8977,4,FALSE) -> PHEAN | F425: =VLOOKUP(B425,All!$B$4:$S$8977,5,FALSE) -> PHIRA | G425: =VLOOKUP(B425,All!$B$4:$S$8977,6,FALSE) -> F | H425: =VLOOKUP(B425,All!$B$4:$S$8977,7,FALSE) -> 30773 | I425: =VLOOKUP(B425,All!$B$4:$S$8977,8,FALSE) -> 44459 | J425: =VLOOKUP(B425,All!$B$4:$S$8977,9,FALSE) -> Production | K425: =VLOOKUP(B425,All!$B$4:$S$8977,10,FALSE) -> Line 12 | L425: =VLOOKUP(B425,All!$B$4:$S$8977,11,FALSE) -> Sewing operator | M425: =VLOOKUP(B425,All!$B$4:$S$8977,12,FALSE) -> 192 | N425: =VLOOKUP(B425,All!$B$4:$S$8977,13,FALSE) -> 0 | O425: =VLOOKUP(B425,All!$B$4:$S$8977,14,FALSE) -> 0 | P425: =VLOOKUP(B425,All!$B$4:$S$8977,15,FALSE) -> 0 | Q425: =VLOOKUP(B425,All!$B$4:$S$8977,16,FALSE) -> 0 | R425: 7 | S425: 10 | T425: =SUM(M425:S425) -> 209 | Z425: =M425+AH425 -> 194 | AA425: =N425 -> 0 | AB425: =O425 -> 0 | AC425: =P425 -> 0 | AD425: =Q425 -> 0 | AE425: =R425 -> 7 | AF425: =S425 -> 10 | AG425: =SUM(Z425:AF425) -> 211 | AH425: 2 | AI425: 0 | AJ425: 0 | AK425: 0 | AL425: 0 | AM425: 0 | AN425: 0 | AO425: 2
A426: =1+A425 -> 423 | B426: 5146 | C426: =VLOOKUP(B426,All!$B$4:$S$8977,2,FALSE) -> សារីម | D426: =VLOOKUP(B426,All!$B$4:$S$89977,3,FALSE) -> មិថុនា | E426: =VLOOKUP(B426,All!$B$4:$S$8977,4,FALSE) -> SARIM | F426: =VLOOKUP(B426,All!$B$4:$S$8977,5,FALSE) -> MITHONA | G426: =VLOOKUP(B426,All!$B$4:$S$8977,6,FALSE) -> F | H426: =VLOOKUP(B426,All!$B$4:$S$8977,7,FALSE) -> 37775 | I426: =VLOOKUP(B426,All!$B$4:$S$8977,8,FALSE) -> 44460 | J426: =VLOOKUP(B426,All!$B$4:$S$8977,9,FALSE) -> Production | K426: =VLOOKUP(B426,All!$B$4:$S$8977,10,FALSE) -> QC A | L426: =VLOOKUP(B426,All!$B$4:$S$8977,11,FALSE) -> Inspector | M426: =VLOOKUP(B426,All!$B$4:$S$8977,12,FALSE) -> 187 | N426: =VLOOKUP(B426,All!$B$4:$S$8977,13,FALSE) -> 0 | O426: =VLOOKUP(B426,All!$B$4:$S$8977,14,FALSE) -> 0 | P426: =VLOOKUP(B426,All!$B$4:$S$8977,15,FALSE) -> 0 | Q426: =VLOOKUP(B426,All!$B$4:$S$8977,16,FALSE) -> 0 | R426: 7 | S426: 10 | T426: =SUM(M426:S426) -> 204 | Z426: =M426+AH426+5 -> 194 | AA426: =N426 -> 0 | AB426: =O426 -> 0 | AC426: =P426 -> 0 | AD426: =Q426 -> 0 | AE426: =R426 -> 7 | AF426: =S426 -> 10 | AG426: =SUM(Z426:AF426) -> 211 | AH426: 2 | AI426: 0 | AJ426: 0 | AK426: 0 | AL426: 0 | AM426: 0 | AN426: 0 | AO426: 2
A427: =1+A426 -> 424 | B427: 5148 | C427: =VLOOKUP(B427,All!$B$4:$S$8977,2,FALSE) -> ព្រែក | D427: =VLOOKUP(B427,All!$B$4:$S$89977,3,FALSE) -> ដាលីន | E427: =VLOOKUP(B427,All!$B$4:$S$8977,4,FALSE) -> PREK | F427: =VLOOKUP(B427,All!$B$4:$S$8977,5,FALSE) -> DALIN | G427: =VLOOKUP(B427,All!$B$4:$S$8977,6,FALSE) -> F | H427: =VLOOKUP(B427,All!$B$4:$S$8977,7,FALSE) -> 35804 | I427: =VLOOKUP(B427,All!$B$4:$S$8977,8,FALSE) -> 44461 | J427: =VLOOKUP(B427,All!$B$4:$S$8977,9,FALSE) -> Production | K427: =VLOOKUP(B427,All!$B$4:$S$8977,10,FALSE) -> Line 12 | L427: =VLOOKUP(B427,All!$B$4:$S$8977,11,FALSE) -> Sewing operator | M427: =VLOOKUP(B427,All!$B$4:$S$8977,12,FALSE) -> 187 | N427: =VLOOKUP(B427,All!$B$4:$S$8977,13,FALSE) -> 0 | O427: =VLOOKUP(B427,All!$B$4:$S$8977,14,FALSE) -> 0 | P427: =VLOOKUP(B427,All!$B$4:$S$8977,15,FALSE) -> 0 | Q427: =VLOOKUP(B427,All!$B$4:$S$8977,16,FALSE) -> 0 | R427: 7 | S427: 10 | T427: =SUM(M427:S427) -> 204 | Z427: =M427+AH427+5 -> 194 | AA427: =N427 -> 0 | AB427: =O427 -> 0 | AC427: =P427 -> 0 | AD427: =Q427 -> 0 | AE427: =R427 -> 7 | AF427: =S427 -> 10 | AG427: =SUM(Z427:AF427) -> 211 | AH427: 2 | AI427: 0 | AJ427: 0 | AK427: 0 | AL427: 0 | AM427: 0 | AN427: 0 | AO427: 2
A428: =1+A427 -> 425 | B428: 5149 | C428: =VLOOKUP(B428,All!$B$4:$S$8977,2,FALSE) -> ឈឺន | D428: =VLOOKUP(B428,All!$B$4:$S$89977,3,FALSE) -> កូឡាប | E428: =VLOOKUP(B428,All!$B$4:$S$8977,4,FALSE) -> CHHEUN | F428: =VLOOKUP(B428,All!$B$4:$S$8977,5,FALSE) -> KOLAB | G428: =VLOOKUP(B428,All!$B$4:$S$8977,6,FALSE) -> F | H428: =VLOOKUP(B428,All!$B$4:$S$8977,7,FALSE) -> 34111 | I428: =VLOOKUP(B428,All!$B$4:$S$8977,8,FALSE) -> 44461 | J428: =VLOOKUP(B428,All!$B$4:$S$8977,9,FALSE) -> Production | K428: =VLOOKUP(B428,All!$B$4:$S$8977,10,FALSE) -> Line 7 | L428: =VLOOKUP(B428,All!$B$4:$S$8977,11,FALSE) -> Sewing operator | M428: =VLOOKUP(B428,All!$B$4:$S$8977,12,FALSE) -> 187 | N428: =VLOOKUP(B428,All!$B$4:$S$8977,13,FALSE) -> 0 | O428: =VLOOKUP(B428,All!$B$4:$S$8977,14,FALSE) -> 0 | P428: =VLOOKUP(B428,All!$B$4:$S$8977,15,FALSE) -> 0 | Q428: =VLOOKUP(B428,All!$B$4:$S$8977,16,FALSE) -> 0 | R428: 7 | S428: 10 | T428: =SUM(M428:S428) -> 204 | Z428: =M428+AH428+5 -> 194 | AA428: =N428 -> 0 | AB428: =O428 -> 0 | AC428: =P428 -> 0 | AD428: =Q428 -> 0 | AE428: =R428 -> 7 | AF428: =S428 -> 10 | AG428: =SUM(Z428:AF428) -> 211 | AH428: 2 | AI428: 0 | AJ428: 0 | AK428: 0 | AL428: 0 | AM428: 0 | AN428: 0 | AO428: 2
A429: =1+A428 -> 426 | B429: 5150 | C429: =VLOOKUP(B429,All!$B$4:$S$8977,2,FALSE) -> យ៉ុង | D429: =VLOOKUP(B429,All!$B$4:$S$89977,3,FALSE) -> ចន្លា | E429: =VLOOKUP(B429,All!$B$4:$S$8977,4,FALSE) -> YONG | F429: =VLOOKUP(B429,All!$B$4:$S$8977,5,FALSE) -> CHANNA | G429: =VLOOKUP(B429,All!$B$4:$S$8977,6,FALSE) -> F | H429: =VLOOKUP(B429,All!$B$4:$S$8977,7,FALSE) -> 36381 | I429: =VLOOKUP(B429,All!$B$4:$S$8977,8,FALSE) -> 44461 | J429: =VLOOKUP(B429,All!$B$4:$S$8977,9,FALSE) -> Production | K429: =VLOOKUP(B429,All!$B$4:$S$8977,10,FALSE) -> Line 7 | L429: =VLOOKUP(B429,All!$B$4:$S$8977,11,FALSE) -> Sewing operator | M429: =VLOOKUP(B429,All!$B$4:$S$8977,12,FALSE) -> 187 | N429: =VLOOKUP(B429,All!$B$4:$S$8977,13,FALSE) -> 0 | O429: =VLOOKUP(B429,All!$B$4:$S$8977,14,FALSE) -> 0 | P429: =VLOOKUP(B429,All!$B$4:$S$8977,15,FALSE) -> 0 | Q429: =VLOOKUP(B429,All!$B$4:$S$8977,16,FALSE) -> 0 | R429: 7 | S429: 10 | T429: =SUM(M429:S429) -> 204 | Z429: =M429+AH429+5 -> 194 | AA429: =N429 -> 0 | AB429: =O429 -> 0 | AC429: =P429 -> 0 | AD429: =Q429 -> 0 | AE429: =R429 -> 7 | AF429: =S429 -> 10 | AG429: =SUM(Z429:AF429) -> 211 | AH429: 2 | AI429: 0 | AJ429: 0 | AK429: 0 | AL429: 0 | AM429: 0 | AN429: 0 | AO429: 2
